Workbook
Name E14a116802: #REF!

Sheet Capa
A21: Relatório de Contas
A28: =DBase!$C$4 -> 45658

Sheet DBase
A2: PRESSUPOSTOS
B4: Ano: | C4: 45658
B6: Cliente: | C6: Mbolo Yeto
B8: NIF: | C8: 5000861677
C10: =C4 -> 45658 | D10: =C10-1 -> 45657
B12: N.º de Empregados | C12: 1 | D12: 1
B15: BALANÇO EM | E15: Datas de Fecho: | F15: =C4+364 -> 46022
B17: DEMONSTRAÇÃO DE RESULTADOS EM
B19: DEMONSTRAÇÃO DE FLUXOS DE CAIXA EM

Sheet TL
A1: Lançamentos | H1: =(SUM($H$2:$H$5400)-SUM($I$2:$I5401)) -> 0 | I1: =IF((SUM($I$2:$I$65983)-SUM($H$2:$H$65983))<>0,"DEB<>CRE","CONCLUÍDO") -> CONCLUÍDO
A2: Salários | C2: =+C157 -> 0 | D2: Pag_Sal | E2: 4511 | F2: =IF(E2>0,(VLOOKUP(E2,'Blnct AR'!$C$2:$D$2259,2,0))," ") -> Caixa Kwanza | G2: Salários Pagto | I2: 5383905
A3: =+A2 -> Salários | C3: =+C2 -> 0 | D3: =+D2 -> Pag_Sal | E3: 36111 | F3: =IF(E3>0,(VLOOKUP(E3,'Blnct AR'!$C$2:$D$2259,2,0))," ") -> Orgaõs sociais | G3: Salários Pagto | H3: 613350 | I3: 613350
A4: =+A3 -> Salários | C4: =+C3 -> 0 | D4: =+D3 -> Pag_Sal | E4: 36121 | F4: =IF(E4>0,(VLOOKUP(E4,'Blnct AR'!$C$2:$D$2259,2,0))," ") -> Empregados | G4: Salários Pagto | H4: 4034258 | I4: 4034258
A5: =+A4 -> Salários | C5: =+C3 -> 0 | D5: =+D3 -> Pag_Sal | E5: 72211 | F5: =IF(E5>0,(VLOOKUP(E5,'Blnct AR'!$C$2:$D$2259,2,0))," ") -> Ordenados | G5: Salários | H5: 4034258
A6: =+A5 -> Salários | C6: =+C4 -> 0 | D6: =+D4 -> Pag_Sal | E6: 7211 | F6: =IF(E6>0,(VLOOKUP(E6,'Blnct AR'!$C$2:$D$2259,2,0))," ") -> Ordenados | G6: Salários | H6: 613350
A7: =+A6 -> Salários | C7: =+C5 -> 0 | D7: =+D5 -> Pag_Sal | E7: 7214 | F7: =IF(E7>0,(VLOOKUP(E7,'Blnct AR'!$C$2:$D$2259,2,0))," ") -> Subsídio de natal | G7: Salários | H7: 0
A8: =+A7 -> Salários | C8: =+C6 -> 0 | D8: =+D6 -> Pag_Sal | E8: 72215 | F8: =IF(E8>0,(VLOOKUP(E8,'Blnct AR'!$C$2:$D$2259,2,0))," ") -> Subsídio de alimentação | G8: Salários | H8: 0
A9: =+A8 -> Salários | C9: =+C7 -> 0 | D9: =+D7 -> Pag_Sal | E9: 3431 | F9: =IF(E9>0,(VLOOKUP(E9,'Blnct AR'!$C$2:$D$2259,2,0))," ") -> IRT dependentes | G9: Salários IRT | H9: 198706 | I9: 198706
A10: =+A9 -> Salários | C10: =+C9 -> 0 | D10: =+D9 -> Pag_Sal | E10: 3452 | F10: =IF(E10>0,(VLOOKUP(E10,'Blnct AR'!$C$2:$D$2259,2,0))," ") -> IVA - Dedutível | G10: Salários INSS | H10: 127386 | I10: 127386
A11: =+A10 -> Salários | C11: =+C10 -> 0 | D11: =+D10 -> Pag_Sal | E11: 3451 | F11: =IF(E11>0,(VLOOKUP(E11,'Blnct AR'!$C$2:$D$2259,2,0))," ") -> IVA Suportado | G11: Salários INSS | H11: 22500 | I11: 22500
A12: =+A11 -> Salários | C12: =+C11 -> 0 | D12: =+D11 -> Pag_Sal | E12: 3453 | F12: =IF(E12>0,(VLOOKUP(E12,'Blnct AR'!$C$2:$D$2259,2,0))," ") -> IVA - Liquidado | G12: Salários INSS | H12: 387705 | I12: 387705
A13: =+A12 -> Salários | C13: =+C12 -> 0 | D13: =+D12 -> Pag_Sal | E13: 72521 | F13: =IF(E13>0,(VLOOKUP(E13,'Blnct AR'!$C$2:$D$2259,2,0))," ") -> Administrativo/outros | G13: Salários INSS (Trab.) | H13: 149886
A14: =+A13 -> Salários | C14: =+C13 -> 0 | D14: =+D13 -> Pag_Sal | E14: 72521 | F14: =IF(E14>0,(VLOOKUP(E14,'Blnct AR'!$C$2:$D$2259,2,0))," ") -> Administrativo/outros | G14: Salários IRT | H14: 198706
A15: =+A14 -> Salários | C15: =+C14 -> 0 | D15: =+D14 -> Pag_Sal | E15: 72511 | F15: =IF(E15>0,(VLOOKUP(E15,'Blnct AR'!$C$2:$D$2259,2,0))," ") -> #N/A | G15: Salários INSS (Ent.) | H15: 387705
A17: Subs_Natal | C17: =+C16 -> 0 | D17: Pag_Sal | E17: 4511 | F17: =IF(E17>0,(VLOOKUP(E17,'Blnct AR'!$C$2:$D$2259,2,0))," ") -> Caixa Kwanza | G17: Subsidio de Natal Pagto | I17: 20710
A18: =+A17 -> Subs_Natal | C18: =+C17 -> 0 | D18: Pag_Sal | E18: 7213 | F18: =IF(E18>0,(VLOOKUP(E18,'Blnct AR'!$C$2:$D$2259,2,0))," ") -> Subsídio de férias | G18: Subsidio de Natal | H18: 17270
A19: =+A18 -> Subs_Natal | C19: =+C18 -> 0 | D19: =+D18 -> Pag_Sal | E19: 72214 | F19: =IF(E19>0,(VLOOKUP(E19,'Blnct AR'!$C$2:$D$2259,2,0))," ") -> Subsídio de natal | G19: Subsidio de Natal | H19: 3440
A21: Subs_Férias | C21: =+C20 -> 0 | D21: Pag_Sal | E21: 4511 | F21: =IF(E21>0,(VLOOKUP(E21,'Blnct AR'!$C$2:$D$2259,2,0))," ") -> Caixa Kwanza | G21: Subsidio de Natal Pagto | I21: 20710
A22: =+A21 -> Subs_Férias | C22: =+C21 -> 0 | D22: Pag_Sal | E22: 7212 | F22: =IF(E22>0,(VLOOKUP(E22,'Blnct AR'!$C$2:$D$2259,2,0))," ") -> Subsídio de férias | G22: Subsidio de Férias | H22: 17270
A23: =+A22 -> Subs_Férias | C23: =+C22 -> 0 | D23: =+D22 -> Pag_Sal | E23: 72213 | F23: =IF(E23>0,(VLOOKUP(E23,'Blnct AR'!$C$2:$D$2259,2,0))," ") -> Subsídio de férias | G23: Subsidio de Férias | H23: 3440
F24: =IF(E24>0,(VLOOKUP(E24,'Blnct AR'!$C$2:$D$2259,2,0))," ")
A25: Imp_Selo | C25: =+C162 -> 0 | D25: Imp_Selo | E25: 34731334 | F25: =IF(E25>0,(VLOOKUP(E25,'Blnct AR'!$C$2:$D$2259,2,0))," ") -> IS - recibos outros | G25: Liquidação Imp. Selo | H25: 5000 | I25: 5000
A26: =+A25 -> Imp_Selo | C26: =+C25 -> 0 | D26: Imp_Selo | E26: 75311 | F26: =IF(E26>0,(VLOOKUP(E26,'Blnct AR'!$C$2:$D$2259,2,0))," ") -> Imposto de selo | G26: Liquidação Imp. Selo | H26: 5000
A27: =+A26 -> Imp_Selo | C27: =+C26 -> 0 | D27: Imp_Selo | E27: 4511 | F27: =IF(E27>0,(VLOOKUP(E27,'Blnct AR'!$C$2:$D$2259,2,0))," ") -> Caixa Kwanza | G27: Liquidação Imp. Selo | I27: 5000
F28: =IF(E28>0,(VLOOKUP(E28,'Blnct AR'!$C$2:$D$2259,2,0))," ")
A29: Tel_Net | C29: =+C28 -> 0 | D29: Dsp_FST | E29: 4511 | F29: =IF(E29>0,(VLOOKUP(E29,'Blnct AR'!$C$2:$D$2259,2,0))," ") -> Caixa Kwanza | G29: UNITEL Recarga | I29: 4500
A30: =+A29 -> Tel_Net | C30: =+C29 -> 0 | D30: Dsp_FST | E30: 75220 | F30: =IF(E30>0,(VLOOKUP(E30,'Blnct AR'!$C$2:$D$2259,2,0))," ") -> Comunicação | G30: UNITEL Recarga | H30: 4286
A31: =+A30 -> Tel_Net | C31: =+C30 -> 0 | D31: Dsp_FST | E31: 342121 | F31: =IF(E31>0,(VLOOKUP(E31,'Blnct AR'!$C$2:$D$2259,2,0))," ") -> IPC-LIQ.-PR.SERV.-TXRED-MERC. NAC. | G31: UNITEL Recarga | H31: 214 | I31: 214
A32: =+A31 -> Tel_Net | C32: =+C31 -> 0 | D32: Dsp_FST | E32: 75312 | F32: =IF(E32>0,(VLOOKUP(E32,'Blnct AR'!$C$2:$D$2259,2,0))," ") -> Imposto de Produção e Consumo | G32: UNITEL Recarga | H32: 214
F33: =IF(E33>0,(VLOOKUP(E33,'Blnct AR'!$C$2:$D$2259,2,0))," ")
A34: Gasolina | C34: =+C54 -> 0 | D34: Dsp_FST | E34: 4511 | F34: =IF(E34>0,(VLOOKUP(E34,'Blnct AR'!$C$2:$D$2259,2,0))," ") -> Caixa Kwanza | G34: Gasolina | I34: 5000
A35: =+A34 -> Gasolina | C35: =+C34 -> 0 | D35: Dsp_FST | E35: 752132 | F35: =IF(E35>0,(VLOOKUP(E35,'Blnct AR'!$C$2:$D$2259,2,0))," ") -> Gasolina | G35: Gasolina | H35: 5000
A37: Gás | C37: =+C57 -> 0 | D37: Dsp_FST | E37: 4511 | F37: =IF(E37>0,(VLOOKUP(E37,'Blnct AR'!$C$2:$D$2259,2,0))," ") -> Caixa Kwanza | G37: Gás | I37: 5000
A38: =+A37 -> Gás | C38: =+C37 -> 0 | D38: Dsp_FST | E38: 752133 | F38: =IF(E38>0,(VLOOKUP(E38,'Blnct AR'!$C$2:$D$2259,2,0))," ") -> Gás | G38: Gás | H38: 5000
A40: Água | C40: =+C57 -> 0 | D40: Dsp_FST | E40: 4511 | F40: =IF(E40>0,(VLOOKUP(E40,'Blnct AR'!$C$2:$D$2259,2,0))," ") -> Caixa Kwanza | G40: Água | I40: 5000
A41: =+A40 -> Água | C41: =+C40 -> 0 | D41: Dsp_FST | E41: 75211 | F41: =IF(E41>0,(VLOOKUP(E41,'Blnct AR'!$C$2:$D$2259,2,0))," ") -> Água | G41: Água | H41: 5000
A43: Eletricidade | C43: =+C63 -> 0 | D43: Dsp_FST | E43: 4511 | F43: =IF(E43>0,(VLOOKUP(E43,'Blnct AR'!$C$2:$D$2259,2,0))," ") -> Caixa Kwanza | G43: Eletricidade | I43: 5500
A44: =+A43 -> Eletricidade | C44: =+C43 -> 0 | D44: Dsp_FST | E44: 75212 | F44: =IF(E44>0,(VLOOKUP(E44,'Blnct AR'!$C$2:$D$2259,2,0))," ") -> Electricidade | G44: Eletricidade | H44: 5500
F45: =IF(E45>0,(VLOOKUP(E45,'Blnct AR'!$C$2:$D$2259,2,0))," ")
A46: Outras Desp. | C46: =+C45 -> 0 | D46: Dsp_FST | E46: 4511 | F46: =IF(E46>0,(VLOOKUP(E46,'Blnct AR'!$C$2:$D$2259,2,0))," ") -> Caixa Kwanza | G46: Pagamento Diversos | I46: 3500
A47: =+A46 -> Outras Desp. | C47: =+C46 -> 0 | D47: Dsp_FST | E47: 75219 | F47: =IF(E47>0,(VLOOKUP(E47,'Blnct AR'!$C$2:$D$2259,2,0))," ") -> Outros fornecimentos | G47: Pagamento Diversos | H47: 3500
F48: =IF(E48>0,(VLOOKUP(E48,'Blnct AR'!$C$2:$D$2259,2,0))," ")
A49: Limpeza | C49: =+C48 -> 0 | D49: Dsp_FST | E49: 4511 | F49: =IF(E49>0,(VLOOKUP(E49,'Blnct AR'!$C$2:$D$2259,2,0))," ") -> Caixa Kwanza | G49: Compra Mat. Limp. Hig. | I49: 159
A50: =+A49 -> Limpeza | C50: =+C49 -> 0 | D50: Dsp_FST | E50: 75228 | F50: =IF(E50>0,(VLOOKUP(E50,'Blnct AR'!$C$2:$D$2259,2,0))," ") -> Limpeza, higiene e conforto | G50: Compra Mat. Limp. Hig. | H50: 159
A52: PrtSegConf | C52: =+C51 -> 0 | D52: Dsp_FST | E52: 4511 | F52: =IF(E52>0,(VLOOKUP(E52,'Blnct AR'!$C$2:$D$2259,2,0))," ") -> Caixa Kwanza | G52: Compra Mat. PrtSegConf | I52: 159
A53: =+A52 -> PrtSegConf | C53: =+C52 -> 0 | D53: Dsp_FST | E53: 75215 | F53: =IF(E53>0,(VLOOKUP(E53,'Blnct AR'!$C$2:$D$2259,2,0))," ") -> Material protecção, seg.e conforto | G53: Compra Mat. PrtSegConf | H53: 159
F54: =IF(E54>0,(VLOOKUP(E54,'Blnct AR'!$C$2:$D$2259,2,0))," ")
A55: Recargas | C55: =+C54 -> 0 | D55: Dsp_FST | E55: 4511 | F55: =IF(E55>0,(VLOOKUP(E55,'Blnct AR'!$C$2:$D$2259,2,0))," ") -> Caixa Kwanza | G55: Recargas | I55: 12680
A56: =+A55 -> Recargas | C56: =+C55 -> 0 | D56: Dsp_FST | E56: 75220 | F56: =IF(E56>0,(VLOOKUP(E56,'Blnct AR'!$C$2:$D$2259,2,0))," ") -> Comunicação | G56: Recargas | H56: 12680
F57: =IF(E57>0,(VLOOKUP(E57,'Blnct AR'!$C$2:$D$2259,2,0))," ")
A58: Rest_Hotel | C58: =+C57 -> 0 | D58: Dsp_FST | E58: 4511 | F58: =IF(E58>0,(VLOOKUP(E58,'Blnct AR'!$C$2:$D$2259,2,0))," ") -> Caixa Kwanza | G58: Despesas Diversas | I58: 1000
A59: =+A58 -> Rest_Hotel | C59: =+C58 -> 0 | D59: Dsp_FST | E59: 75223 | F59: =IF(E59>0,(VLOOKUP(E59,'Blnct AR'!$C$2:$D$2259,2,0))," ") -> Deslocações e estadas | G59: Despesas Diversas | H59: =+I58 -> 1000
A61: Representação | C61: =+C60 -> 0 | D61: Dsp_FST | E61: 4511 | F61: =IF(E61>0,(VLOOKUP(E61,'Blnct AR'!$C$2:$D$2259,2,0))," ") -> Caixa Kwanza | G61: Despesas Diversas | I61: 1000
A62: =+A61 -> Representação | C62: =+C61 -> 0 | D62: Dsp_FST | E62: 75224 | F62: =IF(E62>0,(VLOOKUP(E62,'Blnct AR'!$C$2:$D$2259,2,0))," ") -> Despesas de representação | G62: Despesas Diversas | H62: 1000
F63: =IF(E63>0,(VLOOKUP(E63,'Blnct AR'!$C$2:$D$2259,2,0))," ")
A64: Publicidade | C64: =+C63 -> 0 | D64: Dsp_FST | E64: 4511 | F64: =IF(E64>0,(VLOOKUP(E64,'Blnct AR'!$C$2:$D$2259,2,0))," ") -> Caixa Kwanza | G64: Despesas Diversas | I64: 8000
A65: =+A64 -> Publicidade | C65: =+C64 -> 0 | D65: Dsp_FST | E65: 75229 | F65: =IF(E65>0,(VLOOKUP(E65,'Blnct AR'!$C$2:$D$2259,2,0))," ") -> Publicidade e propaganda | G65: Despesas Diversas | H65: 8000
F66: =IF(E66>0,(VLOOKUP(E66,'Blnct AR'!$C$2:$D$2259,2,0))," ")
A67: Ferramentas | C67: =+C66 -> 0 | D67: Dsp_FST | E67: 4511 | F67: =IF(E67>0,(VLOOKUP(E67,'Blnct AR'!$C$2:$D$2259,2,0))," ") -> Caixa Kwanza | G67: Despesas Diversas | I67: 4299
A68: =+A67 -> Ferramentas | C68: =+C67 -> 0 | D68: Dsp_FST | E68: 75216 | F68: =IF(E68>0,(VLOOKUP(E68,'Blnct AR'!$C$2:$D$2259,2,0))," ") -> Ferrament.e utensílios desg.rápido | G68: Despesas Diversas | H68: 4299
F69: =IF(E69>0,(VLOOKUP(E69,'Blnct AR'!$C$2:$D$2259,2,0))," ")
A70: Gasoleo | C70: =+C69 -> 0 | D70: Dsp_FST | E70: 4511 | F70: =IF(E70>0,(VLOOKUP(E70,'Blnct AR'!$C$2:$D$2259,2,0))," ") -> Caixa Kwanza | G70: Gasoleo | I70: 15350
A71: =+A70 -> Gasoleo | C71: =+C70 -> 0 | D71: Dsp_FST | E71: 752131 | F71: =IF(E71>0,(VLOOKUP(E71,'Blnct AR'!$C$2:$D$2259,2,0))," ") -> Gasoleo | G71: Gasoleo | H71: 15350
F72: =IF(E72>0,(VLOOKUP(E72,'Blnct AR'!$C$2:$D$2259,2,0))," ")
A73: Mat_Contrução | C73: =+C72 -> 0 | D73: Dsp_FST | E73: 752142 | F73: =IF(E73>0,(VLOOKUP(E73,'Blnct AR'!$C$2:$D$2259,2,0))," ") -> Edifícios e outras construções | G73: Mat. Const. Divrs | H73: 13779.4
A74: =+A73 -> Mat_Contrução | C74: =+C73 -> 0 | D74: =+D73 -> Dsp_FST | E74: 4511 | F74: =IF(E74>0,(VLOOKUP(E74,'Blnct AR'!$C$2:$D$2259,2,0))," ") -> Caixa Kwanza | G74: Mat. Const. Divrs | I74: 13779.4
F75: =IF(E75>0,(VLOOKUP(E75,'Blnct AR'!$C$2:$D$2259,2,0))," ")
A76: Obras | C76: =+C75 -> 0 | D76: Dsp_FST | E76: 752262 | F76: =IF(E76>0,(VLOOKUP(E76,'Blnct AR'!$C$2:$D$2259,2,0))," ") -> Edifícios e outras construções | G76: Mão-de-obra 3º | H76: 0
A77: =+A76 -> Obras | C77: =+C76 -> 0 | D77: =+D76 -> Dsp_FST | E77: 4511 | F77: =IF(E77>0,(VLOOKUP(E77,'Blnct AR'!$C$2:$D$2259,2,0))," ") -> Caixa Kwanza | G77: Mão-de-obra 3º | I77: 0
A79: Revisões | C79: =+C75 -> 0 | D79: Dsp_FST | E79: 4511 | F79: =IF(E79>0,(VLOOKUP(E79,'Blnct AR'!$C$2:$D$2259,2,0))," ") -> Caixa Kwanza | G79: Revisões Viaturas | I79: 10000
A80: =+A79 -> Revisões | C80: =+C79 -> 0 | D80: =+D79 -> Dsp_FST | E80: 752144 | F80: =IF(E80>0,(VLOOKUP(E80,'Blnct AR'!$C$2:$D$2259,2,0))," ") -> Equipamento de carga e transporte | G80: Revisões Viaturas material | H80: 7000
A81: =+A80 -> Revisões | C81: =+C80 -> 0 | D81: Dsp_FST | E81: 752264 | F81: =IF(E81>0,(VLOOKUP(E81,'Blnct AR'!$C$2:$D$2259,2,0))," ") -> Equipamento de carga e transporte | G81: Revisões Viaturas mão-de-obra | H81: 3000
A83: Outr_Mat | C83: =+C82 -> 0 | D83: Dsp_FST | E83: 752149 | F83: =IF(E83>0,(VLOOKUP(E83,'Blnct AR'!$C$2:$D$2259,2,0))," ") -> Outras | G83: Mat. Divrs | H83: 70700
A84: =+A83 -> Outr_Mat | C84: =+C83 -> 0 | D84: =+D83 -> Dsp_FST | E84: 4511 | F84: =IF(E84>0,(VLOOKUP(E84,'Blnct AR'!$C$2:$D$2259,2,0))," ") -> Caixa Kwanza | G84: Mat. Divrs | I84: 70700
A86: Alimentação | C86: 0 | D86: Dsp_FST | E86: 752191 | F86: Alimentação Pessoal | G86: Compra Alimentos | H86: 13779.4
A87: Alimentação | C87: 0 | D87: Dsp_FST | E87: 4511 | F87: Caixa Kwanza | G87: Compra Alimentos | I87: 13779.4
F88: =IF(E88>0,(VLOOKUP(E88,'Blnct AR'!$C$2:$D$2259,2,0))," ")
A89: Mat_Escrt | C89: =+C88 -> 0 | D89: Dsp_FST | E89: 4511 | F89: =IF(E89>0,(VLOOKUP(E89,'Blnct AR'!$C$2:$D$2259,2,0))," ") -> Caixa Kwanza | G89: Compra diversos estritório | I89: 1000
A90: =+A89 -> Mat_Escrt | C90: =+C89 -> 0 | D90: Dsp_FST | E90: 75217 | F90: =IF(E90>0,(VLOOKUP(E90,'Blnct AR'!$C$2:$D$2259,2,0))," ") -> Material de escritório | G90: Compra diversos estritório | H90: 1000
A92: Eqpt_Adm | C92: =+C91 -> 0 | D92: Dsp_FST | E92: 4511 | F92: =IF(E92>0,(VLOOKUP(E92,'Blnct AR'!$C$2:$D$2259,2,0))," ") -> Caixa Kwanza | G92: Compra diversos | I92: 589
A93: =+A92 -> Eqpt_Adm | C93: =+C92 -> 0 | D93: Dsp_FST | E93: 752145 | F93: =IF(E93>0,(VLOOKUP(E93,'Blnct AR'!$C$2:$D$2259,2,0))," ") -> Equipamento administrativo | G93: Compra diversos | H93: 589
A95: Contabilidade | C95: =+C94 -> 0 | D95: Dsp_FST | E95: 4511 | F95: =IF(E95>0,(VLOOKUP(E95,'Blnct AR'!$C$2:$D$2259,2,0))," ") -> Caixa Kwanza | G95: Contabilidade | I95: 75000
A96: =+A95 -> Contabilidade | C96: =+C95 -> 0 | D96: Dsp_FST | E96: 75325 | F96: =IF(E96>0,(VLOOKUP(E96,'Blnct AR'!$C$2:$D$2259,2,0))," ") -> Serviços contabilisticos | G96: Contabilidade | H96: 75000
A98: Rendas | C98: =+C97 -> 0 | D98: Dsp_FST | E98: 4511 | F98: =IF(E98>0,(VLOOKUP(E98,'Blnct AR'!$C$2:$D$2259,2,0))," ") -> Caixa Kwanza | G98: Renda Instalações | I98: 237500
A99: =+A98 -> Rendas | C99: =+C98 -> 0 | D99: Dsp_FST | E99: 752211 | F99: =IF(E99>0,(VLOOKUP(E99,'Blnct AR'!$C$2:$D$2259,2,0))," ") -> Rendas de imóveis Prefor | G99: Renda Instalações | H99: 237500
A101: Cpr_ViatPes | C101: =+C100 -> 0 | D101: Cmpr_Imo | E101: 4511 | F101: =IF(E101>0,(VLOOKUP(E101,'Blnct AR'!$C$2:$D$2259,2,0))," ") -> Caixa Kwanza | G101: Compra Camião | I101: 75000
A102: =+A101 -> Cpr_ViatPes | C102: =+C101 -> 0 | D102: =+D101 -> Cmpr_Imo | E102: 1141 | F102: =IF(E102>0,(VLOOKUP(E102,'Blnct AR'!$C$2:$D$2259,2,0))," ") -> Veiculos pesados | G102: Compra Camião | H102: 75000
A104: Cpr_ViatLig | C104: =+C103 -> 0 | D104: Cmpr_Imo | E104: 4511 | F104: =IF(E104>0,(VLOOKUP(E104,'Blnct AR'!$C$2:$D$2259,2,0))," ") -> Caixa Kwanza | G104: Compra Automóvel | I104: 75000
A105: =+A104 -> Cpr_ViatLig | C105: =+C104 -> 0 | D105: =+D104 -> Cmpr_Imo | E105: 1142 | F105: =IF(E105>0,(VLOOKUP(E105,'Blnct AR'!$C$2:$D$2259,2,0))," ") -> Veiculos mistos e ligeiros | G105: Compra Automóvel | H105: 75000
A107: Imobilizado | C107: =+C106 -> 0 | D107: Amrtz_Imo | E107: 7314 | F107: =IF(E107>0,(VLOOKUP(E107,'Blnct AR'!$C$2:$D$2259,2,0))," ") -> Equipamento de carga e transporte | G107: Amortização Sinotruck | H107: 75000
A108: =+A107 -> Imobilizado | C108: =+C107 -> 0 | D108: =+D107 -> Amrtz_Imo | E108: 1814 | F108: =IF(E108>0,(VLOOKUP(E108,'Blnct AR'!$C$2:$D$2259,2,0))," ") -> Equipamento de carga e transporte | G108: Amortização Sinotruck | I108: 75000
A110: Alg_TPA | C110: =+C100 -> 0 | D110: Conc_Bnk_CxAng | E110: 43106 | F110: =IF(E110>0,(VLOOKUP(E110,'Blnct AR'!$C$2:$D$2260,2,0))," ") -> Banco BIC - 118133685.15.1 | G110: Aluguer TPA | I110: 3500
A111: =+A110 -> Alg_TPA | C111: =+C110 -> 0 | D111: =+D110 -> Conc_Bnk_CxAng | E111: 7678 | F111: =IF(E111>0,(VLOOKUP(E111,'Blnct AR'!$C$2:$D$2260,2,0))," ") -> Sb - outros | G111: Aluguer TPA | H111: 3500
A113: Cheques | C113: =+C112 -> 0 | D113: Conc_Bnk_CxAng | E113: 43106 | F113: =IF(E113>0,(VLOOKUP(E113,'Blnct AR'!$C$2:$D$2260,2,0))," ") -> Banco BIC - 118133685.15.1 | G113: Livro de cheques | I113: 4000
A114: =+A113 -> Cheques | C114: =+C113 -> 0 | D114: =+D113 -> Conc_Bnk_CxAng | E114: 7671 | F114: =IF(E114>0,(VLOOKUP(E114,'Blnct AR'!$C$2:$D$2260,2,0))," ") -> Sb - livros bancarios | G114: Livro de cheques | H114: 4000
A116: Imp_Selo_Bnk | C116: =+C115 -> 0 | D116: Conc_Bnk_CxAng | E116: 43106 | F116: =IF(E116>0,(VLOOKUP(E116,'Blnct AR'!$C$2:$D$2260,2,0))," ") -> Banco BIC - 118133685.15.1 | G116: Imposto selo | I116: 601.5
A117: =+A116 -> Imp_Selo_Bnk | C117: =+C116 -> 0 | D117: =+D116 -> Conc_Bnk_CxAng | E117: 34731334 | F117: =IF(E117>0,(VLOOKUP(E117,'Blnct AR'!$C$2:$D$2260,2,0))," ") -> IS - recibos outros | G117: Imposto selo | H117: 601.5 | I117: 601.5
A118: =+A117 -> Imp_Selo_Bnk | C118: =+C117 -> 0 | D118: =+D117 -> Conc_Bnk_CxAng | E118: 75311 | F118: =IF(E118>0,(VLOOKUP(E118,'Blnct AR'!$C$2:$D$2260,2,0))," ") -> Imposto de selo | G118: Imposto selo | H118: 601.5
A120: Acrt_Sld | C120: =+C119 -> 0 | D120: Conc_Bnk_CxAng | E120: 43106 | F120: =IF(E120>0,(VLOOKUP(E120,'Blnct AR'!$C$2:$D$2260,2,0))," ") -> Banco BIC - 118133685.15.1 | G120: Acerto Saldo | H120: 716515.05
...

Sheet Diários
A1: Lançamentos | H1: =(SUM($H$2:$H$5345)-SUM($I$2:$I5346)) -> 0 | I1: =IF((SUM($I$2:$I$65928)-SUM($H$2:$H$65928))<>0,"DEB<>CRE","CONCLUÍDO") -> CONCLUÍDO
A2: 21 Caixa | C2: =+C128 -> 0 | D2: Pgto | E2: 4511 | F2: =IF(E2>0,(VLOOKUP(E2,'Blnct AR'!$C$2:$D$2259,2,0))," ") -> Caixa Kwanza | G2: Pgto Taxas | I2: 0
A3: =+A2 -> 21 Caixa | C3: =+C2 -> 0 | D3: =+D2 -> Pgto | E3: 75329 | F3: =IF(E3>0,(VLOOKUP(E3,'Blnct AR'!$C$2:$D$2259,2,0))," ") -> Outros impostos | G3: =+G2 -> Pgto Taxas | H3: =I2 -> 0
A5: 21 Caixa | C5: =+C131 -> 0 | D5: Rcbto | E5: 4511 | F5: =IF(E5>0,(VLOOKUP(E5,'Blnct AR'!$C$2:$D$2259,2,0))," ") -> Caixa Kwanza | G5: Rcbto Empréstimo | H5: 0
A6: =+A5 -> 21 Caixa | C6: =+C5 -> 0 | D6: =+D5 -> Rcbto | E6: 33921 | F6: =IF(E6>0,(VLOOKUP(E6,'Blnct AR'!$C$2:$D$2259,2,0))," ") -> Entidade grupo | G6: =+G5 -> Rcbto Empréstimo | I6: =H5 -> 0
A8: 21 Caixa | C8: =+C129 -> 0 | D8: INSS | E8: 4511 | F8: =IF(E8>0,(VLOOKUP(E8,'Blnct AR'!$C$2:$D$2259,2,0))," ") -> Caixa Kwanza | G8: Pgto INSS | I8: 0
A9: =+A8 -> 21 Caixa | C9: =+C8 -> 0 | D9: =+D8 -> INSS | E9: 3452 | F9: =IF(E9>0,(VLOOKUP(E9,'Blnct AR'!$C$2:$D$2259,2,0))," ") -> IVA - Dedutível | G9: =+G8 -> Pgto INSS | H9: =I8 -> 0
F10: =IF(E10>0,(VLOOKUP(E10,'Blnct AR'!$C$2:$D$2259,2,0))," ")
A11: 21 Caixa | C11: 0 | D11: IRT | E11: 4511 | F11: =IF(E11>0,(VLOOKUP(E11,'Blnct AR'!$C$2:$D$2259,2,0))," ") -> Caixa Kwanza | G11: Pgto IRT | I11: 0
A12: =+A11 -> 21 Caixa | C12: 0 | D12: =+D11 -> IRT | E12: 3431 | F12: =IF(E12>0,(VLOOKUP(E12,'Blnct AR'!$C$2:$D$2259,2,0))," ") -> IRT dependentes | G12: =+G11 -> Pgto IRT | H12: =I11 -> 0
F13: =IF(E13>0,(VLOOKUP(E13,'Blnct AR'!$C$2:$D$2259,2,0))," ")
A14: 21 Caixa | C14: 0 | D14: IPC | E14: 4511 | F14: =IF(E14>0,(VLOOKUP(E14,'Blnct AR'!$C$2:$D$2259,2,0))," ") -> Caixa Kwanza | G14: Pgto IPC | I14: 0
A15: =+A14 -> 21 Caixa | C15: 0 | D15: =+D14 -> IPC | E15: 75312 | F15: =IF(E15>0,(VLOOKUP(E15,'Blnct AR'!$C$2:$D$2259,2,0))," ") -> Imposto de Produção e Consumo | G15: =+G14 -> Pgto IPC | H15: =I14 -> 0
F16: =IF(E16>0,(VLOOKUP(E16,'Blnct AR'!$C$2:$D$2259,2,0))," ")
A17: 21 Caixa | C17: =+C48 -> 0 | D17: Imp_Selo | E17: 4511 | F17: =IF(E17>0,(VLOOKUP(E17,'Blnct AR'!$C$2:$D$2259,2,0))," ") -> Caixa Kwanza | G17: Pgto Imposto Selo | I17: 0
A18: =+A17 -> 21 Caixa | C18: =+C17 -> 0 | D18: =+D17 -> Imp_Selo | E18: 75311 | F18: =IF(E18>0,(VLOOKUP(E18,'Blnct AR'!$C$2:$D$2259,2,0))," ") -> Imposto de selo | G18: =+G17 -> Pgto Imposto Selo | H18: =+I17 -> 0
A20: 21 Caixa | C20: =+C50 -> 0 | D20: IsL 2% | E20: 4511 | F20: =IF(E20>0,(VLOOKUP(E20,'Blnct AR'!$C$2:$D$2259,2,0))," ") -> Caixa Kwanza | G20: Pgto IsL 2% | I20: 0
A21: =+A20 -> 21 Caixa | C21: =+C20 -> 0 | D21: =+D20 -> IsL 2% | E21: 3412 | F21: =IF(E21>0,(VLOOKUP(E21,'Blnct AR'!$C$2:$D$2259,2,0))," ") -> IL- pagamentos por conta | G21: =+G20 -> Pgto IsL 2% | H21: =+I20 -> 0
A23: 21 Caixa | C23: =+C50 -> 0 | D23: Rf_6,5% | E23: 4511 | F23: =IF(E23>0,(VLOOKUP(E23,'Blnct AR'!$C$2:$D$2259,2,0))," ") -> Caixa Kwanza | G23: Pgto Rf Fornecedor | I23: 0
A24: =+A23 -> 21 Caixa | C24: =+C23 -> 0 | D24: Dsp_FST | E24: 34131 | F24: =IF(E24>0,(VLOOKUP(E24,'Blnct AR'!$C$2:$D$2259,2,0))," ") -> Rf - juros bancarios | G24: =+G23 -> Pgto Rf Fornecedor | H24: =+I23 -> 0
A26: 31 Bancos | C26: =+C55 -> 0 | D26: Rcbto | E26: 43102 | F26: =IF(E26>0,(VLOOKUP(E26,'Blnct AR'!$C$2:$D$2259,2,0))," ") -> Banco - BECN. nº 0000984586 | G26: Recibo Cliente | H26: 0
A27: =+A26 -> 31 Bancos | C27: =+C26 -> 0 | D27: =+D26 -> Rcbto | E27: 31121008 | F27: =IF(E27>0,(VLOOKUP(E27,'Blnct AR'!$C$2:$D$2259,2,0))," ") -> Mota-Engil Angola,S.A | G27: =+G26 -> Recibo Cliente | I27: =+H26 -> 0
A29: 31 Bancos | C29: =+C58 -> 0 | D29: Dep_Num | E29: 43102 | F29: =IF(E29>0,(VLOOKUP(E29,'Blnct AR'!$C$2:$D$2259,2,0))," ") -> Banco - BECN. nº 0000984586 | G29: Depósito Numerário | H29: 0
A30: =+A29 -> 31 Bancos | C30: =+C29 -> 0 | D30: =+D29 -> Dep_Num | E30: 4511 | F30: =IF(E30>0,(VLOOKUP(E30,'Blnct AR'!$C$2:$D$2259,2,0))," ") -> Caixa Kwanza | G30: =+G29 -> Depósito Numerário | I30: =+H29 -> 0
A32: 31 Bancos | C32: =+C58 -> 0 | D32: Adtmto | E32: 43102 | F32: =IF(E32>0,(VLOOKUP(E32,'Blnct AR'!$C$2:$D$2259,2,0))," ") -> Banco - BECN. nº 0000984586 | G32: Adiantamento Cliente Cliente | H32: 0
A33: =+A32 -> 31 Bancos | C33: =+C32 -> 0 | D33: =+D32 -> Adtmto | E33: 319121001 | F33: =IF(E33>0,(VLOOKUP(E33,'Blnct AR'!$C$2:$D$2259,2,0))," ") -> Topoduarte Topografia e Imob, Lda | G33: =+G32 -> Adiantamento Cliente Cliente | I33: =+H32 -> 0
A35: 31 Bancos | C35: =+C34 -> 0 | D35: Dsp_Bnk | E35: 43102 | F35: =IF(E35>0,(VLOOKUP(E35,'Blnct AR'!$C$2:$D$2259,2,0))," ") -> Banco - BECN. nº 0000984586 | G35: Despesas Bancárias | I35: =SUM(H36:H38) -> 0
A36: =+A35 -> 31 Bancos | C36: =+C35 -> 0 | D36: =+D35 -> Dsp_Bnk | E36: 7673 | F36: =IF(E36>0,(VLOOKUP(E36,'Blnct AR'!$C$2:$D$2259,2,0))," ") -> Despesas Bancárias | G36: =+G35 -> Despesas Bancárias | H36: 0
A37: =+A36 -> 31 Bancos | C37: =+C36 -> 0 | D37: =+D36 -> Dsp_Bnk | E37: 7674 | F37: =IF(E37>0,(VLOOKUP(E37,'Blnct AR'!$C$2:$D$2259,2,0))," ") -> #N/A | G37: =+G36 -> Despesas Bancárias | H37: =H36*0.7% -> 0
A38: =+A37 -> 31 Bancos | C38: =+C37 -> 0 | D38: =+D37 -> Dsp_Bnk | E38: 7675 | F38: =IF(E38>0,(VLOOKUP(E38,'Blnct AR'!$C$2:$D$2259,2,0))," ") -> #N/A | G38: =+G37 -> Despesas Bancárias | H38: 0
F39: =IF(E39>0,(VLOOKUP(E39,'Blnct AR'!$C$2:$D$2259,2,0))," ")
A40: 31 Bancos | C40: =+C39 -> 0 | D40: Chq_Bnk | E40: 43102 | F40: =IF(E40>0,(VLOOKUP(E40,'Blnct AR'!$C$2:$D$2259,2,0))," ") -> Banco - BECN. nº 0000984586 | G40: Emissão Cheques | I40: =SUM(H41:H44) -> 0
A41: =+A40 -> 31 Bancos | C41: =+C40 -> 0 | D41: =+D40 -> Chq_Bnk | E41: 7671 | F41: =IF(E41>0,(VLOOKUP(E41,'Blnct AR'!$C$2:$D$2259,2,0))," ") -> Sb - livros bancarios | G41: =+G40 -> Emissão Cheques | H41: 0
A42: =+A41 -> 31 Bancos | C42: =+C41 -> 0 | D42: =+D41 -> Chq_Bnk | E42: 7674 | F42: =IF(E42>0,(VLOOKUP(E42,'Blnct AR'!$C$2:$D$2259,2,0))," ") -> #N/A | G42: =+G41 -> Emissão Cheques | H42: 0
A43: =+A42 -> 31 Bancos | C43: =+C42 -> 0 | D43: =+D42 -> Chq_Bnk | E43: 7674 | F43: =IF(E43>0,(VLOOKUP(E43,'Blnct AR'!$C$2:$D$2259,2,0))," ") -> #N/A | G43: =+G42 -> Emissão Cheques | H43: 0
A44: =+A42 -> 31 Bancos | C44: =+C42 -> 0 | D44: =+D42 -> Chq_Bnk | E44: 7675 | F44: =IF(E44>0,(VLOOKUP(E44,'Blnct AR'!$C$2:$D$2259,2,0))," ") -> #N/A | G44: =+G42 -> Emissão Cheques | H44: 0
A46: 31 Bancos | C46: =+C45 -> 0 | D46: Cms_Bnk | E46: 43105 | F46: =IF(E46>0,(VLOOKUP(E46,'Blnct AR'!$C$2:$D$2259,2,0))," ") -> Banco Valor- 00022736510001 | G46: Comissão | I46: =SUM(H47:H49) -> 2016
A47: =+A46 -> 31 Bancos | C47: =+C46 -> 0 | D47: =+D46 -> Cms_Bnk | E47: 7672 | F47: =IF(E47>0,(VLOOKUP(E47,'Blnct AR'!$C$2:$D$2259,2,0))," ") -> Sb - importação e exportação | G47: =+G46 -> Comissão | H47: 2000
A48: =+A47 -> 31 Bancos | C48: =+C47 -> 0 | D48: =+D47 -> Cms_Bnk | E48: 7674 | F48: =IF(E48>0,(VLOOKUP(E48,'Blnct AR'!$C$2:$D$2259,2,0))," ") -> #N/A | G48: =+G47 -> Comissão | H48: 14
A49: =+A48 -> 31 Bancos | C49: =+C48 -> 0 | D49: =+D48 -> Cms_Bnk | E49: 7675 | F49: =IF(E49>0,(VLOOKUP(E49,'Blnct AR'!$C$2:$D$2259,2,0))," ") -> #N/A | G49: =+G48 -> Comissão | H49: 2
F50: =IF(E50>0,(VLOOKUP(E50,'Blnct AR'!$C$2:$D$2259,2,0))," ")
A51: 31 Bancos | C51: =+C50 -> 0 | D51: Chq_Cx | E51: 43102 | F51: =IF(E51>0,(VLOOKUP(E51,'Blnct AR'!$C$2:$D$2259,2,0))," ") -> Banco - BECN. nº 0000984586 | G51: Cheque de caixa | I51: 2000000
A52: =+A51 -> 31 Bancos | C52: =+C51 -> 0 | D52: Chq_Cx | E52: 4511 | F52: =IF(E52>0,(VLOOKUP(E52,'Blnct AR'!$C$2:$D$2259,2,0))," ") -> Caixa Kwanza | G52: =+G51 -> Cheque de caixa | H52: =+I51 -> 2000000
A53: =+A52 -> 31 Bancos | C53: =+C52 -> 0 | D53: =+D51 -> Chq_Cx | E53: 43102 | F53: =IF(E53>0,(VLOOKUP(E53,'Blnct AR'!$C$2:$D$2259,2,0))," ") -> Banco - BECN. nº 0000984586 | G53: =+G52 -> Cheque de caixa | I53: =I51*0.1% -> 2000
A54: =+A53 -> 31 Bancos | C54: =+C53 -> 0 | D54: =+D52 -> Chq_Cx | E54: 7675 | F54: =IF(E54>0,(VLOOKUP(E54,'Blnct AR'!$C$2:$D$2259,2,0))," ") -> #N/A | G54: =+G53 -> Cheque de caixa | H54: =+I53 -> 2000
F55: =IF(E55>0,(VLOOKUP(E55,'Blnct AR'!$C$2:$D$2259,2,0))," ")
A56: 31 Bancos | C56: =+C55 -> 0 | D56: Chq_Erp | E56: 43102 | F56: =IF(E56>0,(VLOOKUP(E56,'Blnct AR'!$C$2:$D$2259,2,0))," ") -> Banco - BECN. nº 0000984586 | G56: Cheque de caixa ERP | I56: =SUM(H57:H59) -> 0
A57: =+A56 -> 31 Bancos | C57: =+C56 -> 0 | D57: Chq_Erp | E57: 3773 | F57: =IF(E57>0,(VLOOKUP(E57,'Blnct AR'!$C$2:$D$2259,2,0))," ") -> #N/A | G57: =+G56 -> Cheque de caixa ERP | H57: 0
A58: =+A57 -> 31 Bancos | C58: =+C57 -> 0 | D58: =+D56 -> Chq_Erp | E58: 7673 | F58: =IF(E58>0,(VLOOKUP(E58,'Blnct AR'!$C$2:$D$2259,2,0))," ") -> Despesas Bancárias | G58: =+G57 -> Cheque de caixa ERP | H58: 0
A59: =+A58 -> 31 Bancos | C59: =+C58 -> 0 | D59: =+D58 -> Chq_Erp | E59: 7674 | F59: =IF(E59>0,(VLOOKUP(E59,'Blnct AR'!$C$2:$D$2259,2,0))," ") -> #N/A | G59: =+G58 -> Cheque de caixa ERP | H59: =H58*0.7% -> 0
A61: 31 Bancos | C61: =+C60 -> 0 | D61: Tranf_Ent | E61: 43102 | F61: =IF(E61>0,(VLOOKUP(E61,'Blnct AR'!$C$2:$D$2259,2,0))," ") -> Banco - BECN. nº 0000984586 | G61: Transf. Para Iberestradas | I61: =SUM(H62:H64) -> 0
A62: =+A61 -> 31 Bancos | C62: =+C61 -> 0 | D62: Chq_Erp | E62: 33921 | F62: =IF(E62>0,(VLOOKUP(E62,'Blnct AR'!$C$2:$D$2259,2,0))," ") -> Entidade grupo | G62: =+G61 -> Transf. Para Iberestradas | H62: 0
A63: =+A62 -> 31 Bancos | C63: =+C62 -> 0 | D63: =+D61 -> Tranf_Ent | E63: 7673 | F63: =IF(E63>0,(VLOOKUP(E63,'Blnct AR'!$C$2:$D$2259,2,0))," ") -> Despesas Bancárias | G63: =+G62 -> Transf. Para Iberestradas | H63: 0
A64: =+A63 -> 31 Bancos | C64: =+C63 -> 0 | D64: =+D63 -> Tranf_Ent | E64: 7674 | F64: =IF(E64>0,(VLOOKUP(E64,'Blnct AR'!$C$2:$D$2259,2,0))," ") -> #N/A | G64: =+G63 -> Transf. Para Iberestradas | H64: =H63*0.7% -> 0
F65: =IF(E65>0,(VLOOKUP(E65,'Blnct AR'!$C$2:$D$2259,2,0))," ")
A66: 32 Bancos | C66: =+C54 -> 0 | D66: Pgto_Fncd | E66: 43102 | F66: =IF(E66>0,(VLOOKUP(E66,'Blnct AR'!$C$2:$D$2259,2,0))," ") -> Banco - BECN. nº 0000984586 | G66: Pgto Fornecedor | I66: =SUM(H67:H67) -> 0
A67: =+A66 -> 32 Bancos | C67: =+C55 -> 0 | D67: Pgto_Fncd | E67: 32121001 | F67: =IF(E67>0,(VLOOKUP(E67,'Blnct AR'!$C$2:$D$2259,2,0))," ") -> Gameiro Advogados, Lda. | G67: =+G66 -> Pgto Fornecedor | H67: 0
A69: 41 Compras | C69: =+C65 -> 0 | D69: Cmp_Crd | E69: 32121001 | F69: =IF(E69>0,(VLOOKUP(E69,'Blnct AR'!$C$2:$D$2259,2,0))," ") -> Gameiro Advogados, Lda. | G69: Compra a fornecedor | I69: 0
A70: =+A69 -> 41 Compras | C70: =+C69 -> 0 | D70: =+D69 -> Cmp_Crd | E70: 211111 | F70: =IF(E70>0,(VLOOKUP(E70,'Blnct AR'!$C$2:$D$2259,2,0))," ") -> Mp.MN-Custo de factura | G70: =+G69 -> Compra a fornecedor | H70: =+I69 -> 0
F71: =IF(E71>0,(VLOOKUP(E71,'Blnct AR'!$C$2:$D$2259,2,0))," ")
A72: 41 Compras | C72: =+C71 -> 0 | D72: Cmp_Dnh | E72: 4511 | F72: =IF(E72>0,(VLOOKUP(E72,'Blnct AR'!$C$2:$D$2259,2,0))," ") -> Caixa Kwanza | G72: Compra a fornecedor | I72: 0
A73: =+A72 -> 41 Compras | C73: =+C72 -> 0 | D73: =+D72 -> Cmp_Dnh | E73: 32121001 | F73: =IF(E73>0,(VLOOKUP(E73,'Blnct AR'!$C$2:$D$2259,2,0))," ") -> Gameiro Advogados, Lda. | G73: =+G72 -> Compra a fornecedor | H73: 0
A74: =+A73 -> 41 Compras | C74: =+C73 -> 0 | D74: =+D73 -> Cmp_Dnh | E74: 211111 | F74: =IF(E74>0,(VLOOKUP(E74,'Blnct AR'!$C$2:$D$2259,2,0))," ") -> Mp.MN-Custo de factura | G74: =+G73 -> Compra a fornecedor | I74: 0
A75: =+A74 -> 41 Compras | C75: =+C74 -> 0 | D75: =+D74 -> Cmp_Dnh | E75: 32121001 | F75: =IF(E75>0,(VLOOKUP(E75,'Blnct AR'!$C$2:$D$2259,2,0))," ") -> Gameiro Advogados, Lda. | G75: =+G74 -> Compra a fornecedor | H75: 0
F76: =IF(E76>0,(VLOOKUP(E76,'Blnct AR'!$C$2:$D$2259,2,0))," ")
A77: 42 FST | C77: =+C76 -> 0 | D77: Dsp_FST | E77: 752262 | F77: =IF(E77>0,(VLOOKUP(E77,'Blnct AR'!$C$2:$D$2259,2,0))," ") -> Edifícios e outras construções | G77: Mão-de-obra 3º | H77: 0
A78: =+A77 -> 42 FST | C78: =+C77 -> 0 | D78: =+D77 -> Dsp_FST | E78: 4511 | F78: =IF(E78>0,(VLOOKUP(E78,'Blnct AR'!$C$2:$D$2259,2,0))," ") -> Caixa Kwanza | G78: Mão-de-obra 3º | I78: 0
A80: 42 FST | C80: =+C76 -> 0 | D80: Dsp_FST | E80: 4511 | F80: =IF(E80>0,(VLOOKUP(E80,'Blnct AR'!$C$2:$D$2259,2,0))," ") -> Caixa Kwanza | G80: Revisões Viaturas | I80: =SUM(H81:H82) -> 0
A81: =+A80 -> 42 FST | C81: =+C80 -> 0 | D81: =+D80 -> Dsp_FST | E81: 752144 | F81: =IF(E81>0,(VLOOKUP(E81,'Blnct AR'!$C$2:$D$2259,2,0))," ") -> Equipamento de carga e transporte | G81: Revisões Viaturas material | H81: 0
A82: =+A81 -> 42 FST | C82: =+C81 -> 0 | D82: Dsp_FST | E82: 752264 | F82: =IF(E82>0,(VLOOKUP(E82,'Blnct AR'!$C$2:$D$2259,2,0))," ") -> Equipamento de carga e transporte | G82: Revisões Viaturas mão-de-obra | H82: 0
A84: 42 FST | C84: =+C83 -> 0 | D84: Dsp_FST | E84: 752149 | F84: =IF(E84>0,(VLOOKUP(E84,'Blnct AR'!$C$2:$D$2259,2,0))," ") -> Outras | G84: Mat. Divrs | H84: 0
A85: =+A84 -> 42 FST | C85: =+C84 -> 0 | D85: =+D84 -> Dsp_FST | E85: 4511 | F85: =IF(E85>0,(VLOOKUP(E85,'Blnct AR'!$C$2:$D$2259,2,0))," ") -> Caixa Kwanza | G85: Mat. Divrs | I85: =+H84 -> 0
F86: =IF(E86>0,(VLOOKUP(E86,'Blnct AR'!$C$2:$D$2259,2,0))," ")
A87: 42 FST | C87: 0 | D87: Dsp_FST | E87: 4511 | F87: =IF(E87>0,(VLOOKUP(E87,'Blnct AR'!$C$2:$D$2259,2,0))," ") -> Caixa Kwanza | G87: Compra Alimentos | I87: 0
A88: =+A87 -> 42 FST | C88: 0 | D88: Dsp_FST | E88: 728212 | F88: =IF(E88>0,(VLOOKUP(E88,'Blnct AR'!$C$2:$D$2259,2,0))," ") -> Alimentação/ Compras | G88: Compra Alimentos | H88: 0
F89: =IF(E89>0,(VLOOKUP(E89,'Blnct AR'!$C$2:$D$2259,2,0))," ")
A90: 42 FST | C90: =+C89 -> 0 | D90: Dsp_FST | E90: 4511 | F90: =IF(E90>0,(VLOOKUP(E90,'Blnct AR'!$C$2:$D$2259,2,0))," ") -> Caixa Kwanza | G90: Compra diversos estritório | I90: 0
A91: =+A90 -> 42 FST | C91: =+C90 -> 0 | D91: Dsp_FST | E91: 75217 | F91: =IF(E91>0,(VLOOKUP(E91,'Blnct AR'!$C$2:$D$2259,2,0))," ") -> Material de escritório | G91: Compra diversos estritório | H91: =I90 -> 0
A93: 42 FST | C93: =+C92 -> 0 | D93: Dsp_FST | E93: 4511 | F93: =IF(E93>0,(VLOOKUP(E93,'Blnct AR'!$C$2:$D$2259,2,0))," ") -> Caixa Kwanza | G93: Compra diversos | I93: 0
A94: =+A93 -> 42 FST | C94: =+C93 -> 0 | D94: Dsp_FST | E94: 752145 | F94: =IF(E94>0,(VLOOKUP(E94,'Blnct AR'!$C$2:$D$2259,2,0))," ") -> Equipamento administrativo | G94: Compra diversos | H94: =+I93 -> 0
A96: 42 FST | C96: =+C95 -> 0 | D96: Dsp_FST | E96: 4511 | F96: =IF(E96>0,(VLOOKUP(E96,'Blnct AR'!$C$2:$D$2259,2,0))," ") -> Caixa Kwanza | G96: Contabilidade | I96: 0
A97: =+A96 -> 42 FST | C97: =+C96 -> 0 | D97: Dsp_FST | E97: 75325 | F97: =IF(E97>0,(VLOOKUP(E97,'Blnct AR'!$C$2:$D$2259,2,0))," ") -> Serviços contabilisticos | G97: Contabilidade | H97: =+I96 -> 0
A99: 42 FST | C99: =+C98 -> 0 | D99: Dsp_FST | E99: 4511 | F99: =IF(E99>0,(VLOOKUP(E99,'Blnct AR'!$C$2:$D$2259,2,0))," ") -> Caixa Kwanza | G99: Renda Instalações | I99: 0
A100: =+A99 -> 42 FST | C100: =+C99 -> 0 | D100: Dsp_FST | E100: 752211 | F100: =IF(E100>0,(VLOOKUP(E100,'Blnct AR'!$C$2:$D$2259,2,0))," ") -> Rendas de imóveis Prefor | G100: Renda Instalações | H100: =+I99 -> 0
A102: 42 FST | C102: =+C92 -> 0 | D102: Conc_Bnk_CxAng | E102: 43106 | F102: =IF(E102>0,(VLOOKUP(E102,'Blnct AR'!$C$2:$D$2260,2,0))," ") -> Banco BIC - 118133685.15.1 | G102: Aluguer TPA | I102: 0
A103: =+A102 -> 42 FST | C103: =+C102 -> 0 | D103: =+D102 -> Conc_Bnk_CxAng | E103: 7678 | F103: =IF(E103>0,(VLOOKUP(E103,'Blnct AR'!$C$2:$D$2260,2,0))," ") -> Sb - outros | G103: Aluguer TPA | H103: =+I102 -> 0
A105: 42 FST | C105: =+C99 -> 0 | D105: Desp_Pess | E105: 72622 | F105: =IF(E105>0,(VLOOKUP(E105,'Blnct AR'!$C$2:$D$2262,2,0))," ") -> Produção | G105: Seguros Trabalho | H105: =+I106 -> 0
A106: =+A105 -> 42 FST | C106: =+C105 -> 0 | D106: Desp_Pess | E106: 4511 | F106: =IF(E106>0,(VLOOKUP(E106,'Blnct AR'!$C$2:$D$2262,2,0))," ") -> Caixa Kwanza | G106: Seguros Trabalho | I106: 0
A108: 41 Compras | C108: =+C107 -> 0 | D108: Cmpr_Imo | E108: 4511 | F108: =IF(E108>0,(VLOOKUP(E108,'Blnct AR'!$C$2:$D$2259,2,0))," ") -> Caixa Kwanza | G108: Compra Camião | I108: 0
A109: =+A108 -> 41 Compras | C109: =+C108 -> 0 | D109: =+D108 -> Cmpr_Imo | E109: 1141 | F109: =IF(E109>0,(VLOOKUP(E109,'Blnct AR'!$C$2:$D$2259,2,0))," ") -> Veiculos pesados | G109: Compra Camião | H109: =+I108 -> 0
A111: 41 Compras | C111: =+C110 -> 0 | D111: Cmpr_Imo | E111: 4511 | F111: =IF(E111>0,(VLOOKUP(E111,'Blnct AR'!$C$2:$D$2259,2,0))," ") -> Caixa Kwanza | G111: Compra Automóvel | I111: 0
A112: =+A111 -> 41 Compras | C112: =+C111 -> 0 | D112: =+D111 -> Cmpr_Imo | E112: 1142 | F112: =IF(E112>0,(VLOOKUP(E112,'Blnct AR'!$C$2:$D$2259,2,0))," ") -> Veiculos mistos e ligeiros | G112: Compra Automóvel | H112: =+I111 -> 0
A114: 41 Compras | C114: =+C113 -> 0 | D114: Amrtz_Imo | E114: 7314 | F114: =IF(E114>0,(VLOOKUP(E114,'Blnct AR'!$C$2:$D$2259,2,0))," ") -> Equipamento de carga e transporte | G114: Amortização Sinotruck | H114: =+I115 -> 0
A115: =+A114 -> 41 Compras | C115: =+C114 -> 0 | D115: =+D114 -> Amrtz_Imo | E115: 1814 | F115: =IF(E115>0,(VLOOKUP(E115,'Blnct AR'!$C$2:$D$2259,2,0))," ") -> Equipamento de carga e transporte | G115: Amortização Sinotruck | I115: 0
A117: 41 Compras | C117: =+C116 -> 0 | D117: Compr_Merc | E117: 212111 | F117: =IF(E117>0,(VLOOKUP(E117,'Blnct AR'!$C$2:$D$2259,2,0))," ") -> Mr.MN-Custo de factura | G117: Compra Mercadorias Diversas | H117: 30000 | I117: 30000
A118: =+A117 -> 41 Compras | C118: =+C117 -> 0 | D118: =+D117 -> Compr_Merc | E118: 2611 | F118: =IF(E118>0,(VLOOKUP(E118,'Blnct AR'!$C$2:$D$2259,2,0))," ") -> Merc-Existências | G118: Compra Mercadorias Diversas Armz | H118: 30000
A119: =+A118 -> 41 Compras | C119: =+C118 -> 0 | D119: =+D118 -> Compr_Merc | E119: 4511 | F119: =IF(E119>0,(VLOOKUP(E119,'Blnct AR'!$C$2:$D$2259,2,0))," ") -> Caixa Kwanza | G119: Compra Mercadorias Diversas Pagto | I119: 30000
A120: =+A119 -> 41 Compras | C120: =+C119 -> 0 | D120: =+D119 -> Compr_Merc | E120: 32121001 | F120: =IF(E120>0,(VLOOKUP(E120,'Blnct AR'!$C$2:$D$2259,2,0))," ") -> Gameiro Advogados, Lda. | G120: Compra Mercadorias Diversas Pagto | H120: 30000 | I120: 30000
A122: 51 Vendas | C122: =+C1 -> 0 | D122: Vnd_Merc | E122: 6111 | F122: =IF(E122>0,(VLOOKUP(E122,'Blnct AR'!$C$2:$D$2259,2,0))," ") -> Vnd Mercado nacional | G122: Venda a clientes | I122: 3723400
A123: =+A122 -> 51 Vendas | C123: =+C122 -> 0 | D123: =+D122 -> Vnd_Merc | E123: 31121002 | F123: =IF(E123>0,(VLOOKUP(E123,'Blnct AR'!$C$2:$D$2259,2,0))," ") -> Afavias Engª & Const Lda | G123: Venda a clientes | H123: 3723400
...

Sheet Lanç
F1: =ROUND(SUM(F3:F3910)-SUM(G3:G3910),3) -> 0 | G1: =IF(F1<>0,"DEB<>CRE","CONCLUÍDO") -> CONCLUÍDO | H1: =Balanço!$I$52 -> 5.364418e-07
A2: DATA | B2: N.º | C2: CÓD. CONTA | D2: NOME DA CONTA | E2: DESCRITIVO | F2: DÉBITO | G2: CRÉDITO | H2: CRÉDITO
A3: 43830 | B3: ABE_20 | C3: 1122 | D3: =IF(C3>0,(VLOOKUP(C3,'Blnct AR'!$C$2:$D$2262,2,0))," ") -> Outras construções | E3: Abertura 2020 | F3: 33771041
A4: 43830 | B4: ABE_20 | C4: 1131 | D4: =IF(C4>0,(VLOOKUP(C4,'Blnct AR'!$C$2:$D$2262,2,0))," ") -> Material Industrial | E4: Abertura 2020 | F4: 8490739.8
A5: 43830 | B5: ABE_20 | C5: 1132 | D5: =IF(C5>0,(VLOOKUP(C5,'Blnct AR'!$C$2:$D$2262,2,0))," ") -> Ferramentas industriais | E5: Abertura 2020 | F5: 1582983.3
A6: 43830 | B6: ABE_20 | C6: 1134 | D6: =IF(C6>0,(VLOOKUP(C6,'Blnct AR'!$C$2:$D$2262,2,0))," ") -> Gerador Genalec | E6: Abertura 2020 | F6: 3481000
A7: 43830 | B7: ABE_20 | C7: 1135 | D7: =IF(C7>0,(VLOOKUP(C7,'Blnct AR'!$C$2:$D$2262,2,0))," ") -> Empilhadora | E7: Abertura 2020 | F7: 1916250
A8: 43830 | B8: ABE_20 | C8: 114201 | D8: =IF(C8>0,(VLOOKUP(C8,'Blnct AR'!$C$2:$D$2262,2,0))," ") -> Nissan Navara LD -07-66 DQ | E8: Abertura 2020 | F8: 3152500
A9: 43830 | B9: ABE_20 | C9: 114202 | D9: =IF(C9>0,(VLOOKUP(C9,'Blnct AR'!$C$2:$D$2262,2,0))," ") -> Suzuki Grand Vitara LD-05-65-EF | E9: Abertura 2020 | F9: 4455000
A10: 43830 | B10: ABE_20 | C10: 114203 | D10: =IF(C10>0,(VLOOKUP(C10,'Blnct AR'!$C$2:$D$2262,2,0))," ") -> Nissan Micra LD-95-52-FZ | E10: Abertura 2020 | F10: 2500000
A11: 43830 | B11: ABE_20 | C11: 114205 | D11: =IF(C11>0,(VLOOKUP(C11,'Blnct AR'!$C$2:$D$2262,2,0))," ") -> SSANGYON Rexton RX LD-28-34-GD | E11: Abertura 2020 | F11: 4400000
A12: 43830 | B12: ABE_20 | C12: 114207 | D12: =IF(C12>0,(VLOOKUP(C12,'Blnct AR'!$C$2:$D$2262,2,0))," ") -> JMC Conquer 3360 LD-88-46-GK | E12: Abertura 2020 | F12: 3165000
A13: 43830 | B13: ABE_20 | C13: 114208 | D13: =IF(C13>0,(VLOOKUP(C13,'Blnct AR'!$C$2:$D$2262,2,0))," ") -> Motorizada | E13: Abertura 2020 | F13: 269000
A14: 43830 | B14: ABE_20 | C14: 114209 | D14: =IF(C14>0,(VLOOKUP(C14,'Blnct AR'!$C$2:$D$2262,2,0))," ") -> Ford Ranger - LD-22-37-FS | E14: Abertura 2020 | F14: 12400000
... A23: 43830 | B23: ABE_20 | C23: 1291 | D23: =IF(C23>0,(VLOOKUP(C23,'Blnct AR'!$C$2:$D$2262,2,0))," ") -> Outras imobilizações incorporeas | E23: Abertura 2020 | F23: 1717400
A24: 43830 | B24: ABE_20 | C24: 1812 | D24: =IF(C24>0,(VLOOKUP(C24,'Blnct AR'!$C$2:$D$2262,2,0))," ") -> Edificios e outras construções | E24: Abertura 2020 | F24: =IF(G24+H24<>0,G24-H24,"") -> -23837407 | H24: 23837407
A25: 43830 | B25: ABE_20 | C25: 1813 | D25: =IF(C25>0,(VLOOKUP(C25,'Blnct AR'!$C$2:$D$2262,2,0))," ") -> Equipamento básico | E25: Abertura 2020 | F25: =IF(G25+H25<>0,G25-H25,"") -> -7966128.4 | H25: 7966128.4
A26: 43830 | B26: ABE_20 | C26: 18141 | D26: =IF(C26>0,(VLOOKUP(C26,'Blnct AR'!$C$2:$D$2262,2,0))," ") -> Equipamento de carga e transporte | E26: Abertura 2020 | F26: =IF(G26+H26<>0,G26-H26,"") -> -26408167 | H26: 26408167
A27: 43830 | B27: ABE_20 | C27: 18151 | D27: =IF(C27>0,(VLOOKUP(C27,'Blnct AR'!$C$2:$D$2262,2,0))," ") -> Equipamento administrativo | E27: Abertura 2020 | F27: =IF(G27+H27<>0,G27-H27,"") -> -4654722.3 | H27: 4654722.3
A28: 43830 | B28: ABE_20 | C28: 1819 | D28: =IF(C28>0,(VLOOKUP(C28,'Blnct AR'!$C$2:$D$2262,2,0))," ") -> Outras imobilizações corpóreas | E28: Abertura 2020 | F28: =IF(G28+H28<>0,G28-H28,"") -> -86451 | H28: 86451
A29: 43830 | B29: ABE_20 | C29: 1829 | D29: =IF(C29>0,(VLOOKUP(C29,'Blnct AR'!$C$2:$D$2262,2,0))," ") -> Outras imobilizações incorporeas | E29: Abertura 2020 | F29: =IF(G29+H29<>0,G29-H29,"") -> -5669341.6 | H29: 5669341.6
A30: 43830 | B30: ABE_20 | C30: 211111 | D30: =IF(C30>0,(VLOOKUP(C30,'Blnct AR'!$C$2:$D$2262,2,0))," ") -> Mp.MN-Custo de factura | E30: Abertura 2020 | F30: 1566614
A31: 43830 | B31: ABE_20 | C31: 2211 | D31: =IF(C31>0,(VLOOKUP(C31,'Blnct AR'!$C$2:$D$2262,2,0))," ") -> Mp-Existências | E31: Abertura 2020 | F31: 27786231
A32: 43830 | B32: ABE_20 | C32: 2713 | D32: =IF(C32>0,(VLOOKUP(C32,'Blnct AR'!$C$2:$D$2262,2,0))," ") -> Mp.-Outros Mercados | E32: Abertura 2020 | F32: 11330087
A33: 43830 | B33: ABE_20 | C33: 31121003 | D33: =IF(C33>0,(VLOOKUP(C33,'Blnct AR'!$C$2:$D$2262,2,0))," ") -> UEM-Unid. Estruturas Metálicas, SA | E33: Abertura 2020 | F33: 27891307
A34: 43830 | B34: ABE_20 | C34: 31121009 | D34: =IF(C34>0,(VLOOKUP(C34,'Blnct AR'!$C$2:$D$2262,2,0))," ") -> Matra Engenharia e Construção, Lda | E34: Abertura 2020 | F34: 16613407
A35: 43830 | B35: ABE_20 | C35: 31121035 | D35: =IF(C35>0,(VLOOKUP(C35,'Blnct AR'!$C$2:$D$2262,2,0))," ") -> Cummins Angola, Lda | E35: Abertura 2020 | F35: 878.9
A36: 43830 | B36: ABE_20 | C36: 31121051 | D36: =IF(C36>0,(VLOOKUP(C36,'Blnct AR'!$C$2:$D$2262,2,0))," ") -> LYON- Contrução e Manut.Met. | E36: Abertura 2020 | F36: =IF(G36+H36<>0,G36-H36,"") -> -500000 | H36: 500000
A37: 43830 | B37: ABE_20 | C37: 31121077 | D37: =IF(C37>0,(VLOOKUP(C37,'Blnct AR'!$C$2:$D$2262,2,0))," ") -> CATOCA - Sociedade Mineira de Catoca, Lda | E37: Abertura 2020 | F37: 1520238.9
A38: 43830 | B38: ABE_20 | C38: 31121117 | D38: =IF(C38>0,(VLOOKUP(C38,'Blnct AR'!$C$2:$D$2262,2,0))," ") -> PSI Angola | E38: Abertura 2020 | F38: =IF(G38+H38<>0,G38-H38,"") -> -0.9 | H38: 0.9
A39: 43830 | B39: ABE_20 | C39: 31121118 | D39: =IF(C39>0,(VLOOKUP(C39,'Blnct AR'!$C$2:$D$2262,2,0))," ") -> Cimaleste | E39: Abertura 2020 | F39: 2205500
A40: 43830 | B40: ABE_20 | C40: 31121114 | D40: =IF(C40>0,(VLOOKUP(C40,'Blnct AR'!$C$2:$D$2262,2,0))," ") -> SEDIAC-Soc. de Est., Desenv. Ind. Agrícola e Corm. SA | E40: Abertura 2020 | F40: 202910.42
A41: 43830 | B41: ABE_20 | C41: 31121116 | D41: =IF(C41>0,(VLOOKUP(C41,'Blnct AR'!$C$2:$D$2262,2,0))," ") -> IMAVIZ - MINING, LDA. | E41: Abertura 2020 | F41: 2529830.5
A42: 43830 | B42: ABE_20 | C42: 3171034 | D42: =IF(C42>0,(VLOOKUP(C42,'Blnct AR'!$C$2:$D$2262,2,0))," ") -> Cummins Angola, Lda | E42: Abertura 2020 | F42: 94311.1
A43: 43830 | B43: ABE_20 | C43: 3171077 | D43: =IF(C43>0,(VLOOKUP(C43,'Blnct AR'!$C$2:$D$2262,2,0))," ") -> CATOCA - Sociedade Mineira de Catoca, Lda | E43: Abertura 2020 | F43: 10310385
A44: 43830 | B44: ABE_20 | C44: 3171113 | D44: =IF(C44>0,(VLOOKUP(C44,'Blnct AR'!$C$2:$D$2262,2,0))," ") -> PSI Angola | E44: Abertura 2020 | F44: 19500
A45: 43830 | B45: ABE_20 | C45: 3171114 | D45: =IF(C45>0,(VLOOKUP(C45,'Blnct AR'!$C$2:$D$2262,2,0))," ") -> Cimaleste | E45: Abertura 2020 | F45: 19500
A46: 43830 | B46: ABE_20 | C46: 3171116 | D46: =IF(C46>0,(VLOOKUP(C46,'Blnct AR'!$C$2:$D$2262,2,0))," ") -> IMAVIZ - MINING, LDA. | E46: Abertura 2020 | F46: 196167.61
A47: 43830 | B47: ABE_20 | C47: 318121 | D47: =IF(C47>0,(VLOOKUP(C47,'Blnct AR'!$C$2:$D$2262,2,0))," ") -> Nacionais | E47: Abertura 2020 | F47: 32608955
A48: 43831 | B48: ABE_20 | C48: 318121100 | D48: =IF(C48>0,(VLOOKUP(C48,'Blnct AR'!$C$2:$D$2262,2,0))," ") -> Motortech serviços | E48: Abertura 2021 | F48: 3400000
A49: 43830 | B49: ABE_20 | C49: 32121001 | D49: =IF(C49>0,(VLOOKUP(C49,'Blnct AR'!$C$2:$D$2262,2,0))," ") -> Gameiro Advogados, Lda. | E49: Abertura 2020 | F49: =IF(G49+H49<>0,G49-H49,"") -> -4917159.8 | H49: 4917159.8
A50: 43830 | B50: ABE_20 | C50: 32121007 | D50: =IF(C50>0,(VLOOKUP(C50,'Blnct AR'!$C$2:$D$2262,2,0))," ") -> Empedra, Lda | E50: Abertura 2020 | F50: =IF(G50+H50<>0,G50-H50,"") -> -3500000 | H50: 3500000
A51: 43830 | B51: ABE_20 | C51: 32121023 | D51: =IF(C51>0,(VLOOKUP(C51,'Blnct AR'!$C$2:$D$2262,2,0))," ") -> Côry Lda | E51: Abertura 2020 | F51: =IF(G51+H51<>0,G51-H51,"") -> -2615056 | H51: 2615056
A52: 43829 | B52: ABE_20 | C52: 32121074 | D52: =IF(C52>0,(VLOOKUP(C52,'Blnct AR'!$C$2:$D$2262,2,0))," ") -> NEUCE - O Futuro da Tinta | E52: Abertura 2019 | F52: =IF(G52+H52<>0,G52-H52,"") -> -1447175.5 | H52: 1447175.5
A53: 43830 | B53: ABE_20 | C53: 32121076 | D53: =IF(C53>0,(VLOOKUP(C53,'Blnct AR'!$C$2:$D$2262,2,0))," ") -> Pêra Produtos de Interior | E53: Abertura 2020 | F53: =IF(G53+H53<>0,G53-H53,"") -> -268001 | H53: 268001
A54: 43831 | B54: ABE_20 | C54: 32121077 | D54: =IF(C54>0,(VLOOKUP(C54,'Blnct AR'!$C$2:$D$2262,2,0))," ") -> CATOCA - Sociedade Mineira de Catoca, Lda | E54: Abertura 2021 | F54: =IF(G54+H54<>0,G54-H54,"") -> -172215.35 | H54: 172215.35
A55: 43830 | B55: ABE_20 | C55: 32121092 | D55: =IF(C55>0,(VLOOKUP(C55,'Blnct AR'!$C$2:$D$2262,2,0))," ") -> Ferpinta Angola,LDA | E55: Abertura 2020 | F55: =IF(G55+H55<>0,G55-H55,"") -> -5845.1 | H55: 5845.1
A56: 43830 | B56: ABE_20 | C56: 32121098 | D56: =IF(C56>0,(VLOOKUP(C56,'Blnct AR'!$C$2:$D$2262,2,0))," ") -> BONWS Seguros | E56: Abertura 2020 | F56: =IF(G56+H56<>0,G56-H56,"") -> -166783.67 | H56: 166783.67
A57: 43830 | B57: ABE_20 | C57: 32121110 | D57: =IF(C57>0,(VLOOKUP(C57,'Blnct AR'!$C$2:$D$2262,2,0))," ") -> R.G.P., Lda | E57: Abertura 2020 | F57: =IF(G57+H57<>0,G57-H57,"") -> -1715000 | H57: 1715000
A58: 43830 | B58: ABE_20 | C58: 32121117 | D58: =IF(C58>0,(VLOOKUP(C58,'Blnct AR'!$C$2:$D$2262,2,0))," ") -> Alprome | E58: Abertura 2020 | F58: =IF(G58+H58<>0,G58-H58,"") -> -1806000 | H58: 1806000
A59: 43830 | B59: ABE_20 | C59: 32121121 | D59: =IF(C59>0,(VLOOKUP(C59,'Blnct AR'!$C$2:$D$2262,2,0))," ") -> Cimaleste | E59: Abertura 2020 | F59: 1383452.9
A60: 43830 | B60: ABE_20 | C60: 32121143 | D60: =IF(C60>0,(VLOOKUP(C60,'Blnct AR'!$C$2:$D$2262,2,0))," ") -> Massiv Bau | E60: Abertura 2020 | F60: =IF(G60+H60<>0,G60-H60,"") -> -168220 | H60: 168220
A61: 43830 | B61: ABE_20 | C61: 32121150 | D61: =IF(C61>0,(VLOOKUP(C61,'Blnct AR'!$C$2:$D$2262,2,0))," ") -> Realvitur Angola | E61: Abertura 2020 | F61: =IF(G61+H61<>0,G61-H61,"") -> -708300 | H61: 708300
A62: 43831 | B62: ABE_20 | C62: 32121156 | D62: =IF(C62>0,(VLOOKUP(C62,'Blnct AR'!$C$2:$D$2262,2,0))," ") -> Prosegur | E62: Abertura 2021 | F62: =IF(G62+H62<>0,G62-H62,"") -> -285000 | H62: 285000
A63: 43830 | B63: ABE_20 | C63: 32121165 | D63: =IF(C63>0,(VLOOKUP(C63,'Blnct AR'!$C$2:$D$2262,2,0))," ") -> Fernando Virgílio de Almeida Mendes | E63: Abertura 2020 | F63: =IF(G63+H63<>0,G63-H63,"") -> -241460 | H63: 241460
A64: 43830 | B64: ABE_20 | C64: 32121172 | D64: =IF(C64>0,(VLOOKUP(C64,'Blnct AR'!$C$2:$D$2262,2,0))," ") -> Madtec-Mecânica Auto | E64: Abertura 2020 | F64: =IF(G64+H64<>0,G64-H64,"") -> -199900 | H64: 199900
A65: 43830 | B65: ABE_20 | C65: 32122002 | D65: =IF(C65>0,(VLOOKUP(C65,'Blnct AR'!$C$2:$D$2262,2,0))," ") -> UEM-Unid. Estruturas Metálicas, SA | E65: Abertura 2020 | F65: =IF(G65+H65<>0,G65-H65,"") -> -2.4410393e+08 | H65: 2.4410393e+08
A66: 43830 | B66: ABE_20 | C66: 32122007 | D66: =IF(C66>0,(VLOOKUP(C66,'Blnct AR'!$C$2:$D$2262,2,0))," ") -> Aegis Information Tecnologies | E66: Abertura 2020 | F66: =IF(G66+H66<>0,G66-H66,"") -> -93883.72 | H66: 93883.72
A67: 43830 | B67: ABE_20 | C67: 329121145 | D67: =IF(C67>0,(VLOOKUP(C67,'Blnct AR'!$C$2:$D$2262,2,0))," ") -> Bownos Seguros | E67: Abertura 2020 | F67: 1283297.2
A68: 43830 | B68: ABE_20 | C68: 329121146 | D68: =IF(C68>0,(VLOOKUP(C68,'Blnct AR'!$C$2:$D$2262,2,0))," ") -> Perfis Palanca | E68: Abertura 2020 | F68: 144984
A69: 43830 | B69: ABE_20 | C69: 329121147 | D69: =IF(C69>0,(VLOOKUP(C69,'Blnct AR'!$C$2:$D$2262,2,0))," ") -> Superview | E69: Abertura 2020 | F69: 150000
A70: 43830 | B70: ABE_20 | C70: 329121148 | D70: =IF(C70>0,(VLOOKUP(C70,'Blnct AR'!$C$2:$D$2262,2,0))," ") -> VP Soluções | E70: Abertura 2020 | F70: 400000
A71: 43830 | B71: ABE_20 | C71: 329121149 | D71: =IF(C71>0,(VLOOKUP(C71,'Blnct AR'!$C$2:$D$2262,2,0))," ") -> UNITEL,SA | E71: Abertura 2020 | F71: 38500
A72: 43830 | B72: ABE_20 | C72: 3412 | D72: =IF(C72>0,(VLOOKUP(C72,'Blnct AR'!$C$2:$D$2262,2,0))," ") -> IL- pagamentos por conta | E72: Abertura 2020 | F72: 2324548
A73: 43830 | B73: ABE_20 | C73: 3417 | D73: =IF(C73>0,(VLOOKUP(C73,'Blnct AR'!$C$2:$D$2262,2,0))," ") -> IL - a recuperar | E73: Abertura 2020 | F73: 4321929.6
A74: 43830 | B74: ABE_20 | C74: 3431 | D74: =IF(C74>0,(VLOOKUP(C74,'Blnct AR'!$C$2:$D$2262,2,0))," ") -> IRT dependentes | E74: Abertura 2020 | F74: =IF(G74+H74<>0,G74-H74,"") -> -438097 | H74: 438097
A75: 43830 | B75: ABE_20 | C75: 3432 | D75: =IF(C75>0,(VLOOKUP(C75,'Blnct AR'!$C$2:$D$2262,2,0))," ") -> IRT independentes | E75: Abertura 2020 | F75: =IF(G75+H75<>0,G75-H75,"") -> -168252.72 | H75: 168252.72
A76: 43830 | B76: ABE_20 | C76: 345232111 | D76: =IF(C76>0,(VLOOKUP(C76,'Blnct AR'!$C$2:$D$2262,2,0))," ") -> IVA Dedutível - Serviços - M. interno - 14% | E76: Abertura 2019 | F76: 99549.9
A77: 43830 | B77: ABE_20 | C77: 345312111 | D77: =IF(C77>0,(VLOOKUP(C77,'Blnct AR'!$C$2:$D$2262,2,0))," ") -> IVA Liq. - Op. gerais - Prest. Serv. - M.interno - 14% | E77: Abertura 2020 | F77: 10698744
A78: 43830 | B78: ABE_20 | C78: 3461 | D78: =IF(C78>0,(VLOOKUP(C78,'Blnct AR'!$C$2:$D$2262,2,0))," ") -> Segurança social | E78: Abertura 2020 | F78: =IF(G78+H78<>0,G78-H78,"") -> -124556.34 | H78: 124556.34
A79: 43830 | B79: ABE_20 | C79: 3471 | D79: =IF(C79>0,(VLOOKUP(C79,'Blnct AR'!$C$2:$D$2262,2,0))," ") -> Retenção 6,50% | E79: Abertura 2020 | F79: 149300.53
A80: 43830 | B80: ABE_20 | C80: 34731334 | D80: =IF(C80>0,(VLOOKUP(C80,'Blnct AR'!$C$2:$D$2262,2,0))," ") -> IS - recibos outros | E80: Abertura 2020 | F80: 324044.79
A81: 43830 | B81: ABE_20 | C81: 3491 | D81: =IF(C81>0,(VLOOKUP(C81,'Blnct AR'!$C$2:$D$2262,2,0))," ") -> IPU | E81: Abertura 2020 | F81: =IF(G81+H81<>0,G81-H81,"") -> -28984.55 | H81: 28984.55
A82: 43830 | B82: ABE_20 | C82: 351441 | D82: =IF(C82>0,(VLOOKUP(C82,'Blnct AR'!$C$2:$D$2262,2,0))," ") -> UEM-Unidade de Estruturas Metalúrgicas,S.A. | E82: Abertura 2020 | F82: =IF(G82+H82<>0,G82-H82,"") -> -741454.66 | H82: 741454.66
A83: 43830 | B83: ABE_20 | C83: 351443 | D83: =IF(C83>0,(VLOOKUP(C83,'Blnct AR'!$C$2:$D$2262,2,0))," ") -> António Luís da Graça Gameiro | E83: Abertura 2020 | F83: =IF(G83+H83<>0,G83-H83,"") -> -2702215 | H83: 2702215
A84: 43830 | B84: ABE_20 | C84: 3612101 | D84: =IF(C84>0,(VLOOKUP(C84,'Blnct AR'!$C$2:$D$2262,2,0))," ") -> Empregados | E84: Abertura 2020 | F84: =IF(G84+H84<>0,G84-H84,"") -> -4444632 | H84: 4444632
A85: 43830 | B85: ABE_20 | C85: 371121002 | D85: =IF(C85>0,(VLOOKUP(C85,'Blnct AR'!$C$2:$D$2262,2,0))," ") -> MIllennium Leasing | E85: Abertura 2020 | F85: =IF(G85+H85<>0,G85-H85,"") -> -1721241.7 | H85: 1721241.7
A86: 43830 | B86: ABE_20 | C86: 371121004 | D86: =IF(C86>0,(VLOOKUP(C86,'Blnct AR'!$C$2:$D$2262,2,0))," ") -> Millennium Leasing-Ford Ranger | E86: Abertura 2020 | F86: =IF(G86+H86<>0,G86-H86,"") -> -11373943 | H86: 11373943
A87: 43830 | B87: ABE_20 | C87: 371121005 | D87: =IF(C87>0,(VLOOKUP(C87,'Blnct AR'!$C$2:$D$2262,2,0))," ") -> Millennium Leasing - Conquer 3360 D/C Luxury | E87: Abertura 2020 | F87: 363821.03
A88: 43830 | B88: ABE_20 | C88: 371121006 | D88: =IF(C88>0,(VLOOKUP(C88,'Blnct AR'!$C$2:$D$2262,2,0))," ") -> Millennium Leasing LS1001522 - Rexton | E88: Abertura 2020 | F88: 1008005.2
A89: 43830 | B89: ABE_20 | C89: 371121007 | D89: =IF(C89>0,(VLOOKUP(C89,'Blnct AR'!$C$2:$D$2262,2,0))," ") -> Millennium Leasing LS1001523 - Conquer JMC | E89: Abertura 2020 | F89: 725214.2
A90: 43830 | B90: ABE_20 | C90: 371121008 | D90: =IF(C90>0,(VLOOKUP(C90,'Blnct AR'!$C$2:$D$2262,2,0))," ") -> Millennium Leasing LS2000028 - Ford Ranger | E90: Abertura 2020 | F90: 1652730.3
A91: 43830 | B91: ABE_20 | C91: 37511 | D91: =IF(C91>0,(VLOOKUP(C91,'Blnct AR'!$C$2:$D$2262,2,0))," ") -> Férias e Subsídio de Férias | E91: Abertura 2020 | F91: =IF(G91+H91<>0,G91-H91,"") -> -1291608 | H91: 1291608
A92: 43830 | B92: ABE_20 | C92: 3755 | D92: =IF(C92>0,(VLOOKUP(C92,'Blnct AR'!$C$2:$D$2262,2,0))," ") -> Imposto de Selo 2018 | E92: Abertura 2020 | F92: =IF(G92+H92<>0,G92-H92,"") -> -134396.12 | H92: 134396.12
A93: 43830 | B93: ABE_20 | C93: 3791047 | D93: =IF(C93>0,(VLOOKUP(C93,'Blnct AR'!$C$2:$D$2262,2,0))," ") -> Pinto Alberto | E93: Abertura 2020 | F93: 81035.82
A94: 43830 | B94: ABE_20 | C94: 3791074 | D94: =IF(C94>0,(VLOOKUP(C94,'Blnct AR'!$C$2:$D$2262,2,0))," ") -> Claudio Oliveira | E94: Abertura 2020 | F94: =IF(G94+H94<>0,G94-H94,"") -> -982000 | H94: 982000
A95: 43830 | B95: ABE_20 | C95: 38132 | D95: =IF(C95>0,(VLOOKUP(C95,'Blnct AR'!$C$2:$D$2262,2,0))," ") -> Não grupo | E95: Abertura 2020 | F95: =IF(G95+H95<>0,G95-H95,"") -> -2919625.5 | H95: 2919625.5
A96: 43830 | B96: ABE_20 | C96: 42103 | D96: =IF(C96>0,(VLOOKUP(C96,'Blnct AR'!$C$2:$D$2262,2,0))," ") -> MILLENNIUM | E96: Abertura 2020 | F96: 250000
A97: 43830 | B97: ABE_20 | C97: 43101 | D97: =IF(C97>0,(VLOOKUP(C97,'Blnct AR'!$C$2:$D$2262,2,0))," ") -> Banco - BFA | E97: Abertura 2020 | F97: 2616587.3
A98: 43830 | B98: ABE_20 | C98: 43102 | D98: =IF(C98>0,(VLOOKUP(C98,'Blnct AR'!$C$2:$D$2262,2,0))," ") -> Banco - BECN. nº 0000984586 | E98: Abertura 2020 | F98: 54325.09
A99: 43830 | B99: ABE_20 | C99: 43103 | D99: =IF(C99>0,(VLOOKUP(C99,'Blnct AR'!$C$2:$D$2262,2,0))," ") -> Milénnium 500471734904 Kz | E99: Abertura 2020 | F99: 65126624
A100: 43830 | B100: ABE_20 | C100: 43106 | D100: =IF(C100>0,(VLOOKUP(C100,'Blnct AR'!$C$2:$D$2262,2,0))," ") -> Banco BIC - 118133685.15.1 | E100: Abertura 2020 | F100: 27869927
A101: 43830 | B101: ABE_20 | C101: 43107 | D101: =IF(C101>0,(VLOOKUP(C101,'Blnct AR'!$C$2:$D$2262,2,0))," ") -> BAI nº 72519374.10.001 | E101: Abertura 2020 | F101: 21358.03
A102: 43830 | B102: ABE_20 | C102: 43108 | D102: =IF(C102>0,(VLOOKUP(C102,'Blnct AR'!$C$2:$D$2262,2,0))," ") -> BMA Conta Cativa- 06078645532001 | E102: Abertura 2020 | F102: 0.3
A103: 43830 | B103: ABE_20 | C103: 43202 | D103: =IF(C103>0,(VLOOKUP(C103,'Blnct AR'!$C$2:$D$2262,2,0))," ") -> Millennium - 06078645510001 - Euro | E103: Abertura 2020 | F103: 5795.64
A104: 43830 | B104: ABE_20 | C104: 45111 | D104: =IF(C104>0,(VLOOKUP(C104,'Blnct AR'!$C$2:$D$2262,2,0))," ") -> Caixa Geral | E104: Abertura 2020 | F104: 3541747.6
A105: 43830 | B105: ABE_20 | C105: 4802 | D105: =IF(C105>0,(VLOOKUP(C105,'Blnct AR'!$C$2:$D$2262,2,0))," ") -> Banco BFA | E105: Abertura 2020 | F105: =IF(G105+H105<>0,G105-H105,"") -> -345186.44 | H105: 345186.44
A106: 43830 | B106: ABE_20 | C106: 5111 | D106: =IF(C106>0,(VLOOKUP(C106,'Blnct AR'!$C$2:$D$2262,2,0))," ") -> UEM- Unidade de Estruturas Metálicas,S.A | E106: Abertura 2020 | F106: =IF(G106+H106<>0,G106-H106,"") -> -3825000 | H106: 3825000
A107: 43830 | B107: ABE_20 | C107: 5113 | D107: =IF(C107>0,(VLOOKUP(C107,'Blnct AR'!$C$2:$D$2262,2,0))," ") -> António Luís da graça Gameiro | E107: Abertura 2020 | F107: =IF(G107+H107<>0,G107-H107,"") -> -425000 | H107: 425000
A108: 43830 | B108: ABE_20 | C108: 542 | D108: =IF(C108>0,(VLOOKUP(C108,'Blnct AR'!$C$2:$D$2262,2,0))," ") -> Prestações suplementares- Reforço | E108: Abertura 2020 | F108: =IF(G108+H108<>0,G108-H108,"") -> -13282640 | H108: 13282640
...

Sheet Blnct AR
C2: BALANCETE ANALÍTICO APURAMENTO RESULTADOS
E3: =SUBTOTAL(9,E5:E2262) -> -3.0757746e+08 | F3: =SUBTOTAL(9,F5:F2262) -> 7.1894976e+09 | G3: =SUBTOTAL(9,G5:G2262) -> 7.0853258e+09 | H3: =SUBTOTAL(9,H5:H2262) -> 1.0417181e+08 | I3: =SUBTOTAL(9,I5:I2262) -> -2.0340564e+08 | S3: =F3-G3 -> 1.0417181e+08
A4: CRL 0,00 | B4: TIPO | C4: CÓDIGO | D4: DESCRICAO | E4: SALDO ANTERIOR | F4: DÉBITO PERIODO | G4: CRÉDITO PERIODO | H4: SALDO PERIODO | I4: SALDO ACUMULADO
A5: =IF(E5+F5+G5+H5+I5=0,1,0) -> 0 | B5: CL | C5: 1 | D5: MEIOS FIXOS E INVESTIMENTOS | E5: =SUM(E6,E58,E70,E91,E102,E128) -> 24061604 | F5: =SUM(F6,F58,F70,F91,F102,F128) -> 15239773 | G5: =SUM(G6,G58,G70,G91,G102,G128) -> 0 | H5: =(F5)-(G5) -> 15239773 | I5: =(E5)+(H5) -> 39301377
A6: =IF(E6+F6+G6+H6+I6=0,1,0) -> 0 | B6: R | C6: 11 | D6: IMOBILIZAÇÕES CORPÓREAS | E6: =SUM(E7,E15,E23,E31,E44,E52,E55) -> 86785921 | F6: =SUM(F7,F11,F15,F23,F31,F44,F52,F55) -> 15239773 | G6: =SUM(G23,G31,G44,G52,G55) -> 0 | H6: =(F6)-(G6) -> 15239773 | I6: =(E6)+(H6) -> 1.0202569e+08
A7: =IF(E7+F7+G7+H7+I7=0,1,0) -> 1 | B7: I | C7: 111 | D7: Terrenos e Recursos Naturais | E7: =SUM(E8:E10,E11) -> 0 | F7: =SUM(F8:F10,F11) -> 0 | G7: =SUM(G8:G10,G11) -> 0 | H7: =(F7)-(G7) -> 0 | I7: =(E7)+(H7) -> 0
A8: =IF(E8+F8+G8+H8+I8=0,1,0) -> 1 | B8: M | C8: 1111 | D8: Terrenos em Bruto | E8: =SUM(E9:E10) -> 0 | F8: =SUMIF(Lanç!$C$115:$C$6504,C8,Lanç!$F$115:$F$6504) -> 0 | G8: =SUMIF(Lanç!$C$115:$C$6504,C8,Lanç!$G$115:$G$6504) -> 0 | H8: =(F8)-(G8) -> 0 | I8: =(E8)+(H8) -> 0
A9: =IF(E9+F9+G9+H9+I9=0,1,0) -> 1 | B9: M | C9: 1112 | D9: Terrenos com Arranjos | E9: =SUMIF(Lanç!$C$3:$C$114,C9,Lanç!$F$3:$F$114) -> 0 | F9: =SUMIF(Lanç!$C$115:$C$6504,C9,Lanç!$F$115:$F$6504) -> 0 | G9: =SUMIF(Lanç!$C$115:$C$6504,C9,Lanç!$G$115:$G$6504) -> 0 | H9: =(F9)-(G9) -> 0 | I9: =(E9)+(H9) -> 0
A10: =IF(E10+F10+G10+H10+I10=0,1,0) -> 1 | B10: M | C10: 1113 | D10: Subsolos | E10: =SUMIF(Lanç!$C$3:$C$114,C10,Lanç!$F$3:$F$114) -> 0 | F10: =SUMIF(Lanç!$C$115:$C$6504,C10,Lanç!$F$115:$F$6504) -> 0 | G10: =SUMIF(Lanç!$C$115:$C$6504,C10,Lanç!$G$115:$G$6504) -> 0 | H10: =(F10)-(G10) -> 0 | I10: =(E10)+(H10) -> 0
A11: =IF(E11+F11+G11+H11+I11=0,1,0) -> 1 | B11: I | C11: 1114 | D11: Terrenos com edificios | E11: =SUM(E12:E14) -> 0 | F11: =SUM(F12:F14) -> 0 | G11: =SUM(G12:G14) -> 0 | H11: =(F11)-(G11) -> 0 | I11: =(E11)+(H11) -> 0
A12: =IF(E12+F12+G12+H12+I12=0,1,0) -> 1 | B12: M | C12: 11141 | D12: Relativos edificios industriais | E12: =SUMIF(Lanç!$C$3:$C$114,C12,Lanç!$F$3:$F$114) -> 0 | F12: =SUMIF(Lanç!$C$115:$C$6504,C12,Lanç!$F$115:$F$6504) -> 0 | G12: =SUMIF(Lanç!$C$115:$C$6504,C12,Lanç!$G$115:$G$6504) -> 0 | H12: =(F12)-(G12) -> 0 | I12: =(E12)+(H12) -> 0
A13: =IF(E13+F13+G13+H13+I13=0,1,0) -> 1 | B13: M | C13: 11142 | D13: Relativos edi. administrativos/come | E13: =SUMIF(Lanç!$C$3:$C$114,C13,Lanç!$F$3:$F$114) -> 0 | F13: =SUMIF(Lanç!$C$115:$C$6504,C13,Lanç!$F$115:$F$6504) -> 0 | G13: =SUMIF(Lanç!$C$115:$C$6504,C13,Lanç!$G$115:$G$6504) -> 0 | H13: =(F13)-(G13) -> 0 | I13: =(E13)+(H13) -> 0
A14: =IF(E14+F14+G14+H14+I14=0,1,0) -> 1 | B14: M | C14: 11143 | D14: Relativos a outros edificios | E14: =SUMIF(Lanç!$C$3:$C$114,C14,Lanç!$F$3:$F$114) -> 0 | F14: =SUMIF(Lanç!$C$115:$C$6504,C14,Lanç!$F$115:$F$6504) -> 0 | G14: =SUMIF(Lanç!$C$115:$C$6504,C14,Lanç!$G$115:$G$6504) -> 0 | H14: =(F14)-(G14) -> 0 | I14: =(E14)+(H14) -> 0
A15: =IF(E15+F15+G15+H15+I15=0,1,0) -> 0 | B15: I | C15: 112 | D15: Edificios e outras Construções | E15: =SUM(E16:E21) -> 33771041 | F15: =SUM(F16:F21) -> 0 | G15: =SUM(G16:G21) -> 0 | H15: =(F15)-(G15) -> 0 | I15: =(E15)+(H15) -> 33771041
A16: =IF(E16+F16+G16+H16+I16=0,1,0) -> 1 | B16: M | C16: 1121 | D16: Edificios | E16: =SUMIF(Lanç!$C$3:$C$114,C16,Lanç!$F$3:$F$114) -> 0 | F16: =SUMIF(Lanç!$C$115:$C$6504,C16,Lanç!$F$115:$F$6504) -> 0 | G16: =SUMIF(Lanç!$C$115:$C$6504,C16,Lanç!$G$115:$G$6504) -> 0 | H16: =(F16)-(G16) -> 0 | I16: =(E16)+(H16) -> 0
A17: =IF(E17+F17+G17+H17+I17=0,1,0) -> 1 | B17: M | C17: 11211 | D17: Integrados em conjuntos industriais | E17: =SUMIF(Lanç!$C$3:$C$114,C17,Lanç!$F$3:$F$114) -> 0 | F17: =SUMIF(Lanç!$C$115:$C$6504,C17,Lanç!$F$115:$F$6504) -> 0 | G17: =SUMIF(Lanç!$C$115:$C$6504,C17,Lanç!$G$115:$G$6504) -> 0 | H17: =(F17)-(G17) -> 0 | I17: =(E17)+(H17) -> 0
A18: =IF(E18+F18+G18+H18+I18=0,1,0) -> 1 | B18: M | C18: 11212 | D18: Integrados em conj.adm.e comerciais | E18: =SUMIF(Lanç!$C$3:$C$114,C18,Lanç!$F$3:$F$114) -> 0 | F18: =SUMIF(Lanç!$C$115:$C$6504,C18,Lanç!$F$115:$F$6504) -> 0 | G18: =SUMIF(Lanç!$C$115:$C$6504,C18,Lanç!$G$115:$G$6504) -> 0 | H18: =(F18)-(G18) -> 0 | I18: =(E18)+(H18) -> 0
A19: =IF(E19+F19+G19+H19+I19=0,1,0) -> 1 | B19: M | C19: 11213 | D19: Outros conjuntos industriais | E19: =SUMIF(Lanç!$C$3:$C$114,C19,Lanç!$F$3:$F$114) -> 0 | F19: =SUMIF(Lanç!$C$115:$C$6504,C19,Lanç!$F$115:$F$6504) -> 0 | G19: =SUMIF(Lanç!$C$115:$C$6504,C19,Lanç!$G$115:$G$6504) -> 0 | H19: =(F19)-(G19) -> 0 | I19: =(E19)+(H19) -> 0
A20: =IF(E20+F20+G20+H20+I20=0,1,0) -> 1 | B20: M | C20: 11214 | D20: Implantados em propriedade alheia | E20: =SUMIF(Lanç!$C$3:$C$114,C20,Lanç!$F$3:$F$114) -> 0 | F20: =SUMIF(Lanç!$C$115:$C$6504,C20,Lanç!$F$115:$F$6504) -> 0 | G20: =SUMIF(Lanç!$C$115:$C$6504,C20,Lanç!$G$115:$G$6504) -> 0 | H20: =(F20)-(G20) -> 0 | I20: =(E20)+(H20) -> 0
A21: =IF(E21+F21+G21+H21+I21=0,1,0) -> 0 | B21: M | C21: 1122 | D21: Outras construções | E21: =SUMIF(Lanç!C3:C114,C21,Lanç!F3:F114) -> 33771041 | F21: =SUMIF(Lanç!C115:C6504,C21,Lanç!F115:F6504) -> 0 | G21: =SUMIF(Lanç!C115:C6504,C21,Lanç!G115:G6504) -> 0 | H21: =(F21)-(G21) -> 0 | I21: =(E21)+(H21) -> 33771041
A22: =IF(E22+F22+G22+H22+I22=0,1,0) -> 1 | B22: M | C22: 1123 | D22: Instalações posto transformador | E22: =SUMIF(Lanç!$C$3:$C$114,C22,Lanç!$F$3:$F$114) -> 0 | F22: =SUMIF(Lanç!$C$115:$C$6504,C22,Lanç!$F$115:$F$6504) -> 0 | G22: =SUMIF(Lanç!$C$115:$C$6504,C22,Lanç!$G$115:$G$6504) -> 0 | H22: =(F22)-(G22) -> 0 | I22: =(E22)+(H22) -> 0
A23: =IF(E23+F23+G23+H23+I23=0,1,0) -> 0 | B23: I | C23: 113 | D23: Equipamento básico | E23: =SUM(E24) -> 15470973 | F23: =SUM(F24) -> 1200000 | G23: =SUM(G24) -> 0 | H23: =(F23)-(G23) -> 1200000 | I23: =(E23)+(H23) -> 16670973
A24: =IF(E24+F24+G24+H24+I24=0,1,0) -> 0 | B24: I | C24: 1131 | D24: Material Industrial | E24: =SUM(E25:E30) -> 15470973 | F24: =SUM(F25:F30) -> 1200000 | G24: =SUM(G25:G30) -> 0 | H24: =(F24)-(G24) -> 1200000 | I24: =(E24)+(H24) -> 16670973
A25: =IF(E25+F25+G25+H25+I25=0,1,0) -> 0 | B25: M | C25: 1131 | D25: Contentor Marítimo | E25: =SUMIF(Lanç!C3:C114,C25,Lanç!F3:F114) -> 8490739.8 | F25: =SUMIF(Lanç!C115:C6504,C25,Lanç!F115:F6504) -> 0 | G25: =SUMIF(Lanç!C115:C6504,C25,Lanç!G115:G6504) -> 0 | H25: =(F25)-(G25) -> 0 | I25: =(E25)+(H25) -> 8490739.8
A26: =IF(E26+F26+G26+H26+I26=0,1,0) -> 0 | B26: M | C26: 1132 | D26: Ferramentas industriais | E26: =SUMIF(Lanç!C3:C114,C26,Lanç!F3:F114) -> 1582983.3 | F26: =SUMIF(Lanç!C115:C6504,C26,Lanç!F115:F6504) -> 0 | G26: =SUMIF(Lanç!C115:C6504,C26,Lanç!G115:G6504) -> 0 | H26: =(F26)-(G26) -> 0 | I26: =(E26)+(H26) -> 1582983.3
A27: =IF(E27+F27+G27+H27+I27=0,1,0) -> 1 | B27: M | C27: 1133 | D27: Melhoramentos em equip.básicos | E27: =SUMIF(Lanç!$C$3:$C$114,C27,Lanç!$F$3:$F$114) -> 0 | F27: =SUMIF(Lanç!$C$115:$C$6504,C27,Lanç!$F$115:$F$6504) -> 0 | G27: =SUMIF(Lanç!$C$115:$C$6504,C27,Lanç!$G$115:$G$6504) -> 0 | H27: =(F27)-(G27) -> 0 | I27: =(E27)+(H27) -> 0
A28: =IF(E28+F28+G28+H28+I28=0,1,0) -> 0 | B28: M | C28: 1134 | D28: Gerador Genalec | E28: =SUMIF(Lanç!C3:C114,C28,Lanç!F3:F114) -> 3481000 | F28: =SUMIF(Lanç!C115:C6504,C28,Lanç!F115:F6504) -> 0 | G28: =SUMIF(Lanç!C115:C6504,C28,Lanç!G115:G6504) -> 0 | H28: =(F28)-(G28) -> 0 | I28: =(E28)+(H28) -> 3481000
A29: =IF(E29+F29+G29+H29+I29=0,1,0) -> 0 | B29: M | C29: 1135 | D29: Empilhadora | E29: =SUMIF(Lanç!C2:C113,C29,Lanç!F2:F113) -> 1916250 | F29: =SUMIF(Lanç!C114:C6503,C29,Lanç!F114:F6503) -> 0 | G29: =SUMIF(Lanç!C114:C6503,C29,Lanç!G114:G6503) -> 0 | H29: =(F29)-(G29) -> 0 | I29: =(E29)+(H29) -> 1916250
A30: =IF(E30+F30+G30+H30+I30=0,1,0) -> 0 | B30: M | C30: 1136 | D30: Gerador Kipor | E30: =SUMIF(Lanç!C3:C114,C30,Lanç!F3:F114) -> 0 | F30: =SUMIF(Lanç!C115:C6504,C30,Lanç!F115:F6504) -> 1200000 | G30: =SUMIF(Lanç!C115:C6504,C30,Lanç!G115:G6504) -> 0 | H30: =(F30)-(G30) -> 1200000 | I30: =(E30)+(H30) -> 1200000
A31: =IF(E31+F31+G31+H31+I31=0,1,0) -> 0 | B31: I | C31: 114 | D31: Equipamento de carga e transporte | E31: =SUM(E32,E33) -> 30341500 | F31: =SUM(F32,F33) -> 13611616 | G31: =SUM(G32,G33) -> 0 | H31: =(F31)-(G31) -> 13611616 | I31: =(E31)+(H31) -> 43953116
A32: =IF(E32+F32+G32+H32+I32=0,1,0) -> 1 | B32: M | C32: 1141 | D32: Veiculos pesados | E32: =SUMIF(Lanç!$C$3:$C$114,C32,Lanç!$F$3:$F$114) -> 0 | F32: =SUMIF(Lanç!$C$115:$C$6504,C32,Lanç!$F$115:$F$6504) -> 0 | G32: =SUMIF(Lanç!$C$115:$C$6504,C32,Lanç!$G$115:$G$6504) -> 0 | H32: =(F32)-(G32) -> 0 | I32: =(E32)+(H32) -> 0
A33: =IF(E33+F33+G33+H33+I33=0,1,0) -> 0 | B33: I | C33: 1142 | D33: Veiculos mistos e ligeiros | E33: =SUM(E34:E43) -> 30341500 | F33: =SUM(F34:F43) -> 13611616 | G33: =SUM(G34:G43) -> 0 | H33: =(F33)-(G33) -> 13611616 | I33: =(E33)+(H33) -> 43953116
A34: =IF(E34+F34+G34+H34+I34=0,1,0) -> 0 | B34: M | C34: 114201 | D34: Nissan Navara LD -07-66 DQ | E34: =SUMIF(Lanç!C3:C114,C34,Lanç!F3:F114) -> 3152500 | F34: =SUMIF(Lanç!C115:C6504,C34,Lanç!F115:F6504) -> 0 | G34: =SUMIF(Lanç!C115:C6504,C34,Lanç!G115:G6504) -> 0 | H34: =(F34)-(G34) -> 0 | I34: =(E34)+(H34) -> 3152500
A35: =IF(E35+F35+G35+H35+I35=0,1,0) -> 0 | B35: M | C35: 114202 | D35: Suzuki Grand Vitara LD-05-65-EF | E35: =SUMIF(Lanç!C3:C114,C35,Lanç!F3:F114) -> 4455000 | F35: =SUMIF(Lanç!C115:C6504,C35,Lanç!F115:F6504) -> 0 | G35: =SUMIF(Lanç!C115:C6504,C35,Lanç!G115:G6504) -> 0 | H35: =(F35)-(G35) -> 0 | I35: =(E35)+(H35) -> 4455000
A36: =IF(E36+F36+G36+H36+I36=0,1,0) -> 0 | B36: M | C36: 114203 | D36: Nissan Micra LD-95-52-FZ | E36: =SUMIF(Lanç!C3:C114,C36,Lanç!F3:F114) -> 2500000 | F36: =SUMIF(Lanç!C115:C6504,C36,Lanç!F115:F6504) -> 0 | G36: =SUMIF(Lanç!C115:C6504,C36,Lanç!G115:G6504) -> 0 | H36: =(F36)-(G36) -> 0 | I36: =(E36)+(H36) -> 2500000
A37: =IF(E37+F37+G37+H37+I37=0,1,0) -> 1 | B37: M | C37: 114204 | D37: Plataforma Articulado Piego 1985x750 | E37: =SUMIF(Lanç!$C$3:$C$114,C37,Lanç!$F$3:$F$114) -> 0 | F37: =SUMIF(Lanç!$C$115:$C$6504,C37,Lanç!$F$115:$F$6504) -> 0 | G37: =SUMIF(Lanç!$C$115:$C$6504,C37,Lanç!$G$115:$G$6504) -> 0 | H37: =(F37)-(G37) -> 0 | I37: =(E37)+(H37) -> 0
A38: =IF(E38+F38+G38+H38+I38=0,1,0) -> 0 | B38: M | C38: 114205 | D38: SSANGYON Rexton RX LD-28-34-GD | E38: =SUMIF(Lanç!C3:C114,C38,Lanç!F3:F114) -> 4400000 | F38: =SUMIF(Lanç!C115:C6504,C38,Lanç!F115:F6504) -> 0 | G38: =SUMIF(Lanç!C115:C6504,C38,Lanç!G115:G6504) -> 0 | H38: =(F38)-(G38) -> 0 | I38: =(E38)+(H38) -> 4400000
A39: =IF(E39+F39+G39+H39+I39=0,1,0) -> 1 | B39: M | C39: 114206 | D39: Nissan Micra HB 4AT | E39: =SUMIF(Lanç!C3:C114,C39,Lanç!F3:F114) -> 0 | F39: =SUMIF(Lanç!C115:C6504,C39,Lanç!F115:F6504) -> 0 | G39: =SUMIF(Lanç!C115:C6504,C39,Lanç!G115:G6504) -> 0 | H39: =(F39)-(G39) -> 0 | I39: =(E39)+(H39) -> 0
A40: =IF(E40+F40+G40+H40+I40=0,1,0) -> 0 | B40: M | C40: 114207 | D40: JMC Conquer 3360 LD-88-46-GK | E40: =SUMIF(Lanç!C3:C114,C40,Lanç!F3:F114) -> 3165000 | F40: =SUMIF(Lanç!C115:C6504,C40,Lanç!F115:F6504) -> 0 | G40: =SUMIF(Lanç!C115:C6504,C40,Lanç!G115:G6504) -> 0 | H40: =(F40)-(G40) -> 0 | I40: =(E40)+(H40) -> 3165000
A41: =IF(E41+F41+G41+H41+I41=0,1,0) -> 0 | B41: M | C41: 114208 | D41: Motorizada | E41: =SUMIF(Lanç!C3:C114,C41,Lanç!F3:F114) -> 269000 | F41: =SUMIF(Lanç!C115:C6504,C41,Lanç!F115:F6504) -> 0 | G41: =SUMIF(Lanç!C115:C6504,C41,Lanç!G115:G6504) -> 0 | H41: =(F41)-(G41) -> 0 | I41: =(E41)+(H41) -> 269000
A42: =IF(E42+F42+G42+H42+I42=0,1,0) -> 0 | B42: M | C42: 114209 | D42: Ford Ranger - LD-22-37-FS | E42: =SUMIF(Lanç!$C$3:$C$114,C42,Lanç!$F$3:$F$114) -> 12400000 | F42: =SUMIF(Lanç!$C$115:$C$6504,C42,Lanç!$F$115:$F$6504) -> 0 | G42: =SUMIF(Lanç!$C$115:$C$6504,C42,Lanç!$G$115:$G$6504) -> 0 | H42: =(F42)-(G42) -> 0 | I42: =(E42)+(H42) -> 12400000
A43: =IF(E43+F43+G43+H43+I43=0,1,0) -> 0 | B43: M | C43: 114210 | D43: Toyota Land Cruiser - LD-74-36-FS | E43: =SUMIF(Lanç!$C$3:$C$114,C43,Lanç!$F$3:$F$114) -> 0 | F43: =SUMIF(Lanç!$C$115:$C$6504,C43,Lanç!$F$115:$F$6504) -> 13611616 | G43: =SUMIF(Lanç!$C$115:$C$6504,C43,Lanç!$G$115:$G$6504) -> 0 | H43: =(F43)-(G43) -> 13611616 | I43: =(E43)+(H43) -> 13611616
A44: =IF(E44+F44+G44+H44+I44=0,1,0) -> 0 | B44: I | C44: 115 | D44: Equipamento administrativo | E44: =SUM(E45,E46,E48,E49,E50,E51) -> 7084999.1 | F44: =SUM(F45,F46,F48,F49,F50,F51) -> 428157.75 | G44: =SUM(G45,G46,G48,G49,G50,G51) -> 0 | H44: =(F44)-(G44) -> 428157.75 | I44: =(E44)+(H44) -> 7513156.9
A45: =IF(E45+F45+G45+H45+I45=0,1,0) -> 0 | B45: M | C45: 1151 | D45: Equipamento informatico | E45: =SUMIF(Lanç!C3:C114,C45,Lanç!F3:F114) -> 832396.09 | F45: =SUMIF(Lanç!C115:C6504,C45,Lanç!F115:F6504) -> 428157.75 | G45: =SUMIF(Lanç!C115:C6504,C45,Lanç!G115:G6504) -> 0 | H45: =(F45)-(G45) -> 428157.75 | I45: =(E45)+(H45) -> 1260553.8
A46: =IF(E46+F46+G46+H46+I46=0,1,0) -> 0 | B46: I | C46: 1152 | D46: Equipamento social | E46: =SUM(E47) -> 555241.13 | F46: =SUM(F47) -> 0 | G46: =SUM(G47) -> 0 | H46: =(F46)-(G46) -> 0 | I46: =(E46)+(H46) -> 555241.13
A47: =IF(E47+F47+G47+H47+I47=0,1,0) -> 0 | B47: M | C47: 115201 | D47: Equipamento Social | E47: =SUMIF(Lanç!C3:C114,C47,Lanç!F3:F114) -> 555241.13 | F47: =SUMIF(Lanç!C115:C6504,C47,Lanç!F115:F6504) -> 0 | G47: =SUMIF(Lanç!C115:C6504,C47,Lanç!G115:G6504) -> 0 | H47: =(F47)-(G47) -> 0 | I47: =(E47)+(H47) -> 555241.13
A48: =IF(E48+F48+G48+H48+I48=0,1,0) -> 0 | B48: M | C48: 1153 | D48: Mobiliário | E48: =SUMIF(Lanç!C3:C114,C48,Lanç!F3:F114) -> 4426438.1 | F48: =SUMIF(Lanç!C115:C6504,C48,Lanç!F115:F6504) -> 0 | G48: =SUMIF(Lanç!C115:C6504,C48,Lanç!G115:G6504) -> 0 | H48: =(F48)-(G48) -> 0 | I48: =(E48)+(H48) -> 4426438.1
A49: =IF(E49+F49+G49+H49+I49=0,1,0) -> 0 | B49: M | C49: 1154 | D49: AR Condicionado SPLIT 9000BTU MS9A- 09CR | E49: =SUMIF(Lanç!C3:C114,C49,Lanç!F3:F114) -> 245563.3 | F49: =SUMIF(Lanç!C115:C6504,C49,Lanç!F115:F6504) -> 0 | G49: =SUMIF(Lanç!C115:C6504,C49,Lanç!G115:G6504) -> 0 | H49: =(F49)-(G49) -> 0 | I49: =(E49)+(H49) -> 245563.3
A50: =IF(E50+F50+G50+H50+I50=0,1,0) -> 0 | B50: M | C50: 1155 | D50: Outros | E50: =SUMIF(Lanç!C3:C114,C50,Lanç!F3:F114) -> 955783.37 | F50: =SUMIF(Lanç!C115:C6504,C50,Lanç!F115:F6504) -> 0 | G50: =SUMIF(Lanç!C115:C6504,C50,Lanç!G115:G6504) -> 0 | H50: =(F50)-(G50) -> 0 | I50: =(E50)+(H50) -> 955783.37
A51: =IF(E51+F51+G51+H51+I51=0,1,0) -> 0 | B51: M | C51: 1156 | D51: Cofre | E51: =SUMIF(Lanç!C3:C114,C51,Lanç!F3:F114) -> 69577.15 | F51: =SUMIF(Lanç!C115:C6504,C51,Lanç!F115:F6504) -> 0 | G51: =SUMIF(Lanç!C115:C6504,C51,Lanç!G115:G6504) -> 0 | H51: =(F51)-(G51) -> 0 | I51: =(E51)+(H51) -> 69577.15
A52: =IF(E52+F52+G52+H52+I52=0,1,0) -> 1 | B52: I | C52: 116 | D52: Taras e vasilhame | E52: =SUM(E53:E54) -> 0 | F52: =SUM(F53:F54) -> 0 | G52: =SUM(G53:G54) -> 0 | H52: =(F52)-(G52) -> 0 | I52: =(E52)+(H52) -> 0
A53: =IF(E53+F53+G53+H53+I53=0,1,0) -> 1 | B53: M | C53: 1161 | D53: Embalagens retornáveis | E53: =SUMIF(Lanç!$C$3:$C$114,C53,Lanç!$F$3:$F$114) -> 0 | F53: =SUMIF(Lanç!$C$115:$C$6504,C53,Lanç!$F$115:$F$6504) -> 0 | G53: =SUMIF(Lanç!$C$115:$C$6504,C53,Lanç!$G$115:$G$6504) -> 0 | H53: =(F53)-(G53) -> 0 | I53: =(E53)+(H53) -> 0
A54: =IF(E54+F54+G54+H54+I54=0,1,0) -> 1 | B54: M | C54: 1162 | D54: Outras taras e outras embalagens | E54: =SUMIF(Lanç!$C$3:$C$114,C54,Lanç!$F$3:$F$114) -> 0 | F54: =SUMIF(Lanç!$C$115:$C$6504,C54,Lanç!$F$115:$F$6504) -> 0 | G54: =SUMIF(Lanç!$C$115:$C$6504,C54,Lanç!$G$115:$G$6504) -> 0 | H54: =(F54)-(G54) -> 0 | I54: =(E54)+(H54) -> 0
A55: =IF(E55+F55+G55+H55+I55=0,1,0) -> 0 | B55: I | C55: 119 | D55: Outras imobilizações corpóreas | E55: =SUM(E56:E57) -> 117408.44 | F55: =SUM(F56:F57) -> 0 | G55: =SUM(G56:G57) -> 0 | H55: =(F55)-(G55) -> 0 | I55: =(E55)+(H55) -> 117408.44
A56: =IF(E56+F56+G56+H56+I56=0,1,0) -> 1 | B56: M | C56: 1191 | D56: Obras em edíficios alheios | E56: =SUMIF(Lanç!$C$3:$C$114,C56,Lanç!$F$3:$F$114) -> 0 | F56: =SUMIF(Lanç!$C$115:$C$6504,C56,Lanç!$F$115:$F$6504) -> 0 | G56: =SUMIF(Lanç!$C$115:$C$6504,C56,Lanç!$G$115:$G$6504) -> 0 | H56: =(F56)-(G56) -> 0 | I56: =(E56)+(H56) -> 0
A57: =IF(E57+F57+G57+H57+I57=0,1,0) -> 0 | B57: M | C57: 1192 | D57: Tanque de Água | E57: =SUMIF(Lanç!C3:C114,C57,Lanç!F3:F114) -> 117408.44 | F57: =SUMIF(Lanç!C115:C6504,C57,Lanç!F115:F6504) -> 0 | G57: =SUMIF(Lanç!C115:C6504,C57,Lanç!G115:G6504) -> 0 | H57: =(F57)-(G57) -> 0 | I57: =(E57)+(H57) -> 117408.44
A58: =IF(E58+F58+G58+H58+I58=0,1,0) -> 0 | B58: R | C58: 12 | D58: IMOBILIZAÇÕES INCORPOREAS | E58: =SUM(E59,E60,E62,E64,E66,E68) -> 5897900 | F58: =SUM(F59,F60,F62,F64,F66,F68) -> 0 | G58: =SUM(G59,G60,G62,G64,G66,G68) -> 0 | H58: =(F58)-(G58) -> 0 | I58: =(E58)+(H58) -> 5897900
A59: =IF(E59+F59+G59+H59+I59=0,1,0) -> 1 | B59: M | C59: 1201 | D59: Banco....... | E59: =SUMIF(Lanç!$C$3:$C$114,C59,Lanç!$F$3:$F$114) -> 0 | F59: =SUMIF(Lanç!$C$115:$C$6504,C59,Lanç!$F$115:$F$6504) -> 0 | G59: =SUMIF(Lanç!$C$115:$C$6504,C59,Lanç!$G$115:$G$6504) -> 0 | H59: =(F59)-(G59) -> 0 | I59: =(E59)+(H59) -> 0
A60: =IF(E60+F60+G60+H60+I60=0,1,0) -> 1 | B60: I | C60: 121 | D60: Trespasses | E60: =SUM(E61) -> 0 | F60: =SUM(F61) -> 0 | G60: =SUM(G61) -> 0 | H60: =(F60)-(G60) -> 0 | I60: =(E60)+(H60) -> 0
A61: =IF(E61+F61+G61+H61+I61=0,1,0) -> 1 | B61: M | C61: 1211 | D61: Trespasse ...... | E61: =SUMIF(Lanç!$C$3:$C$114,C61,Lanç!$F$3:$F$114) -> 0 | F61: =SUMIF(Lanç!$C$115:$C$6504,C61,Lanç!$F$115:$F$6504) -> 0 | G61: =SUMIF(Lanç!$C$115:$C$6504,C61,Lanç!$G$115:$G$6504) -> 0 | H61: =(F61)-(G61) -> 0 | I61: =(E61)+(H61) -> 0
A62: =IF(E62+F62+G62+H62+I62=0,1,0) -> 1 | B62: I | C62: 122 | D62: Desp.investiga. e desenvolvimento | E62: =SUM(E63) -> 0 | F62: =SUM(F63) -> 0 | G62: =SUM(G63) -> 0 | H62: =(F62)-(G62) -> 0 | I62: =(E62)+(H62) -> 0
A63: =IF(E63+F63+G63+H63+I63=0,1,0) -> 1 | B63: M | C63: 1221 | D63: Desp.investiga. e desenvolvimento | E63: =SUMIF(Lanç!$C$3:$C$114,C63,Lanç!$F$3:$F$114) -> 0 | F63: =SUMIF(Lanç!$C$115:$C$6504,C63,Lanç!$F$115:$F$6504) -> 0 | G63: =SUMIF(Lanç!$C$115:$C$6504,C63,Lanç!$G$115:$G$6504) -> 0 | H63: =(F63)-(G63) -> 0 | I63: =(E63)+(H63) -> 0
A64: =IF(E64+F64+G64+H64+I64=0,1,0) -> 1 | B64: I | C64: 123 | D64: Propriedade industrial e outros | E64: =SUM(E65) -> 0 | F64: =SUM(F65) -> 0 | G64: =SUM(G65) -> 0 | H64: =(F64)-(G64) -> 0 | I64: =(E64)+(H64) -> 0
A65: =IF(E65+F65+G65+H65+I65=0,1,0) -> 1 | B65: M | C65: 1231 | D65: Propriedade industrial e outros | E65: =SUMIF(Lanç!$C$3:$C$114,C65,Lanç!$F$3:$F$114) -> 0 | F65: =SUMIF(Lanç!$C$115:$C$6504,C65,Lanç!$F$115:$F$6504) -> 0 | G65: =SUMIF(Lanç!$C$115:$C$6504,C65,Lanç!$G$115:$G$6504) -> 0 | H65: =(F65)-(G65) -> 0 | I65: =(E65)+(H65) -> 0
A66: =IF(E66+F66+G66+H66+I66=0,1,0) -> 0 | B66: I | C66: 124 | D66: Despesas de constituição | E66: =SUM(E67) -> 4180500 | F66: =SUM(F67) -> 0 | G66: =SUM(G67) -> 0 | H66: =(F66)-(G66) -> 0 | I66: =(E66)+(H66) -> 4180500
A67: =IF(E67+F67+G67+H67+I67=0,1,0) -> 0 | B67: M | C67: 1241 | D67: Despesas de constituição | E67: =SUMIF(Lanç!C3:C114,C67,Lanç!F3:F114) -> 4180500 | F67: =SUMIF(Lanç!C115:C6504,C67,Lanç!F115:F6504) -> 0 | G67: =SUMIF(Lanç!C115:C6504,C67,Lanç!G115:G6504) -> 0 | H67: =(F67)-(G67) -> 0 | I67: =(E67)+(H67) -> 4180500
A68: =IF(E68+F68+G68+H68+I68=0,1,0) -> 0 | B68: I | C68: 129 | D68: Outras imobilizações incorporeas | E68: =SUM(E69:E69) -> 1717400 | F68: =SUM(F69:F69) -> 0 | G68: =SUM(G69:G69) -> 0 | H68: =(F68)-(G68) -> 0 | I68: =(E68)+(H68) -> 1717400
A69: =IF(E69+F69+G69+H69+I69=0,1,0) -> 0 | B69: M | C69: 1291 | D69: Outras imobilizações incorporeas | E69: =SUMIF(Lanç!C3:C114,C69,Lanç!F3:F114) -> 1717400 | F69: =SUMIF(Lanç!C115:C6504,C69,Lanç!F115:F6504) -> 0 | G69: =SUMIF(Lanç!C115:C6504,C69,Lanç!G115:G6504) -> 0 | H69: =(F69)-(G69) -> 0 | I69: =(E69)+(H69) -> 1717400
A70: =IF(E70+F70+G70+H70+I70=0,1,0) -> 1 | B70: R | C70: 13 | D70: INVESTIMENTOS FINANCEIROS | E70: =SUM(E71,E75,E79,E83,E85,E87) -> 0 | F70: =SUM(F71,F75,F79,F83,F85,F87) -> 0 | G70: =SUM(G71,G75,G79,G83,G85,G87) -> 0 | H70: =(F70)-(G70) -> 0 | I70: =(E70)+(H70) -> 0
A71: =IF(E71+F71+G71+H71+I71=0,1,0) -> 1 | B71: I | C71: 131 | D71: Empresas subsidiarias | E71: =SUM(E72:E74) -> 0 | F71: =SUM(F72:F74) -> 0 | G71: =SUM(G72:G74) -> 0 | H71: =(F71)-(G71) -> 0 | I71: =(E71)+(H71) -> 0
A72: =IF(E72+F72+G72+H72+I72=0,1,0) -> 1 | B72: M | C72: 1311 | D72: Partes de capital | E72: =SUMIF(Lanç!$C$3:$C$114,C72,Lanç!$F$3:$F$114) -> 0 | F72: =SUMIF(Lanç!$C$115:$C$6504,C72,Lanç!$F$115:$F$6504) -> 0 | G72: =SUMIF(Lanç!$C$115:$C$6504,C72,Lanç!$G$115:$G$6504) -> 0 | H72: =(F72)-(G72) -> 0 | I72: =(E72)+(H72) -> 0
A73: =IF(E73+F73+G73+H73+I73=0,1,0) -> 1 | B73: M | C73: 1312 | D73: Obrigações e tít.de participação | E73: =SUMIF(Lanç!$C$3:$C$114,C73,Lanç!$F$3:$F$114) -> 0 | F73: =SUMIF(Lanç!$C$115:$C$6504,C73,Lanç!$F$115:$F$6504) -> 0 | G73: =SUMIF(Lanç!$C$115:$C$6504,C73,Lanç!$G$115:$G$6504) -> 0 | H73: =(F73)-(G73) -> 0 | I73: =(E73)+(H73) -> 0
A74: =IF(E74+F74+G74+H74+I74=0,1,0) -> 1 | B74: M | C74: 1313 | D74: Empréstimos | E74: =SUMIF(Lanç!$C$3:$C$114,C74,Lanç!$F$3:$F$114) -> 0 | F74: =SUMIF(Lanç!$C$115:$C$6504,C74,Lanç!$F$115:$F$6504) -> 0 | G74: =SUMIF(Lanç!$C$115:$C$6504,C74,Lanç!$G$115:$G$6504) -> 0 | H74: =(F74)-(G74) -> 0 | I74: =(E74)+(H74) -> 0
A75: =IF(E75+F75+G75+H75+I75=0,1,0) -> 1 | B75: I | C75: 132 | D75: Empresas associadas | E75: =SUM(E76:E78) -> 0 | F75: =SUM(F76:F78) -> 0 | G75: =SUM(G76:G78) -> 0 | H75: =(F75)-(G75) -> 0 | I75: =(E75)+(H75) -> 0
A76: =IF(E76+F76+G76+H76+I76=0,1,0) -> 1 | B76: M | C76: 1321 | D76: Partes de capital | E76: =SUMIF(Lanç!$C$3:$C$114,C76,Lanç!$F$3:$F$114) -> 0 | F76: =SUMIF(Lanç!$C$115:$C$6504,C76,Lanç!$F$115:$F$6504) -> 0 | G76: =SUMIF(Lanç!$C$115:$C$6504,C76,Lanç!$G$115:$G$6504) -> 0 | H76: =(F76)-(G76) -> 0 | I76: =(E76)+(H76) -> 0
A77: =IF(E77+F77+G77+H77+I77=0,1,0) -> 1 | B77: M | C77: 1322 | D77: Obrigações e tít.de participação | E77: =SUMIF(Lanç!$C$3:$C$114,C77,Lanç!$F$3:$F$114) -> 0 | F77: =SUMIF(Lanç!$C$115:$C$6504,C77,Lanç!$F$115:$F$6504) -> 0 | G77: =SUMIF(Lanç!$C$115:$C$6504,C77,Lanç!$G$115:$G$6504) -> 0 | H77: =(F77)-(G77) -> 0 | I77: =(E77)+(H77) -> 0
A78: =IF(E78+F78+G78+H78+I78=0,1,0) -> 1 | B78: M | C78: 1323 | D78: Empréstimos | E78: =SUMIF(Lanç!$C$3:$C$114,C78,Lanç!$F$3:$F$114) -> 0 | F78: =SUMIF(Lanç!$C$115:$C$6504,C78,Lanç!$F$115:$F$6504) -> 0 | G78: =SUMIF(Lanç!$C$115:$C$6504,C78,Lanç!$G$115:$G$6504) -> 0 | H78: =(F78)-(G78) -> 0 | I78: =(E78)+(H78) -> 0
A79: =IF(E79+F79+G79+H79+I79=0,1,0) -> 1 | B79: I | C79: 133 | D79: Outras empresas | E79: =SUM(E80:E82) -> 0 | F79: =SUM(F80:F82) -> 0 | G79: =SUM(G80:G82) -> 0 | H79: =(F79)-(G79) -> 0 | I79: =(E79)+(H79) -> 0
A80: =IF(E80+F80+G80+H80+I80=0,1,0) -> 1 | B80: M | C80: 1331 | D80: Partes de capital | E80: =SUMIF(Lanç!$C$3:$C$114,C80,Lanç!$F$3:$F$114) -> 0 | F80: =SUMIF(Lanç!$C$115:$C$6504,C80,Lanç!$F$115:$F$6504) -> 0 | G80: =SUMIF(Lanç!$C$115:$C$6504,C80,Lanç!$G$115:$G$6504) -> 0 | H80: =(F80)-(G80) -> 0 | I80: =(E80)+(H80) -> 0
A81: =IF(E81+F81+G81+H81+I81=0,1,0) -> 1 | B81: M | C81: 1332 | D81: Obrigações e tít.de participação | E81: =SUMIF(Lanç!$C$3:$C$114,C81,Lanç!$F$3:$F$114) -> 0 | F81: =SUMIF(Lanç!$C$115:$C$6504,C81,Lanç!$F$115:$F$6504) -> 0 | G81: =SUMIF(Lanç!$C$115:$C$6504,C81,Lanç!$G$115:$G$6504) -> 0 | H81: =(F81)-(G81) -> 0 | I81: =(E81)+(H81) -> 0
A82: =IF(E82+F82+G82+H82+I82=0,1,0) -> 1 | B82: M | C82: 1333 | D82: Empréstimos | E82: =SUMIF(Lanç!$C$3:$C$114,C82,Lanç!$F$3:$F$114) -> 0 | F82: =SUMIF(Lanç!$C$115:$C$6504,C82,Lanç!$F$115:$F$6504) -> 0 | G82: =SUMIF(Lanç!$C$115:$C$6504,C82,Lanç!$G$115:$G$6504) -> 0 | H82: =(F82)-(G82) -> 0 | I82: =(E82)+(H82) -> 0
A83: =IF(E83+F83+G83+H83+I83=0,1,0) -> 1 | B83: I | C83: 134 | D83: Investimentos em imoveis | E83: =SUM(E84) -> 0 | F83: =SUM(F84) -> 0 | G83: =SUM(G84) -> 0 | H83: =(F83)-(G83) -> 0 | I83: =(E83)+(H83) -> 0
A84: =IF(E84+F84+G84+H84+I84=0,1,0) -> 1 | B84: M | C84: 1341 | D84: ... | E84: =SUMIF(Lanç!$C$3:$C$114,C84,Lanç!$F$3:$F$114) -> 0 | F84: =SUMIF(Lanç!$C$115:$C$6504,C84,Lanç!$F$115:$F$6504) -> 0 | G84: =SUMIF(Lanç!$C$115:$C$6504,C84,Lanç!$G$115:$G$6504) -> 0 | H84: =(F84)-(G84) -> 0 | I84: =(E84)+(H84) -> 0
A85: =IF(E85+F85+G85+H85+I85=0,1,0) -> 1 | B85: I | C85: 135 | D85: Fundos | E85: =SUM(E86) -> 0 | F85: =SUM(F86) -> 0 | G85: =SUM(G86) -> 0 | H85: =(F85)-(G85) -> 0 | I85: =(E85)+(H85) -> 0
A86: =IF(E86+F86+G86+H86+I86=0,1,0) -> 1 | B86: M | C86: 1351 | D86: ... | E86: =SUMIF(Lanç!$C$3:$C$114,C86,Lanç!$F$3:$F$114) -> 0 | F86: =SUMIF(Lanç!$C$115:$C$6504,C86,Lanç!$F$115:$F$6504) -> 0 | G86: =SUMIF(Lanç!$C$115:$C$6504,C86,Lanç!$G$115:$G$6504) -> 0 | H86: =(F86)-(G86) -> 0 | I86: =(E86)+(H86) -> 0
A87: =IF(E87+F87+G87+H87+I87=0,1,0) -> 1 | B87: I | C87: 139 | D87: Outros investimentos financeiros | E87: =SUM(E88:E90) -> 0 | F87: =SUM(F88:F90) -> 0 | G87: =SUM(G88:G90) -> 0 | H87: =(F87)-(G87) -> 0 | I87: =(E87)+(H87) -> 0
A88: =IF(E88+F88+G88+H88+I88=0,1,0) -> 1 | B88: M | C88: 1391 | D88: Diamantes | E88: =SUMIF(Lanç!$C$3:$C$114,C88,Lanç!$F$3:$F$114) -> 0 | F88: =SUMIF(Lanç!$C$115:$C$6504,C88,Lanç!$F$115:$F$6504) -> 0 | G88: =SUMIF(Lanç!$C$115:$C$6504,C88,Lanç!$G$115:$G$6504) -> 0 | H88: =(F88)-(G88) -> 0 | I88: =(E88)+(H88) -> 0
A89: =IF(E89+F89+G89+H89+I89=0,1,0) -> 1 | B89: M | C89: 1392 | D89: Ouro | E89: =SUMIF(Lanç!$C$3:$C$114,C89,Lanç!$F$3:$F$114) -> 0 | F89: =SUMIF(Lanç!$C$115:$C$6504,C89,Lanç!$F$115:$F$6504) -> 0 | G89: =SUMIF(Lanç!$C$115:$C$6504,C89,Lanç!$G$115:$G$6504) -> 0 | H89: =(F89)-(G89) -> 0 | I89: =(E89)+(H89) -> 0
A90: =IF(E90+F90+G90+H90+I90=0,1,0) -> 1 | B90: M | C90: 1393 | D90: Depósitps bancários | E90: =SUMIF(Lanç!$C$3:$C$114,C90,Lanç!$F$3:$F$114) -> 0 | F90: =SUMIF(Lanç!$C$115:$C$6504,C90,Lanç!$F$115:$F$6504) -> 0 | G90: =SUMIF(Lanç!$C$115:$C$6504,C90,Lanç!$G$115:$G$6504) -> 0 | H90: =(F90)-(G90) -> 0 | I90: =(E90)+(H90) -> 0
A91: =IF(E91+F91+G91+H91+I91=0,1,0) -> 1 | B91: R | C91: 14 | D91: IMOBILIZAÇÕES EM CURSO | E91: =SUM(E92,E93,E94,E97,E99) -> 0 | F91: =SUM(F92,F93,F94,F97,F99) -> 0 | G91: =SUM(G92,G93,G94,G97,G99) -> 0 | H91: =(F91)-(G91) -> 0 | I91: =(E91)+(H91) -> 0
A92: =IF(E92+F92+G92+H92+I92=0,1,0) -> 1 | B92: M | C92: 141 | D92: Obra em curso | E92: =SUMIF(Lanç!$C$3:$C$114,C92,Lanç!$F$3:$F$114) -> 0 | F92: =SUMIF(Lanç!$C$115:$C$6504,C92,Lanç!$F$115:$F$6504) -> 0 | G92: =SUMIF(Lanç!$C$115:$C$6504,C92,Lanç!$G$115:$G$6504) -> 0 | H92: =(F92)-(G92) -> 0 | I92: =(E92)+(H92) -> 0
A93: =IF(E93+F93+G93+H93+I93=0,1,0) -> 1 | B93: I | C93: 142 | D93: Obra em curso | E93: =SUMIF(Lanç!$C$3:$C$114,C93,Lanç!$F$3:$F$114) -> 0 | F93: =SUMIF(Lanç!$C$115:$C$6504,C93,Lanç!$F$115:$F$6504) -> 0 | G93: =SUMIF(Lanç!$C$115:$C$6504,C93,Lanç!$G$115:$G$6504) -> 0 | H93: =(F93)-(G93) -> 0 | I93: =(E93)+(H93) -> 0
A94: =IF(E94+F94+G94+H94+I94=0,1,0) -> 1 | B94: I | C94: 143 | D94: Imobilizações em curso | E94: =SUM(E95:E96) -> 0 | F94: =SUM(F95:F96) -> 0 | G94: =SUM(G95:G96) -> 0 | H94: =(F94)-(G94) -> 0 | I94: =(E94)+(H94) -> 0
A95: =IF(E95+F95+G95+H95+I95=0,1,0) -> 1 | B95: M | C95: 1431 | D95: Obras Balneário refeitório e escritório | E95: =SUMIF(Lanç!$C$3:$C$114,C95,Lanç!$F$3:$F$114) -> 0 | F95: =SUMIF(Lanç!$C$115:$C$6504,C95,Lanç!$F$115:$F$6504) -> 0 | G95: =SUMIF(Lanç!$C$115:$C$6504,C95,Lanç!$G$115:$G$6504) -> 0 | H95: =(F95)-(G95) -> 0 | I95: =(E95)+(H95) -> 0
A96: =IF(E96+F96+G96+H96+I96=0,1,0) -> 1 | B96: M | C96: 1432 | D96: Obras em Moradia | E96: =SUMIF(Lanç!$C$3:$C$114,C96,Lanç!$F$3:$F$114) -> 0 | F96: =SUMIF(Lanç!$C$115:$C$6504,C96,Lanç!$F$115:$F$6504) -> 0 | G96: =SUMIF(Lanç!$C$115:$C$6504,C96,Lanç!$G$115:$G$6504) -> 0 | H96: =(F96)-(G96) -> 0 | I96: =(E96)+(H96) -> 0
A97: =IF(E97+F97+G97+H97+I97=0,1,0) -> 1 | B97: I | C97: 147 | D97: Adiantamentos p/conta imob.incorp. | E97: =SUM(E98) -> 0 | F97: =SUM(F98) -> 0 | G97: =SUM(G98) -> 0 | H97: =(F97)-(G97) -> 0 | I97: =(E97)+(H97) -> 0
A98: =IF(E98+F98+G98+H98+I98=0,1,0) -> 1 | B98: M | C98: 1471 | D98: ... | E98: =SUMIF(Lanç!$C$3:$C$114,C98,Lanç!$F$3:$F$114) -> 0 | F98: =SUMIF(Lanç!$C$115:$C$6504,C98,Lanç!$F$115:$F$6504) -> 0 | G98: =SUMIF(Lanç!$C$115:$C$6504,C98,Lanç!$G$115:$G$6504) -> 0 | H98: =(F98)-(G98) -> 0 | I98: =(E98)+(H98) -> 0
A99: =IF(E99+F99+G99+H99+I99=0,1,0) -> 1 | B99: I | C99: 148 | D99: Adiantamentos p/conta imob.incorp. | E99: =SUM(E100:E101) -> 0 | F99: =SUM(F100:F101) -> 0 | G99: =SUM(G100:G101) -> 0 | H99: =(F99)-(G99) -> 0 | I99: =(E99)+(H99) -> 0
A100: =IF(E100+F100+G100+H100+I100=0,1,0) -> 1 | B100: M | C100: 1481 | D100: ... | E100: =SUMIF(Lanç!$C$3:$C$114,C100,Lanç!$F$3:$F$114) -> 0 | F100: =SUMIF(Lanç!$C$115:$C$6504,C100,Lanç!$F$115:$F$6504) -> 0 | G100: =SUMIF(Lanç!$C$115:$C$6504,C100,Lanç!$G$115:$G$6504) -> 0 | H100: =(F100)-(G100) -> 0 | I100: =(E100)+(H100) -> 0
A101: =IF(E101+F101+G101+H101+I101=0,1,0) -> 1 | B101: M | C101: 149 | D101: Adiantamentos p/conta de investim. | E101: =SUMIF(Lanç!$C$3:$C$114,C101,Lanç!$F$3:$F$114) -> 0 | F101: =SUMIF(Lanç!$C$115:$C$6504,C101,Lanç!$F$115:$F$6504) -> 0 | G101: =SUMIF(Lanç!$C$115:$C$6504,C101,Lanç!$G$115:$G$6504) -> 0 | H101: =(F101)-(G101) -> 0 | I101: =(E101)+(H101) -> 0
...

Sheet Balanço
G1: =DBase!C6 -> Mbolo Yeto
B3: =DBase!B15 -> BALANÇO EM
B4: =DBase!F15 -> 46022
G6: Valores expressos em AKZ
B7: Designção | E7: Notas | F7: Exercicios
F8: =DBase!C4 -> 45658 | G8: =F8-1 -> 45657
B9: ACTIVO
B10: Activos não Correntes
B11: Imobilizações corpóreas | E11: 4 | F11: ='Blnct AR'!I6 -> 1.0202569e+08 | G11: ='Blnct AR'!E6 -> 86785921
B12: Imobilizações incorpóreas | E12: 5 | F12: ='Blnct AR'!I58 -> 5897900 | G12: ='Blnct AR'!E58 -> 5897900
B13: Amortizações Acumuladas | F13: ='Blnct AR'!I102 -> -68622217 | G13: ='Blnct AR'!E102 -> -68622217
B14: Outros activos não correntes | E14: 7 | F14: 0 | G14: 0
D15: Total dos Activos Não Correntes | F15: =SUM(F11:F14) -> 39301377 | G15: =SUM(G11:G14) -> 24061604
B17: Activos Correntes
B18: Existências | E18: 8 | F18: ='Blnct AR'!I147 -> 81037969 | G18: ='Blnct AR'!E147 -> 40682932
B19: Contas a Receber | E19: 9 | F19: =IF('Blnct AR'!I388>0,'Blnct AR'!I388,0)+IF('Blnct AR'!I1036>0,'Blnct AR'!I1036,0)+IF('Blnct AR'!I1135>0,'Blnct AR'!I1135,0)+IF('Blnct AR'!I1181>0,'Blnct AR'!I1181,0)+IF('Blnct AR'!I1419<0,'Blnct AR'!I1419,0) -> 2.1787692e+08 | G19: =IF('Blnct AR'!E388>0,'Blnct AR'!E388,0)+IF('Blnct AR'!E1036>0,'Blnct AR'!E1036,0)+IF('Blnct AR'!E1135>0,'Blnct AR'!E1135,0)+IF('Blnct AR'!E1181>0,'Blnct AR'!E1181,0)+IF('Blnct AR'!E1419<0,'Blnct AR'!E1419,0) -> 1.1135149e+08
B20: Disponibilidades | E20: 10 | F20: ='Blnct AR'!I1453 -> 30063528 | G20: ='Blnct AR'!E1453 -> 99141178
B21: Outros Acivos Correntes | E21: 11 | F21: =+(IF('Blnct AR'!I1245>0,'Blnct AR'!E1245,0)+(IF('Blnct AR'!I1267>0,'Blnct AR'!I1267,0)+(IF('Blnct AR'!I1280>0,'Blnct AR'!I1280,0)+IF('Blnct AR'!I1284>0,'Blnct AR'!I1284,0))+IF('Blnct AR'!I1294>0,'Blnct AR'!I1294,0)+IF('Blnct AR'!I1302>0,'Blnct AR'!I1302,0)+IF('Blnct AR'!I1309>0,'Blnct AR'!I1309,0)+IF('Blnct AR'!I1311>0,'Blnct AR'!I1311,0)+IF('Blnct AR'!I1321>0,'Blnct AR'!I1321,0))) -> 0 | G21: =+(IF('Blnct AR'!E1245>0,'Blnct AR'!E1245,0)+(IF('Blnct AR'!E1267>0,'Blnct AR'!E1267,0)+(IF('Blnct AR'!E1280>0,'Blnct AR'!E1280,0)+IF('Blnct AR'!E1284>0,'Blnct AR'!E1284,0))+IF('Blnct AR'!E1294>0,'Blnct AR'!E1294,0)+IF('Blnct AR'!E1302>0,'Blnct AR'!E1302,0)+IF('Blnct AR'!E1309>0,'Blnct AR'!E1309,0)+IF('Blnct AR'!E1311>0,'Blnct AR'!E1311,0)+IF('Blnct AR'!E1321>0,'Blnct AR'!E1321,0))) -> 0
D22: Total dos Activos Correntes | F22: =SUM(F18:F21) -> 3.2897842e+08 | G22: =SUM(G18:G21) -> 2.511756e+08
B24: TOTAL DO ACTIVO | F24: =F15+F22 -> 3.682798e+08 | G24: =G15+G22 -> 2.7523721e+08
B25: CAPITAL PRÓPRIO E PASSIVO
B27: Capital Próprio
B28: Capital | E28: 12 | F28: =-'Blnct AR'!I1539-'Blnct AR'!I1552 -> 17532640 | G28: =-'Blnct AR'!E1539-'Blnct AR'!E1552 -> 17532640
B29: Reservas | E29: 13 | F29: =-(IF('Blnct AR'!I1555<>0,'Blnct AR'!I1555,0)+IF('Blnct AR'!I1557<>0,'Blnct AR'!I1557,0)+IF('Blnct AR'!I1561<>0,'Blnct AR'!I1561,0)+IF('Blnct AR'!I1564<>0,'Blnct AR'!I1564,0)+IF('Blnct AR'!I1567<>0,'Blnct AR'!I1567,0)) -> 1309804.4 | G29: =-(IF('Blnct AR'!E1555<>0,'Blnct AR'!E1555,0)+IF('Blnct AR'!E1557<>0,'Blnct AR'!E1557,0)+IF('Blnct AR'!E1561<>0,'Blnct AR'!E1561,0)+IF('Blnct AR'!E1564<>0,'Blnct AR'!E1564,0)+IF('Blnct AR'!E1567<>0,'Blnct AR'!E1567,0)) -> 1309804.4
B30: Resultados Transitados | E30: 14 | F30: =-'Blnct AR'!I2194 -> -22179622 | G30: =-'Blnct AR'!E2213+-'Blnct AR'!E2217+-'Blnct AR'!E2219 -> -30112421
B31: Resultados do Exercicio | F31: =-'Blnct AR'!I2252 -> -14501165 | G31: =-'Blnct AR'!E2215 -> 7932798.8
D32: Total do Capital Próprio | F32: =SUM(F28:F31) -> -17838343 | G32: =SUM(G28:G31) -> -3337177.8
B34: TOTAL DE CAPITAIS PRÓPRIOS | F34: =F32 -> -17838343 | G34: =G32 -> -3337177.8
B36: Passivo não Corrente
B37: Empréstimos de Médio e Longo Prazo | E37: 15 | F37: =-IF('Blnct AR'!I1014<0,'Blnct AR'!I1014,0) -> 0 | G37: =-IF('Blnct AR'!E1014<0,'Blnct AR'!E1014,0) -> 0
B38: Impostos diferidos | E38: 16 | F38: 0 | G38: 0
B39: Provisões para pensões | E39: 17 | F39: =-(IF('Blnct AR'!I1442<0,'Blnct AR'!I1442,0)) -> 0 | G39: =-(IF('Blnct AR'!E1442<0,'Blnct AR'!E1442,0)) -> 0
B40: ='Blnct AR'!D1451 -> Provisões p/ outros riscos e encargos | E40: 18 | F40: =-(IF('Blnct AR'!I1451<0,'Blnct AR'!I1451,0)) -> 0 | G40: =-(IF('Blnct AR'!E1451<0,'Blnct AR'!E1451,0)) -> 0
B41: Outros passivos não correntes | E41: 19 | F41: 0 | G41: 0
D42: Total do Passivo não Corrente | F42: =SUM(F37:F41) -> 0 | G42: =SUM(G37:G41) -> 0
B44: Passivo Corrente
B45: Contas a Pagar | E45: 19 | F45: =-(IF('Blnct AR'!I694<0,'Blnct AR'!I694,0)+IF('Blnct AR'!I1036<0,'Blnct AR'!I1036,0)+IF('Blnct AR'!I1135<0,'Blnct AR'!I1135,0)+IF('Blnct AR'!I1181<0,'Blnct AR'!I1181,0)) -> 3.7444576e+08 | G45: =-(IF('Blnct AR'!E694<0,'Blnct AR'!E694,0)+IF('Blnct AR'!E1036<0,'Blnct AR'!E1036,0)+IF('Blnct AR'!E1135<0,'Blnct AR'!E1135,0)+IF('Blnct AR'!E1181<0,'Blnct AR'!E1181,0)) -> 2.66902e+08
B46: Empréstimos de Curto Prazo | E46: 20 | F46: =IF('Blnct AR'!E1009<0,'Blnct AR'!E1009,0) -> 0 | G46: =IF('Blnct AR'!E1009<0,'Blnct AR'!E1009,0) -> 0
B47: Outros Passivos Correntes | E47: 19 | F47: =-(IF('Blnct AR'!I1245<0,'Blnct AR'!I1245,0)+IF('Blnct AR'!I1267<0,'Blnct AR'!I1267,0)+IF('Blnct AR'!I1280<0,'Blnct AR'!I1280,0)+IF('Blnct AR'!I1284<0,'Blnct AR'!I1284,0)+IF('Blnct AR'!I1294<0,'Blnct AR'!I1294,0)+IF('Blnct AR'!I1302<0,'Blnct AR'!I1302,0)+IF('Blnct AR'!I1309<0,'Blnct AR'!I1309,0)+IF('Blnct AR'!I1311<0,'Blnct AR'!I1311,0+IF('Blnct AR'!I1321<0,'Blnct AR'!I1321,0))) -> 11672383 | G47: =-(IF('Blnct AR'!E1245<0,'Blnct AR'!E1245,0)+IF('Blnct AR'!E1267<0,'Blnct AR'!E1267,0)+IF('Blnct AR'!E1280<0,'Blnct AR'!E1280,0)+IF('Blnct AR'!E1284<0,'Blnct AR'!E1284,0)+IF('Blnct AR'!E1294<0,'Blnct AR'!E1294,0)+IF('Blnct AR'!E1302<0,'Blnct AR'!E1302,0)+IF('Blnct AR'!E1309<0,'Blnct AR'!E1309,0)+IF('Blnct AR'!E1311<0,'Blnct AR'!E1311,0+IF('Blnct AR'!E1321<0,'Blnct AR'!E1321,0))) -> 11672383
D48: Total do Passivo Corrente | F48: =SUM(F45:F47) -> 3.8611814e+08 | G48: =SUM(G45:G47) -> 2.7857438e+08
B50: TOTAL DO PASSIVO | F50: =F42+F48 -> 3.8611814e+08 | G50: =G42+G48 -> 2.7857438e+08
B52: TOTAL DO CAPITAL PRÓPRIO E PASSIVO | F52: =F34+F50 -> 3.682798e+08 | G52: =G34+G50 -> 2.7523721e+08 | I52: =F24-F52 -> 5.364418e-07 | J52: =G24-G52 -> 5.9604645e-07

Sheet D R
G1: =DBase!C6 -> Mbolo Yeto
B3: =DBase!B17 -> DEMONSTRAÇÃO DE RESULTADOS EM
B4: =DBase!F15 -> 46022
G6: Valores expressos em AKZ
B7: Designção | E7: Notas | F7: Exercicios
F8: =DBase!C4 -> 45658 | G8: =F8-1 -> 45657
B10: Vendas | E10: 22 | F10: =-'Blnct AR'!H2222 -> 82553815 | G10: 1.5561823e+08
B11: Prestação de Serviços | E11: 23 | F11: =-'Blnct AR'!H2223 -> 2.1847371e+08 | G11: 0
B12: Outros Proveitos | E12: 24 | F12: =-'Blnct AR'!H2224 -> 0 | G12: 1033342.2
D14: Total dos Proveitos e Ganhos Operacionais | F14: =SUM(F10:F12) -> 3.0102752e+08 | G14: =SUM(G10:G12) -> 1.5665157e+08
B16: Variação nos Prod. Acab. e em vias de fabr. | E16: 25 | F16: =-'Blnct AR'!H2225 -> 0 | G16: =-'Blnct AR'!E2225 -> 0
B17: Trabalhos para a Própria Empresa | E17: 26 | F17: =-'Blnct AR'!H2226 -> 0 | G17: =-'Blnct AR'!E2226 -> 0
B18: Custo das Exist. Vend. e das Mat-prim Cons. | E18: 27 | F18: =-'Blnct AR'!H2227 -> -48496258 | G18: -1.0563901e+08
B19: Custo com o pessoal | E19: 28 | F19: =-'Blnct AR'!H2228 -> -33038303 | G19: -29405897
B20: Amortizações | E20: 29 | F20: =-'Blnct AR'!H2229 -> 0 | G20: -12554881
B21: Outros Custos e perdas operacionais | E21: 30 | F21: =-'Blnct AR'!H2230 -> -2.1985272e+08 | G21: -65717293
D23: Total dos Custos e Perdas Operacionais | F23: =SUM(F16:F21) -> -3.0138728e+08 | G23: =SUM(G16:G21) -> -2.1331708e+08
B25: Resultados Operacionais | F25: =F14+F23 -> -359754.27 | G25: -56665509
B26: Resultados Financeiros | E26: 31 | F26: =-'Blnct AR'!H2254 -> -89656 | G26: -2087859.3
B27: Resultados de Filiais e Associadas | E27: 32 | F27: ='Blnct AR'!H2255 -> 0 | G27: 0
B28: Resultados não operacionais | E28: 33 | F28: =-'Blnct AR'!H2256 -> -14051754 | G28: 17078659
B29: Resultado antes de Impostos | F29: =SUM(F25:F28) -> -14501165 | G29: -41674709
B30: Imposto sobre o Rendimento | E30: 35 | F30: =-IF(F29>0,F29*30%,0) -> 0 | G30: 0
B31: Resultados Líq. das Actividades Correntes | F31: =IF(F30>0,F29-F30,F29+F30) -> -14501165 | G31: -41674709
B33: RESULTADOS LÍQUIDOS DO EXERCíCIO | F33: =F31 -> -14501165 | G33: =G31 -> -41674709

Sheet NDF
B2: NOTAS ÀS DEMONSTRAÇÕES FINANCEIRAS

Sheet NB
B2: NOTAS AO BALANÇO
I4: Aplicável / Não Aplicável
B6: 4 | C6: Imobilizações corpóreas | I6: =IF(Balanço!F11>0.1*Balanço!F28,"Aplicável","Não Aplicável") -> Aplicável
B8: 5 | C8: Imobilizações incorpóreas | I8: =IF(Balanço!F12>0.1*Balanço!F24,"Aplicável","Não Aplicável") -> Não Aplicável
B10: 6 | C10: Investimentos em subsidiárias e associadas | I10: =IF(Balanço!F13>0.1*Balanço!F24,"Aplicável","Não Aplicável") -> Não Aplicável
B12: 7 | C12: Outros activos não correntes | I12: =IF(Balanço!F14>0.1*Balanço!F24,"Aplicável","Não Aplicável") -> Não Aplicável
B14: 8 | C14: Existências | I14: =IF(Balanço!F18>0.1*Balanço!F24,"Aplicável","Não Aplicável") -> Aplicável
B16: 9 | C16: Outros ativos correntes e contas a receber | I16: =IF(Balanço!F19>0.1*Balanço!F24,"Aplicável","Não Aplicável") -> Aplicável
B18: 10 | C18: Disponibilidades | I18: =IF(Balanço!F20>0.1*Balanço!F24,"Aplicável","Não Aplicável") -> Não Aplicável
B20: 11 | C20: Outros ativos correntes | I20: =IF(Balanço!F21>0.1*Balanço!F24,"Aplicável","Não Aplicável") -> Não Aplicável
B22: 12 | C22: Capital | I22: =IF(Balanço!F28>0.1*Balanço!F24,"Aplicável","Não Aplicável") -> Não Aplicável
B24: 13 | C24: Reservas | I24: =IF(Balanço!F29>0.1*Balanço!F24,"Aplicável","Não Aplicável") -> Não Aplicável
B26: 14 | C26: Resultados transitados | I26: =IF(Balanço!F30>0.1*Balanço!F24,"Aplicável","Não Aplicável") -> Não Aplicável
B28: 15 | C28: Empréstimos de Médio e Longo Prazo | I28: =IF(Balanço!F37>0.1*Balanço!F24,"Aplicável","Não Aplicável") -> Não Aplicável
B30: 16 | C30: Impostos diferidos | I30: =IF(Balanço!F41>0.1*Balanço!F24,"Aplicável","Não Aplicável") -> Não Aplicável
B32: 17 | C32: Provisões para pensões | I32: =IF(Balanço!F42>0.1*Balanço!F24,"Aplicável","Não Aplicável") -> Não Aplicável
B34: 18 | C34: Provisões p/ outros riscos e encargos | I34: =IF(Balanço!F45>0.1*Balanço!F24,"Aplicável","Não Aplicável") -> Aplicável
B36: 19 | C36: Contas a Pagar | I36: =IF(Balanço!F49>0.1*Balanço!F24,"Aplicável","Não Aplicável") -> Não Aplicável
B38: 20 | C38: Empréstimos de Curto Prazo | I38: =IF(Balanço!F46>0.1*Balanço!F24,"Aplicável","Não Aplicável") -> Não Aplicável
B40: 21 | C40: Outros Passivos Correntes | I40: =IF(Balanço!F47>0.1*Balanço!F24,"Aplicável","Não Aplicável") -> Não Aplicável

Sheet NDR
B2: NOTAS À DEMONSTRAÇÃO DOS RESULTADOS
I4: Aplicável / Não Aplicável
B6: 22 | C6: Vendas | I6: =IF('D R'!F10>0.05*'D R'!F14,"Aplicável","Não Aplicável") -> Aplicável
B8: 23 | C8: Prestação de serviços | I8: =IF('D R'!F11>0.05*'D R'!F14,"Aplicável","Não Aplicável") -> Aplicável
B10: 24 | C10: Outros proveitos operacionais | I10: =IF('D R'!F12>0.05*'D R'!F14,"Aplicável","Não Aplicável") -> Não Aplicável
B12: 25 | C12: Variação nos prod. acab. e em vias de fabrico | I12: =IF('D R'!F16>0.05*'D R'!F14,"Aplicável","Não Aplicável") -> Não Aplicável
B14: 26 | C14: Trabalhos para a própria empresa | I14: =IF('D R'!F17>0.05*'D R'!F14,"Aplicável","Não Aplicável") -> Não Aplicável
B16: 27 | C16: Custos das merc. Vendidas e das mat. Consumidas | I16: =IF('D R'!F18>0.05*'D R'!F14,"Aplicável","Não Aplicável") -> Não Aplicável
B18: 28 | C18: Custos com pessoal | I18: =IF('D R'!F19>0.05*'D R'!F14,"Aplicável","Não Aplicável") -> Não Aplicável
B20: 29 | C20: Amortizações | I20: =IF('D R'!F20>0.05*'D R'!F14,"Aplicável","Não Aplicável") -> Não Aplicável
B22: 30 | C22: Outros custos e perdas operacionais | I22: =IF('D R'!F21>0.05*'D R'!F14,"Aplicável","Não Aplicável") -> Não Aplicável
B24: 31 | C24: Resultados financeiros | I24: =IF('D R'!F26>0.05*'D R'!F14,"Aplicável","Não Aplicável") -> Não Aplicável
B26: 32 | C26: Resultados de filiais e associadas | I26: =IF('D R'!F275%*'D R'!F14,"Aplicável","Não Aplicável") -> Não Aplicável
B28: 33 | C28: Resultados não operacionais | I28: =IF('D R'!F28>0.05*'D R'!F14,"Aplicável","Não Aplicável") -> Não Aplicável
B30: 34 | C30: Resultado Extraordinários | I30: =IF('D R'!F32>0.05*'D R'!F14,"Aplicável","Não Aplicável") -> Não Aplicável
B32: 35 | C32: Imposto sobre o Rendimento | I32: =IF('D R'!F30>0.05*'D R'!F14,"Aplicável","Não Aplicável") -> Não Aplicável

Sheet NB4 IC
A2: 4 | B2: Imobilizações corpóreas
A4: 4.1 | B4: Composição
B6: Rubricas | F6: Valor Bruto | H6: Amortizações Acumuladas | J6: Valor Líquido
B7: Terrenos e Recursos Naturais | F7: ='Blnct AR'!E7 -> 0 | H7: =-'Blnct AR'!I104 -> 0 | J7: =F7-H7 -> 0
B8: Edificios e outras Construções | F8: ='Blnct AR'!E15 -> 33771041 | H8: =-'Blnct AR'!I105 -> 23837407 | J8: =F8-H8 -> 9933633.3
B9: Equipamento básico | F9: ='Blnct AR'!I23 -> 16670973 | H9: =-'Blnct AR'!I106 -> 7966128.4 | J9: =F9-H9 -> 8704844.7
B10: Equipamento de carga e transporte | F10: ='Blnct AR'!E31 -> 30341500 | H10: =-'Blnct AR'!I107 -> 26408167 | J10: =F10-H10 -> 3933333.3
B11: Equipamento administrativo | F11: ='Blnct AR'!I44 -> 7513156.9 | H11: =-'Blnct AR'!I110 -> 4654722.3 | J11: =F11-H11 -> 2858434.6
B12: Taras e vasilhame | F12: ='Blnct AR'!E52 -> 0 | H12: =-'Blnct AR'!F116 -> 0 | J12: =F12-H12 -> 0
B13: Outras imobilizações corpóreas | F13: ='Blnct AR'!E55 -> 117408.44 | H13: =-'Blnct AR'!$I$117 -> 86451 | J13: =F13-H13 -> 30957.44
B14: Imobilizações em curso | F14: ='Blnct AR'!E91 -> 0 | J14: =F14-H14 -> 0
B15: Adiantamentos p/conta imob.corporeo | F15: ='Blnct AR'!E94 -> 0 | J15: =F15-H15 -> 0
B16: Total | F16: =SUM(F7:G15) -> 88414079 | H16: =SUM(H7:I15) -> 62952876 | J16: =SUM(J7:K14) -> 25461203
A18: 4.2 | B18: Movimentos, ocorridos durante o exercício, no valor bruto
B20: Rubricas | F20: Saldo Inicial | H20: Reavaliações | J20: Aumentos | L20: Alienações | N20: Transf. / Abates | P20: Saldo Final
B21: Terrenos e Recursos Naturais | F21: ='Blnct AR'!E7 -> 0 | H21: ='Blnct AR'!F7 -> 0 | J21: ='Blnct AR'!F7 -> 0 | L21: ='Blnct AR'!G7 -> 0 | N21: ='Blnct AR'!$F$2158 -> 0 | P21: =F21+H21+J21-L21-N21 -> 0
B22: Edificios e outras Construções | F22: ='Blnct AR'!E15 -> 33771041 | J22: ='Blnct AR'!F15 -> 0 | L22: ='Blnct AR'!G15 -> 0 | N22: 0 | P22: =F22+H22+J22-L22-N22 -> 33771041
B23: Equipamento básico | F23: ='Blnct AR'!E23 -> 15470973 | J23: ='Blnct AR'!F23 -> 1200000 | L23: ='Blnct AR'!G23 -> 0 | N23: 0 | P23: =F23+H23+J23-L23-N23 -> 16670973
B24: Equipamento de carga e transporte | F24: ='Blnct AR'!E31 -> 30341500 | J24: ='Blnct AR'!F31 -> 13611616 | L24: ='Blnct AR'!G31 -> 0 | N24: 0 | P24: =F24+H24+J24-L24-N24 -> 43953116
B25: Equipamento administrativo | F25: ='Blnct AR'!E44 -> 7084999.1 | J25: ='Blnct AR'!F44 -> 428157.75 | L25: ='Blnct AR'!G44 -> 0 | N25: 0 | P25: =F25+H25+J25-L25-N25 -> 7513156.9
B26: Taras e vasilhame | F26: ='Blnct AR'!E52 -> 0 | J26: ='Blnct AR'!F52 -> 0 | L26: ='Blnct AR'!G52 -> 0 | N26: 0 | P26: =F26+H26+J26-L26-N26 -> 0
B27: Outras imobilizações corpóreas | F27: ='Blnct AR'!E55 -> 117408.44 | J27: ='Blnct AR'!F55 -> 0 | L27: ='Blnct AR'!G55 -> 0 | N27: 0 | P27: =F27+H27+J27-L27-N27 -> 117408.44
B28: Imobilizações em curso | F28: ='Blnct AR'!E91 -> 0 | P28: =F28+H28+J28-L28-N28 -> 0
B29: Adiantamentos p/conta imob.corporeo | F29: ='Blnct AR'!E94 -> 0 | P29: =F29+H29+J29-L29-N29 -> 0
B30: Total | F30: =SUM(F21:G28) -> 86785921 | H30: =SUM(H21:I28) -> 0 | J30: =SUM(J21:K28) -> 15239773 | L30: =SUM(L21:M28) -> 0 | N30: =SUM(N21:O28) -> 0 | P30: =SUM(P21:Q28) -> 1.0202569e+08
A32: 4.3 | B32: Movimentos, ocorridos durante o exercício, nas amortizações acumuladas
B34: Rubricas | F34: Saldo Inicial | H34: Reavaliações | J34: Reforços | L34: Alienações | N34: Transferências Abates | P34: Saldo Final
B35: Terrenos e Recursos Naturais | F35: =-'Blnct AR'!E104 -> 0 | H35: ='Blnct AR'!G104 -> 0 | L35: ='Blnct AR'!G7 -> 0 | N35: 0 | P35: =F35+H35+J35-L35-N35 -> 0
B36: Edificios e outras Construções | F36: =-'Blnct AR'!E105 -> 23837407 | J36: ='Blnct AR'!F1920 -> 0 | L36: ='Blnct AR'!F105 -> 0 | N36: 0 | P36: =F36+H36+J36-L36-N36 -> 23837407
B37: Equipamento básico | F37: =-'Blnct AR'!E106 -> 7966128.4 | J37: ='Blnct AR'!F1921 -> 0 | L37: ='Blnct AR'!F106 -> 0 | N37: 0 | P37: =F37+H37+J37-L37-N37 -> 7966128.4
B38: Equipamento de carga e transporte | F38: =-'Blnct AR'!E107 -> 26408167 | J38: ='Blnct AR'!F1922 -> 0 | L38: ='Blnct AR'!F107 -> 0 | N38: 0 | P38: =F38+H38+J38-L38-N38 -> 26408167
B39: Equipamento administrativo | F39: =-'Blnct AR'!$E$110 -> 4654722.3 | J39: ='Blnct AR'!F1923 -> 0 | L39: ='Blnct AR'!F109 -> 0 | N39: 0 | P39: =F39+H39+J39-L39-N39 -> 4654722.3
B40: Taras e vasilhame | F40: =-'Blnct AR'!E116 -> 0 | J40: ='Blnct AR'!F1924 -> 0 | L40: ='Blnct AR'!F116 -> 0 | N40: 0
B41: Outras imobilizações corpóreas | F41: =-'Blnct AR'!E117 -> 86451 | J41: ='Blnct AR'!$G$117 -> 0 | L41: ='Blnct AR'!F117 -> 0 | N41: 0 | P41: =F41+H41+J41-L41-N41 -> 86451
B42: Total | F42: =SUM(F35:G41) -> 62952876 | H42: =SUM(H35:I41) -> 0 | J42: =SUM(J35:K41) -> 0 | L42: =SUM(L35:M41) -> 0 | N42: =SUM(N35:O41) -> 0 | P42: =SUM(P35:Q41) -> 62952876

Sheet NB5 IInc
A2: 5 | B2: Imobilizações Incorpóreas
A4: 5.1 | B4: Composição
B6: Rubricas | F6: Valor Bruto | H6: Amortizações Acumuladas | J6: Valor Líquido
B7: Trespasses | F7: ='Blnct AR'!E60 -> 0 | H7: ='Blnct AR'!E119 -> 0 | J7: =SUM(F7:I7) -> 0
B8: Desp.investiga. e desenvolvimento | F8: ='Blnct AR'!E62 -> 0 | H8: ='Blnct AR'!E120 -> 0 | J8: =SUM(F8:I8) -> 0
B9: Propriedade industrial e outros | F9: ='Blnct AR'!E64 -> 0 | H9: ='Blnct AR'!E121 -> 0 | J9: =SUM(F9:I9) -> 0
B10: Despesas de constituição | F10: ='Blnct AR'!E66 -> 4180500 | H10: ='Blnct AR'!E122 -> 0 | J10: =SUM(F10:I10) -> 4180500
B11: Outras imobilizações incorporeas | F11: ='Blnct AR'!E68 -> 1717400 | H11: ='Blnct AR'!I118 -> -5669341.6 | J11: =SUM(F11:I11) -> -3951941.6
B12: Total | F12: =SUM(F7:G11) -> 5897900 | H12: =SUM(H7:I11) -> -5669341.6 | J12: =SUM(J7:K11) -> 228558.36
A14: 5.2 | B14: Movimentos, ocorridos durante o exercício, no valor bruto
B16: Rubricas | F16: Saldo Inicial | H16: Aumentos | J16: Diminuições | L16: Saldo Final
B17: Trespasses | F17: ='Blnct AR'!E60 -> 0 | H17: ='Blnct AR'!F60 -> 0 | J17: ='Blnct AR'!G60 -> 0 | L17: =F17+H17-J17 -> 0
B18: Desp.investiga. e desenvolvimento | F18: ='Blnct AR'!E62 -> 0 | H18: ='Blnct AR'!F62 -> 0 | J18: ='Blnct AR'!G62 -> 0 | L18: =F18+H18-J18 -> 0
B19: Propriedade industrial e outros | F19: ='Blnct AR'!E64 -> 0 | H19: ='Blnct AR'!F64 -> 0 | J19: ='Blnct AR'!G64 -> 0 | L19: =F19+H19-J19 -> 0
B20: Despesas de constituição | F20: ='Blnct AR'!E66 -> 4180500 | H20: ='Blnct AR'!F66 -> 0 | J20: ='Blnct AR'!G66 -> 0 | L20: =F20+H20-J20 -> 4180500
B21: Outras imobilizações incorporeas | F21: ='Blnct AR'!E68 -> 1717400 | H21: ='Blnct AR'!F68 -> 0 | J21: ='Blnct AR'!G68 -> 0 | L21: =F21+H21-J21 -> 1717400
B22: Total | F22: =SUM(F17:G21) -> 5897900 | H22: =SUM(H17:I21) -> 0 | J22: =SUM(J17:K21) -> 0 | L22: =SUM(L17:M21) -> 5897900
A24: 5.3 | B24: Movimentos, ocorridos durante o exercício, nas amortizações acumuladas
B26: Rubricas | F26: Saldo Inicial | H26: Aumentos | J26: Diminuições | L26: Saldo Final
B27: Trespasses | F27: ='Blnct AR'!E119 -> 0 | H27: ='Blnct AR'!F1927 -> 0 | J27: ='Blnct AR'!G1927 -> 0 | L27: =F27+H27-J27 -> 0
B28: Desp.investiga. e desenvolvimento | F28: ='Blnct AR'!E120 -> 0 | H28: ='Blnct AR'!F1928 -> 0 | J28: ='Blnct AR'!G1928 -> 0 | L28: =F28+H28-J28 -> 0
B29: Propriedade industrial e outros | F29: ='Blnct AR'!E121 -> 0 | H29: ='Blnct AR'!F1929 -> 0 | J29: ='Blnct AR'!G1929 -> 0 | L29: =F29+H29-J29 -> 0
B30: Despesas de constituição | F30: ='Blnct AR'!E122 -> 0 | H30: ='Blnct AR'!F1930 -> 0 | J30: ='Blnct AR'!G1930 -> 0 | L30: =F30+H30-J30 -> 0
B31: Outras imobilizações incorporeas | F31: =-'Blnct AR'!E123 -> 5669341.6 | H31: ='Blnct AR'!F1931 -> 0 | J31: ='Blnct AR'!G1931 -> 0 | L31: =F31+H31-J31 -> 5669341.6
B32: Total | F32: =SUM(F27:G31) -> 5669341.6 | H32: =SUM(H27:I31) -> 0 | J32: =SUM(J27:K31) -> 0 | L32: =SUM(L27:M31) -> 5669341.6

Sheet NB8a19
A2: 8 | B2: Existências
A4: 8.1 | B4: Composição
B6: Rubricas | F6: Valor Bruto | H6: Provisões Acumuladas | J6: Valor Líquido
B7: Materias-primas, subs. e de consumo | F7: ='Blnct AR'!I308+'Blnct AR'!I148 -> 65207882 | J7: =F7+H7 -> 65207882
B8: Produtos e trabalhos em curso | F8: ='Blnct AR'!I325 -> 0 | J8: =F8+H8 -> 0
B9: Produtos acabados e intermédios | F9: ='Blnct AR'!I328 -> 0 | J9: =F9+H9 -> 0
B10: Sub-produtos, desp., resíd. e refugos | F10: ='Blnct AR'!I335 -> 0 | J10: =F10+H10 -> 0
B11: Mercadorias | F11: ='Blnct AR'!I340 -> 4500000 | J11: =F11+H11 -> 4500000
B12: Mat. primas, merc. e materiais em trans. | F12: ='Blnct AR'!I352 -> 11330087 | J12: =F12+H12 -> 11330087
B13: Total | F13: =SUM(F7:G12) -> 81037969 | H13: =SUM(H7:I12) -> 0 | J13: =SUM(J7:K12) -> 81037969
A15: 8.2 | B15: Movimentos, ocorridos durante o exercício, nas provisões
B17: Rubricas | F17: Saldo Inicial | H17: Aumentos | J17: Diminuições | L17: Saldo Final
B18: Materias-primas, subs. e de consumo | F18: ='Blnct AR'!E377 -> 0 | H18: ='Blnct AR'!F377 -> 0 | J18: ='Blnct AR'!G377 -> 0 | L18: =F18+H18-J18 -> 0
B19: Produtos e trabalhos em curso | F19: ='Blnct AR'!E379 -> 0 | H19: ='Blnct AR'!F379 -> 0 | J19: ='Blnct AR'!G379 -> 0 | L19: =F19+H19-J19 -> 0
B20: Produtos acabados e intermédios | F20: ='Blnct AR'!E381 -> 0 | H20: ='Blnct AR'!F381 -> 0 | J20: ='Blnct AR'!G381 -> 0 | L20: =F20+H20-J20 -> 0
B21: Sub-produtos, desp., resíd. e refugos | F21: ='Blnct AR'!E383 -> 0 | H21: ='Blnct AR'!F383 -> 0 | J21: ='Blnct AR'!G383 -> 0 | L21: =F21+H21-J21 -> 0
B22: Mercadorias | F22: ='Blnct AR'!E340 -> 0 | H22: ='Blnct AR'!F340 -> 4500000 | J22: ='Blnct AR'!G340 -> 0 | L22: =F22+H22-J22 -> 4500000
B23: Mat. primas, merc. e materiais em trans. | F23: 0 | H23: 0 | J23: 0 | L23: =F23+H23-J23 -> 0
B24: Total | F24: =SUM(F18:G23) -> 0 | H24: =SUM(H18:I23) -> 4500000 | J24: =SUM(J18:K23) -> 0 | L24: =SUM(L18:M23) -> 4500000
A26: 9 | B26: Outros activos correntes e contas a receber
B28: Rubricas | F28: Corrente | H28: Total
B29: Valor Bruto
B30: Clientes correntes | F30: =IF('Blnct AR'!I389>0,'Blnct AR'!I389,0) -> 1.8592921e+08 | H30: =F30 -> 1.8592921e+08
B31: Clientes-titulos a receber | F31: =IF('Blnct AR'!I522>0,'Blnct AR'!I522,0) -> 0 | H31: =F31 -> 0
B32: Clientes Retenções | F32: =IF('Blnct AR'!I556>0,'Blnct AR'!I556,0) -> 24840655 | H32: =F32 -> 24840655
B33: Clientes de cobrança duvidosa | F33: =IF('Blnct AR'!I574>0,'Blnct AR'!I574,0) -> 32608955 | H33: =F33 -> 32608955
B34: Fornecedores-saldos devedores | F34: =IF('Blnct AR'!I952>0,'Blnct AR'!I952,0)*0 -> 0 | H34: =F34 -> 0
B35: Estado | F35: =IF('Blnct AR'!I1036>0,'Blnct AR'!I1036,0) -> 0 | H35: =F35 -> 0
B36: Participantes e Participadas | F36: =IF('Blnct AR'!I1136>0,'Blnct AR'!I1136,0) -> 0 | H36: =F36 -> 0
B37: Pessoal | F37: =IF('Blnct AR'!I1181>0,'Blnct AR'!I1181,0) -> 0 | H37: =F37 -> 0
B38: Devedores - vendas de imobilizado | F38: =IF('Blnct AR'!I1267>0,'Blnct AR'!I1267,0) -> 0 | H38: =F38 -> 0
B39: Outros devedores | F39: =IF('Blnct AR'!I1321>0,'Blnct AR'!I1321,0) -> 0 | H39: =F39 -> 0
B40: Provisões para cobranças duvidosas | F40: ='Blnct AR'!$I$1429 -> -2919625.5 | H40: =F40 -> -2919625.5
B41: Total | F41: =SUM(F30:G40) -> 2.4045919e+08 | H41: =SUM(H30:I40) -> 2.4045919e+08
A43: 10 | B43: Disponibilidades
B45: Rubricas | F45: =DBase!C4 -> 45658 | H45: =F45-1 -> 45657
B46: Títulos Negociáveis | F46: ='Blnct AR'!I1454 -> 0 | H46: ='Blnct AR'!E1454 -> 0
B47: Depósitos a prazo | F47: ='Blnct AR'!I1465 -> 250000 | H47: ='Blnct AR'!E1465 -> 250000
B48: Depósitos à ordem | F48: ='Blnct AR'!I1476 -> 29822829 | H48: ='Blnct AR'!E1476 -> 95694617
B49: Caixa | F49: ='Blnct AR'!I1500 -> 335884.98 | H49: ='Blnct AR'!E1500 -> 3541747.6
B50: Conta Transitória | F50: ='Blnct AR'!I1525 -> -345186.44 | H50: ='Blnct AR'!E1525 -> -345186.44
B51: Total | F51: =SUM(F46:G50) -> 30063528 | H51: =SUM(H46:I50) -> 99141178
A53: 11 | B53: Outros activos correntes
B55: Rubricas | F55: =DBase!C4 -> 45658 | H55: =F55-1 -> 45657
B56: Proveitos a facturar:
B57: Contratos plrianuais em curso
B58: Encargos a repartir por exercicios futuros:
B59: Seguros | F59: ='Blnct AR'!I1287 -> 0 | H59: ='Blnct AR'!E1287 -> 0
B60: Outros encargos | F60: ='Blnct AR'!I1291+'Blnct AR'!I1292 -> 0 | H60: ='Blnct AR'!E1291+'Blnct AR'!I1292 -> 0
B61: Total | F61: =SUM(F56:G60) -> 0 | H61: =SUM(H56:I60) -> 0
A63: 12.1 | B63: Capital
B65: Rubricas | F65: Saldo Inicial | H65: Aumentos | J65: Diminuições | L65: Saldo Final
B66: Capital | F66: ='Blnct AR'!E1538 -> -4250000 | H66: ='Blnct AR'!G1538 -> 0 | J66: ='Blnct AR'!F1538 -> 0 | L66: =F66+H66-J66 -> -4250000
B67: Ações / Quotas próprias | F67: ='Blnct AR'!E1543 -> 0 | H67: ='Blnct AR'!G1543 -> 0 | J67: ='Blnct AR'!F1543 -> 0 | L67: =F67+H67-J67 -> 0
B68: Prémios de emissão | F68: ='Blnct AR'!E1550 -> 0 | H68: ='Blnct AR'!G1550 -> 0 | J68: ='Blnct AR'!F1550 -> 0 | L68: =F68+H68-J68 -> 0
B69: Prestações suplementares | F69: ='Blnct AR'!E1552 -> -13282640 | H69: ='Blnct AR'!G1552 -> 0 | J69: ='Blnct AR'!F1552 -> 0 | L69: =F69+H69-J69 -> -13282640
E70: Total | F70: =SUM(F66:G69) -> -17532640 | H70: =SUM(H66:I69) -> 0 | J70: =SUM(J66:K69) -> 0 | L70: =SUM(L66:M69) -> -17532640
A72: 12.2 | B72: Capital
B74: Rubricas | F74: Saldo Inicial | H74: Aumentos | J74: Diminuições | L74: Saldo Final
B75: Sócios/Acionistas com participação superior a 20%
B76: UEM - Unidade de Estruturas Metálicas, Lda | F76: ='Blnct AR'!E1540 -> -3825000 | H76: ='Blnct AR'!G1543 -> 0 | J76: ='Blnct AR'!F1543 -> 0 | L76: =F76+H76-J76 -> -3825000
B77: Sócios/Acionistas com participação inferior a 20%
B78: António Gameiro | F78: ='Blnct AR'!E1542 -> -425000 | H78: ='Blnct AR'!G1552 -> 0 | J78: ='Blnct AR'!F1552 -> 0 | L78: =F78+H78-J78 -> -425000
E79: Total | F79: =SUM(F75:G78) -> -4250000 | H79: =SUM(H75:I78) -> 0 | J79: =SUM(J75:K78) -> 0 | L79: =SUM(L75:M78) -> -4250000
A81: 15 | B81: Empréstimos correntes e não correntes
A83: 15.1 | B83: Composição
B85: Rubricas | F85: Corrente | H85: Vencível até 5 anos | J85: Vencível a mais de 5 anos | L85: Total
B86: Emprestimos bancários | F86: ='Blnct AR'!E1009 -> 0 | H86: =-'Blnct AR'!I1014 -> 0 | L86: =SUM(F86:K86) -> 0
B87: Emprestimos por obrigações | F87: ='Blnct AR'!E1019 -> 0
B88: Emprestimos p/tittulos de partic. | F88: ='Blnct AR'!E1026 -> 0
B89: Outros emprestimos | F89: ='Blnct AR'!E1029 -> 0
E90: Total | F90: =SUM(F86:G89) -> 0 | H90: =SUM(H86:I89) -> 0 | J90: =SUM(J86:K89) -> 0 | L90: =SUM(L86:M89) -> 0
A92: 15.2 | B92: Movimentos, ocorridos durante o exercício
B94: Rubricas | F94: Saldo Inicial | H94: Aumentos | J94: Diminuições | L94: Saldo Final
B95: Emprestimos bancários | F95: =-'Blnct AR'!E1007 -> 0 | H95: ='Blnct AR'!G1007 -> 0 | J95: ='Blnct AR'!F1007 -> 0 | L95: =F95+H95-J95 -> 0
B96: Emprestimos por obrigações | F96: ='Blnct AR'!E1019 -> 0 | H96: ='Blnct AR'!G1019 -> 0 | J96: ='Blnct AR'!F1019 -> 0 | L96: =F96+H96-J96 -> 0
B97: Emprestimos p/tittulos de partic. | F97: ='Blnct AR'!E1026 -> 0 | H97: ='Blnct AR'!G1026 -> 0 | J97: ='Blnct AR'!F1026 -> 0 | L97: =F97+H97-J97 -> 0
B98: Outros emprestimos | F98: ='Blnct AR'!E1029 -> 0 | H98: ='Blnct AR'!G1029 -> 0 | J98: ='Blnct AR'!F1029 -> 0 | L98: =F98+H98-J98 -> 0
E99: Total | F99: =SUM(F95:G98) -> 0 | H99: =SUM(H95:I98) -> 0 | J99: =SUM(J95:K98) -> 0 | L99: =F99+H99-J99 -> 0
A101: 19 | B101: Outros passivos correntes e contas a pagar
B103: Rubricas | F103: Corrente | H103: Total
B104: Fornecedores correntes | F104: =-IF('Blnct AR'!I694<0,'Blnct AR'!I694,0) -> 3.5029738e+08 | H104: =F104 -> 3.5029738e+08
B105: Fornecedores-titulos a pagar | F105: =-IF('Blnct AR'!I924<0,'Blnct AR'!I924,0) -> 0 | H105: =F105 -> 0
B106: Clientes-saldos credores | F106: =-IF('Blnct AR'!I586<0,'Blnct AR'!I586,0) -> 22582270 | H106: =F106 -> 22582270
B107: Estado | F107: =-IF('Blnct AR'!I1036<0,'Blnct AR'!I1036,0) -> 16260073 | H107: =F107 -> 16260073
B108: Participantes e Participadas | F108: =-IF('Blnct AR'!I1135<0,'Blnct AR'!I1135,0) -> 3443669.7 | H108: =F108 -> 3443669.7
B109: Pessoal | F109: =-IF('Blnct AR'!I1181<0,'Blnct AR'!I1181,0) -> 4444632 | H109: =F109 -> 4444632
B110: Credores - compras de imobilizado | F110: =-IF('Blnct AR'!I1245<0,'Blnct AR'!I1245,0) -> 9345414.3 | H110: =F110 -> 9345414.3
B111: Outros devedores | F111: =-IF('Blnct AR'!I1294<0,'Blnct AR'!I1294,0)-IF('Blnct AR'!I1321<0,'Blnct AR'!I1321,0) -> 2326968.3 | H111: =F111 -> 2326968.3
B112: Total | F112: =SUM(F104:G111) -> 4.0870041e+08 | H112: =SUM(H104:I111) -> 4.0870041e+08

Sheet NDR22a35
A2: 22 | B2: Vendas
B4: Rubricas | F4: =DBase!C4 -> 45658 | H4: =F4-1 -> 45657
B5: Mercado interno
B6: Vendas | F6: ='Blnct AR'!G1571 -> 95353815
B7: Subsídios a preços | F7: ='Blnct AR'!G1080 -> 0
B8: Mercado externo | F8: ='Blnct AR'!G1584 -> 0
B9: Total | F9: =SUM(F6:G8) -> 95353815
A11: 23 | B11: Prestação de serviços
B13: Rubricas | F13: =DBase!C4 -> 45658 | H13: =F13-1 -> 45657
B14: Mercado interno | F14: ='Blnct AR'!G1636 -> 2.1847371e+08
B15: Mercado externo | F15: ='Blnct AR'!G1637 -> 0
B16: Total | F16: =SUM(F14:G15) -> 2.1847371e+08 | H16: =SUM(H14:I15) -> 0
A18: 27 | B18: Custo das existências vendidas e das matérias-primas e subsidiárias consumidas
B20: Rubricas | F20: Existências iniciais | H20: Compras | J20: Ofertas e perdas ou ganhos | L20: Existências finais | N20: Custo no ano
B21: Matérias-primas, subsidiárias e de consumo | F21: ='Blnct AR'!E147 -> 40682932 | H21: =L21+N21-F21 -> 88851295 | J21: =SUM('Blnct AR'!I1742,'Blnct AR'!F2133) -> 0 | L21: ='Blnct AR'!$I$147 -> 81037969 | N21: ='Blnct AR'!$I$1807 -> 48496258
B22: Mercadorias | F22: ='Blnct AR'!E341 -> 0 | H22: ='Blnct AR'!F341 -> 4500000 | J22: =SUM('Blnct AR'!I2137,'Blnct AR'!I2060,'Blnct AR'!I1746) -> 0 | L22: ='Blnct AR'!I341 -> 4500000 | N22: =F22+H22-J22-L22 -> 0
B23: Total | F23: =SUM(F21:G22) -> 40682932 | H23: =SUM(H21:I22) -> 93351295 | J23: =SUM(J21:K22) -> 0 | L23: =SUM(L21:M22) -> 85537969 | N23: =SUM(N21:O22) -> 48496258
A25: 28 | B25: Custos com o pessoal
B27: Rubricas | F27: =DBase!C4 -> 45658 | H27: =F27-1 -> 45657
B28: Remunerações do pessoal | F28: =SUM('Blnct AR'!F1831,'Blnct AR'!F1879) -> 28034340
B29: Seguros acidente trab.doenç.prof. | F29: ='Blnct AR'!F1883 -> 0
B30: Formação | F30: ='Blnct AR'!F1888 -> 0
B31: Outros despesas com pessoal | F31: ='Blnct AR'!F1893 -> 5003962.5
B32: Total | F32: =SUM(F28:G31) -> 33038303 | H32: =SUM(H30:I31) -> 0
H33: =DBase!D12 -> 1
A35: 30 | B35: Outros custos e perdas operacionais
B37: Rubricas | F37: =DBase!C4 -> 45658 | H37: =F37-1 -> 45657
B38: Subcontratos | F38: ='Blnct AR'!I1934 -> 51542270
B39: Fornecimento e serviço de terceiros | F39: ='Blnct AR'!I2016+'Blnct AR'!I2026+'Blnct AR'!I2038 -> 92283684
B40: Água e Combustíveis | F40: ='Blnct AR'!$I$1946 -> 2072681.3
B41: Conservação e reparação | F41: ='Blnct AR'!I1955+'Blnct AR'!I1995 -> 38729353
B42: Comunicação | F42: ='Blnct AR'!$I$1969 -> 1459803.5
B43: Rendas e alugueres | F43: ='Blnct AR'!$I$1974 -> 14179508
B44: Seguros | F44: ='Blnct AR'!$I$1982 -> 972249.06
B45: Deslocações e estadas | F45: ='Blnct AR'!I1987 -> 12749394
B46: Impostos | F46: ='Blnct AR'!I2040 -> 1752340
B47: Ofertas e amostras de existências | F47: ='Blnct AR'!I2060 -> 0
B48: Custos e perdas operacionais | F48: ='Blnct AR'!I2061 -> 0
B49: Total | F49: =SUM(F38:G48) -> 2.1574128e+08 | H49: =SUM(H40:I48,H38) -> 0
A51: 31 | B51: Resultados financeiros
B53: Rubricas | F53: =DBase!C4 -> 45658 | H53: =F53-1 -> 45657
B54: Proveitos e ganhos financeiros
B55: Juros
B56: Investimentos financeiros | F56: =-'Blnct AR'!I1689 -> 0
B57: Outros | F57: ='Blnct AR'!I1694 -> 0
B58: Rendimentos de investimentos em imóveis
B59: Investimentos financeiros | F59: ='Blnct AR'!I1705 -> 0
B60: Outros | F60: 0
B61: Rendimentos de participações de capital
B62: Investimentos financeiros | F62: ='Blnct AR'!I1707 -> 0
B63: Outros | F63: 0
B64: Ganhos na alienação de participações financeiras
B65: Investimentos financeiros | F65: ='Blnct AR'!I1712 -> 0
B66: Outros | F66: ='Blnct AR'!$I$1718 -> 0
B67: Reposição de provisões (a)
B68: Investimentos em filiais e associadas (Nota 6) | F68: ='Blnct AR'!I1734 -> 0
B69: Outros ativos financeiros (Nota 7) | F69: 0
B70: Disponibilidades (Nota 10) | F70: ='Blnct AR'!G1728 -> 0
B71: Diferenças de câmbio favoráveis
B72: Realizadas | F72: ='Blnct AR'!I1701 -> 0
B73: Realizadas | F73: =-'Blnct AR'!$H$1701 -> 0
B74: Descontos de pronto pagamento obtidos | F74: ='Blnct AR'!I1703 -> 0
B75: Outros | F75: ='Blnct AR'!I1739 -> 0
B76: Custos e perdas financeiros
B77: Juros | F77: =-'Blnct AR'!I2067 -> 0
B78: Amortizações de investimentos em imóveis | F78: ='Blnct AR'!I2084 -> 0
B79: Provisões para aplicações financeiras
B80: Investimentos em filiais e associadas (Nota 6) | F80: ='Blnct AR'!I2128 -> 0
B81: Outros ativos financeiros (Nota 7) | F81: ='Blnct AR'!I2098 -> 0
B82: Disponibilidades (Nota 10) | F82: ='Blnct AR'!I2093 -> 0
B83: Perdas na alienação de aplicações financeiras
B84: Investimentos financeiros | F84: ='Blnct AR'!I2099 -> 0
B85: Outros | F85: ='Blnct AR'!I2104 -> 0
B86: Diferenças de câmbio desfavoráveis
B87: Realizadas | F87: =-'Blnct AR'!I2080 -> 0
B88: Não realizadas | F88: ='Blnct AR'!I2081 -> 0
B89: Descontos de pronto pagamento concedidos | F89: ='Blnct AR'!I2082 -> 0
B90: Outros | F90: =-'Blnct AR'!I2106 -> -89656
B92: Total | F92: =SUM(F56,F73,F77,F90,F87,F89,F78) -> -89656

Sheet Flx CX
G1: =#REF! -> #REF!
B3: =#REF! -> #REF!
B4: =#REF! -> #REF!
G6: Valores expressos em AKZ
B7: Designção | E7: Notas | F7: Exercicios
F8: 2015 | G8: 2014
B9: Fluxo de caixa das atividades operacionais
B10: Recebimentos de Clientes
B11: Pagamentos a fornecedores e empregados
D12: Caixa gerada pelas operações | F12: =F10-F11 -> 0 | G12: =G10-G11 -> 0
B14: Juros pagos | F14: ='Blnct AR'!I147 -> 81037969 | G14: 1072415
B15: Impostos sobre os lucros pagos | F15: =IF('Blnct AR'!I389>0,'Blnct AR'!I389,0)+IF('Blnct AR'!I541>0,'Blnct AR'!I541,0)+IF('Blnct AR'!I522>0,'Blnct AR'!I522,0)+IF('Blnct AR'!I553>0,'Blnct AR'!I553,0)+IF('Blnct AR'!I574>0,'Blnct AR'!I574,0)+IF('Blnct AR'!I586>0,'Blnct AR'!I586,0)+IF('Blnct AR'!I695>0,'Blnct AR'!I695,0)+IF('Blnct AR'!I924>0,'Blnct AR'!I924,0)+IF('Blnct AR'!I946>0,'Blnct AR'!I946,0)+IF('Blnct AR'!I952>0,'Blnct AR'!I952,0)+IF('Blnct AR'!I1037>0,'Blnct AR'!I1037,0)+IF('Blnct AR'!I1047>0,'Blnct AR'!I1047,0)+IF('Blnct AR'!I1063>0,'Blnct AR'!I1063,0+IF('Blnct AR'!I1066>0,'Blnct AR'!I1066,0))+IF('Blnct AR'!I1070>0,'Blnct AR'!I1070,0)+IF('Blnct AR'!I1079>0,'Blnct AR'!I1079,0)+IF('Blnct AR'!I1081>0,'Blnct AR'!I1081,0)+IF('Blnct AR'!I1136>0,'Blnct AR'!I1136,0)+IF('Blnct AR'!I1160>0,'Blnct AR'!I1160,0)+IF('Blnct AR'!I1182>0,'Blnct AR'!I1182,0)+IF('Blnct AR'!I1214>0,'Blnct AR'!I1214,0)+IF('Blnct AR'!I1219>0,'Blnct AR'!I1219,0)+IF('Blnct AR'!I1242>0,'Blnct AR'!I1242,0) -> 2.2833184e+08 | G15: 0
B16: Fluxo de caixa antes da rubrica extraordinária | F16: =SUM(F14:F15) -> 3.0936981e+08 | G16: =SUM(G14:G15) -> 1072415
B18: Caixa proveniente das atividades operacionais | F18: =F12-F16 -> -3.0936981e+08 | G18: =G16+G12 -> 1072415
B19: Fluxo de caixa das atividaddes de investimento
B20: Recebimentos provenientes de: | F20: =-'Blnct AR'!I1537 -> 18842444 | G20: 100000
B21: Imobilizações corpóreas | F21: =-(IF('Blnct AR'!I1555<>0,'Blnct AR'!I1555,0)+IF('Blnct AR'!I1557<>0,'Blnct AR'!I1557,0)+IF('Blnct AR'!I1561<>0,'Blnct AR'!I1561,0)+IF('Blnct AR'!I1564<>0,'Blnct AR'!I1564,0)+IF('Blnct AR'!I1567<>0,'Blnct AR'!I1567,0)) -> 1309804.4 | G21: 0
B22: Imobilizações incorpóreas
B23: Investimentos financeiros
B24: Subsídios a investimento
B25: Juros e proveitos similares
B26: Dividendos ou lucros recebidos | F26: =-'Blnct AR'!I2194 -> -22179622 | G26: 0
B28: Pagamentos respeitantes a: | F28: =SUM(F20:F27) -> -2027373.4 | G28: =SUM(G20:G27) -> 100000
B29: Imobilizações corpóreas
B30: Imobilizações incorpóreas
B31: Investimentos financeiros
B32: Subsídios a investimento
B34: Fluxo de caixa antes da rubrica extraordinária
B37: Passivo não Corrente
B38: Empréstimos de Médio e Longo Prazo | E38: 15 | F38: =-IF('Blnct AR'!I1014<0,'Blnct AR'!I1014,0)+IF('Blnct AR'!I1019<0,'Blnct AR'!I1019,0)+IF('Blnct AR'!I1026<0,'Blnct AR'!I1026,0)+IF('Blnct AR'!I1029<0,'Blnct AR'!I1029,0) -> 0 | G38: 5427601
B39: ='Blnct AR'!D1451 -> Provisões p/ outros riscos e encargos | E39: 18 | F39: =-(IF('Blnct AR'!I1419<0,'Blnct AR'!I1419,0)+IF('Blnct AR'!I1441<0,'Blnct AR'!I1441,0)) -> 2919625.5 | G39: 35000
D40: Total do Passivo não Corrente | F40: =SUM(F38:F39) -> 2919625.5 | G40: =SUM(G38:G39) -> 5462601
B42: Passivo Corrente
B43: Contas a Pagar | E43: 19 | F43: =-(IF('Blnct AR'!I389<0,'Blnct AR'!I389,0)+IF('Blnct AR'!I541<0,'Blnct AR'!I541,0)+IF('Blnct AR'!I522<0,'Blnct AR'!I522,0)+IF('Blnct AR'!I553<0,'Blnct AR'!I553,0)+IF('Blnct AR'!I574<0,'Blnct AR'!I574,0)+IF('Blnct AR'!I586<0,'Blnct AR'!I586,0)+IF('Blnct AR'!I695<0,'Blnct AR'!I695,0)+IF('Blnct AR'!I924<0,'Blnct AR'!I924,0)+IF('Blnct AR'!I946<0,'Blnct AR'!I946,0)+IF('Blnct AR'!I952<0,'Blnct AR'!I952,0)+IF('Blnct AR'!I1037<0,'Blnct AR'!I1037,0)+IF('Blnct AR'!I1047<0,'Blnct AR'!I1047,0)+IF('Blnct AR'!I1063<0,'Blnct AR'!I1063,0+IF('Blnct AR'!I1066<0,'Blnct AR'!I1066,0))+IF('Blnct AR'!I1070<0,'Blnct AR'!I1070,0)+IF('Blnct AR'!I1079<0,'Blnct AR'!I1079,0)+IF('Blnct AR'!I1081<0,'Blnct AR'!I1081,0)+IF('Blnct AR'!I1136<0,'Blnct AR'!I1136,0)+IF('Blnct AR'!I1160<0,'Blnct AR'!I1160,0)+IF('Blnct AR'!I1182<0,'Blnct AR'!I1182,0)+IF('Blnct AR'!I1214<0,'Blnct AR'!I1214,0)+IF('Blnct AR'!I1219<0,'Blnct AR'!I1219,0)+IF('Blnct AR'!I1242<0,'Blnct AR'!I1242,0)) -> 3.8281372e+08 | G43: 2198278
B44: Empréstimos de Curto Prazo | E44: 20 | F44: =IF('Blnct AR'!I1009<0,'Blnct AR'!I1009,0) -> 0 | G44: 0
B45: Outros Passivos Correntes | E45: 21 | F45: =-(IF('Blnct AR'!I1245<0,'Blnct AR'!I1245,0)+IF('Blnct AR'!I1267<0,'Blnct AR'!I1267,0)+IF('Blnct AR'!I1280<0,'Blnct AR'!I1280,0)+IF('Blnct AR'!I1284<0,'Blnct AR'!I1284,0)+IF('Blnct AR'!I1294<0,'Blnct AR'!I1294,0)+IF('Blnct AR'!I1302<0,'Blnct AR'!I1302,0)+IF('Blnct AR'!I1309<0,'Blnct AR'!I1309,0)+IF('Blnct AR'!I1321<0,'Blnct AR'!I1321,0)+IF('Blnct AR'!I1419<0,'Blnct AR'!I1419,0)) -> 14592008 | G45: 0
D46: Total do Passivo Corrente | F46: =SUM(F43:F45) -> 3.9740573e+08 | G46: =SUM(G43:G45) -> 2198278
B48: TOTAL DO PASSIVO | F48: =F40+F46 -> 4.0032535e+08 | G48: =G40+G46 -> 7660879
B50: TOTAL DO CAPITAL PRÓPRIO E PASSIVO | F50: =F35+F48 -> 4.0032535e+08 | G50: =G35+G48 -> 7660879
